Workbook
Name Beg_Bal: #REF!
Name Data: #REF!
Name End_Bal: #REF!
Name Extra_Pay: #REF!
Name Full_Print: #REF!
Name Header_Row: ROW(#REF!)
Name Int: #REF!
Name Interest_Rate: #REF!
Name Last_Row: IF(Values_Entered,Header_Row+Number_of_Payments,Header_Row)
Name Loan_Amount: #REF!
Name Loan_Start: #REF!
Name Loan_Years: #REF!
Name Num_Pmt_Per_Year: #REF!
Name Number_of_Payments: MATCH(0.01,End_Bal,-1)+1
Name Pay_Date: #REF!
Name Pay_Num: #REF!
Name Payment_Date: DATE(YEAR(Loan_Start),MONTH(Loan_Start)+payment_number,DAY(Loan_Start))
Name Princ: #REF!
Name Print_Area_Reset: OFFSET(Full_Print,0,0,Last_Row)
Name Sched_Pay: #REF!
Name Scheduled_Extra_Payments: #REF!
Name Scheduled_Interest_Rate: #REF!
Name Scheduled_Monthly_Payment: #REF!
Name Total_Interest: #REF!
Name Total_Pay: #REF!
Name Total_Payment: scheduled_payment+extra_payment
Name Values_Entered: IF(Loan_Amount*Interest_Rate*Loan_Years*Loan_Start>0,1,0)
Name Versements_supplémentaires_facultatifs: #REF!
Name Payment_Date: DATE(YEAR([0]!Loan_Start),MONTH([0]!Loan_Start)+payment_number,DAY([0]!Loan_Start))
Name Total_Payment: scheduled_payment+extra_payment
Name Payment_Date: DATE(YEAR(Loan_Start),MONTH(Loan_Start)+payment_number,DAY(Loan_Start))
Name Total_Payment: scheduled_payment+extra_payment

Sheet Consolidation
A1: Consolidation ******
A3: Date à préciser
A6: Support | B6: ISIN & DIC | C6: Contrat 1 | D6: Contrat 2 | E6: Contrat 3 | F6: Contrat 4 | G6: Contrat 5 | H6: Contrat 6 | I6: Contrat 7 | J6: Contrat 8 | K6: Contrat 9 | L6: Contrat 10 | M6: Contrat 11 | N6: Contrat 12 | O6: Contrat 13 | P6: Contrat 14 | Q6: Contrat 15 | R6: Contrat 16 | S6: Contrat 17 | T6: TOTAL | V6: Risque / 7 | W6: Calcul SRI | X6: Dernière Valeur Liquidative | Z6: Mouvements en cours
C7: =C8+C139+C230+C311+C194+C455+C173+C100 | D7: =D8+D139+D230+D311+D194+D455+D173+D100 | E7: =E8+E139+E230+E311+E194+E455+E173+E100 | F7: =F8+F139+F230+F311+F194+F455+F173+F100 | G7: =G8+G139+G230+G311+G194+G455+G173+G100 | H7: =H8+H139+H230+H311+H194+H455+H173+H100 | I7: =I8+I139+I230+I311+I194+I455+I173+I100 | J7: =J8+J139+J230+J311+J194+J455+J173+J100 | ... S7: =S8+S139+S230+S311+S194+S455+S173+S100 | T7: =SUM(C7:S7) | U7: =+U8+U139+U194+U230+U311+U455+U100+U173 | V7: =W7/T7 | W7: =SUM(W8:W460)
A8: Fonds prudents | C8: =SUM(C9,C23,C43) | D8: =SUM(D9,D23,D43) | E8: =SUM(E9,E23,E43) | F8: =SUM(F9,F23,F43) | G8: =SUM(G9,G23,G43) | H8: =SUM(H9,H23,H43) | I8: =SUM(I9,I23,I43) | J8: =SUM(J9,J23,J43) | ... S8: =SUM(S9,S23,S43) | T8: =SUM(C8:S8) | U8: =U9+U23+U43
A9: Fonds en euro garanti | C9: =SUM(C10:C22) | D9: =SUM(D10:D22) | E9: =SUM(E10:E22) | F9: =SUM(F10:F22) | G9: =SUM(G10:G22) | H9: =SUM(H10:H22) | I9: =SUM(I10:I22) | J9: =SUM(J10:J22) | ... S9: =SUM(S10:S22) | T9: =SUM(C9:S9) | U9: =SUM(U10:U22)
A10: Fonds en euro | B10: / | T10: =SUM(C10:S10) | U10: =T10/T$7 | V10: 1 | W10: =T10*V10
A11: Fonds en euro CARDIF Lux | B11: / | T11: =SUM(C11:S11) | U11: =T11/T$7 | V11: 1 | W11: =T11*V11
A12: Actif Général Generali Vie | B12: / | T12: =SUM(C12:S12) | U12: =T12/T$7 | V12: 1 | W12: =T12*V12
A13: Allianz Fonds Euros | B13: / | T13: =SUM(C13:S13) | U13: =T13/T$7 | V13: 1 | W13: =T13*V13
A14: Fonds en euro Generali Luxembourg | B14: / | T14: =SUM(C14:S14) | U14: =T14/T$7 | V14: 1 | W14: =T14*V14
A15: Apicil Euro Garanti | B15: / | T15: =SUM(C15:S15) | U15: =T15/T$7 | V15: 1 | W15: =T15*V15
A16: Coralis Opportunité | B16: / | T16: =SUM(C16:S16) | U16: =T16/T$7 | V16: 1 | W16: =T16*V16
T17: =SUM(C17:S17) | U17: =T17/T$7 | V17: 1 | W17: =T17*V17
T18: =SUM(C18:S18) | U18: =T18/T$7 | V18: 1 | W18: =T18*V18
T19: =SUM(C19:S19) | U19: =T19/T$7 | V19: 1 | W19: =T19*V19
T20: =SUM(C20:S20) | U20: =T20/T$7 | V20: 1 | W20: =T20*V20
T21: =SUM(C21:S21) | U21: =T21/T$7 | V21: 1 | W21: =T21*V21
T22: =SUM(C22:S22) | U22: =T22/T$7 | V22: 1 | W22: =T22*V22
A23: Fonds monétaires | C23: =SUM(C24:C42) | D23: =SUM(D24:D42) | E23: =SUM(E24:E42) | F23: =SUM(F24:F42) | G23: =SUM(G24:G42) | H23: =SUM(H24:H42) | I23: =SUM(I24:I42) | J23: =SUM(J24:J42) | ... S23: =SUM(S24:S42) | T23: =SUM(C23:S23) | U23: =SUM(U24:U42)
A24: Solde espèces | B24: / | T24: =SUM(C24:S24) | U24: =T24/T$7 | V24: 1 | W24: =T24*V24
A25: BNP Paribas Insticash EUR 1D Short Terme | B25: LU0094219127 | T25: =SUM(C25:S25) | U25: =T25/T$7 | V25: 1 | W25: =T25*V25
A26: BNP Paribas Mois ISR | B26: FR0007009808 | T26: =SUM(C26:S26) | U26: =T26/T$7 | V26: 1 | W26: =T26*V26
A27: Amundi Funds Cash EUR A2 C | B27: LU0568620560 | T27: =SUM(C27:S27) | U27: =T27/T$7 | V27: 1 | W27: =T27*V27
A28: Allianz Securicash SRI I (C) EUR | B28: FR0010017731 | T28: =SUM(C28:S28) | U28: =T28/T$7 | V28: 1 | W28: =T28*V28
A29: SG Monétaire Plus P-C | B29: FR0011362094 | T29: =SUM(C29:S29) | U29: =T29/T$7 | V29: 1 | W29: =T29*V29
A30: SLF (F) Bond ESG 6M | B30: FR0010914358 | T30: =SUM(C30:S30) | U30: =T30/T$7 | V30: 1 | W30: =T30*V30
A31: Generali trésorerie B EUR C | B31: FR0010233726 | T31: =SUM(C31:S31) | U31: =T31/T$7 | V31: 1 | W31: =T31*V31
A32: Apicil Trésorerie P | B32: FR0013328317 | T32: =SUM(C32:S32) | U32: =T32/T$7 | V32: 1 | W32: =T32*V32
A33: AXA Court Terme AC | B33: FR0000288946 | T33: =SUM(C33:S33) | U33: =T33/T$7 | V33: 1 | W33: =T33*V33
A34: Liquidités fonds de fonds | B34: / | T34: =SUM(C34:S34) | U34: =T34/T$7 | V34: 1 | W34: =T34*V34
A35: CIC Union Plus EUR | B35: / | T35: =SUM(C35:S35) | U35: =T35/T$7 | V35: 1 | W35: =T35*V35
A36: Union + TC CAP | B36: / | T36: =SUM(C36:S36) | U36: =T36/T$7 | V36: 1 | W36: =T36*V36
T37: =SUM(C37:S37) | U37: =T37/T$7 | V37: 1 | W37: =T37*V37
T38: =SUM(C38:S38) | U38: =T38/T$7 | V38: 1 | W38: =T38*V38
T39: =SUM(C39:S39) | U39: =T39/T$7 | V39: 1 | W39: =T39*V39
T40: =SUM(C40:S40) | U40: =T40/T$7 | V40: 1 | W40: =T40*V40
T41: =SUM(C41:S41) | U41: =T41/T$7 | V41: 1 | W41: =T41*V41
T42: =SUM(C42:S42) | U42: =T42/T$7 | V42: 1 | W42: =T42*V42
A43: Fonds obligataires | C43: =SUM(C44:C99) | D43: =SUM(D44:D99) | E43: =SUM(E44:E99) | F43: =SUM(F44:F99) | G43: =SUM(G44:G99) | H43: =SUM(H44:H99) | I43: =SUM(I44:I99) | J43: =SUM(J44:J99) | ... S43: =SUM(S44:S99) | T43: =SUM(C43:S43) | U43: =SUM(U44:U99)
A44: IVO Emerging Markets Corporate Debt EUR-I | B44: LU1165637460 | T44: =SUM(C44:S44) | U44: =T44/T$7 | V44: 2 | W44: =T44*V44
A45: IVO Emerging Markets Corporate Debt EUR-R | B45: LU1165644672 | T45: =SUM(C45:S45) | U45: =T45/T$7 | V45: 3 | W45: =T45*V45
A46: IVO Emerging Markets Coporate Debt Short Duration SRI EUR | B46: LU2061939646 | T46: =SUM(C46:S46) | U46: =T46/T$7 | V46: 2 | W46: =T46*V46
A47: Ivo Emerging Markets Corporate Debt Short Duration SRI Z | B47: LU2061940222 | T47: =SUM(C47:S47) | U47: =T47/T$7 | V47: 2 | W47: =T47*V47
A48: IVO Emerging Markets Corporate Debt Short Duration SRI R | B48: LU2061939729 | T48: =SUM(C48:S48) | U48: =T48/T$7 | V48: 2 | W48: =T48*V48
A49: IVO IG 2030 I | B49: FR001400SJC8 | T49: =SUM(C49:S49) | U49: =T49/T$7 | V49: 2 | W49: =T49*V49
A50: IVO IG 2030 R | B50: FR001400SJA2 | T50: =SUM(C50:S50) | U50: =T50/T$7 | V50: 2 | W50: =T50*V50
A51: IVO 2028 I | B51: FR001400BJV4 | T51: =SUM(C51:S51) | U51: =T51/T$7 | V51: 2 | W51: =T51*V51
A52: IVO 2028 R | B52: FR001400BJT8 | T52: =SUM(C52:S52) | U52: =T52/T$7 | V52: 2 | W52: =T52*V52
A53: Sycoyield 2030 RC | B53: FR001400MCQ6 | T53: =SUM(C53:S53) | U53: =T53/T$7 | V53: 2 | W53: =T53*V53
A54: Sycoyield 2032 RC | B54: FR0014010IG3 | T54: =SUM(C54:S54) | U54: =T54/T$7 | V54: 2 | W54: =T54*V54
A55: Sycoyield 2026 IC | B55: FR001400A6X2 | T55: =SUM(C55:S55) | U55: =T55/T$7 | V55: 2 | W55: =T55*V55
... A81: Omnibond R | B81: FR0011147594 | T81: =SUM(C81:S81) | U81: =T81/T$7 | V81: 2 | W81: =T81*V81
T82: =SUM(C82:S82) | U82: =T82/T$7 | W82: =T82*V82
T83: =SUM(C83:S83) | U83: =T83/T$7 | W83: =T83*V83
T84: =SUM(C84:S84) | U84: =T84/T$7 | W84: =T84*V84
T85: =SUM(C85:S85) | U85: =T85/T$7 | W85: =T85*V85
T86: =SUM(C86:S86) | U86: =T86/T$7 | W86: =T86*V86
T87: =SUM(C87:S87) | U87: =T87/T$7 | W87: =T87*V87
T88: =SUM(C88:S88) | U88: =T88/T$7 | W88: =T88*V88
T89: =SUM(C89:S89) | U89: =T89/T$7 | W89: =T89*V89
T90: =SUM(C90:S90) | U90: =T90/T$7 | W90: =T90*V90
T91: =SUM(C91:S91) | U91: =T91/T$7 | W91: =T91*V91
T92: =SUM(C92:S92) | U92: =T92/T$7 | W92: =T92*V92
T93: =SUM(C93:S93) | U93: =T93/T$7 | W93: =T93*V93
... T99: =SUM(C99:S99) | U99: =T99/T$7 | W99: =T99*V99
A100: Hedge Fund | C100: =SUM(C101:C138) | D100: =SUM(D101:D138) | E100: =SUM(E101:E138) | F100: =SUM(F101:F138) | G100: =SUM(G101:G138) | H100: =SUM(H101:H138) | I100: =SUM(I101:I138) | J100: =SUM(J101:J138) | ... S100: =SUM(S101:S138) | T100: =SUM(C100:S100) | U100: =SUM(U101:U138)
A101: Helium Performance A EUR | B101: LU0912261970 | T101: =SUM(C101:S101) | U101: =T101/T$7 | V101: 2 | W101: =T101*V101
A102: Helium Sélection A EUR | B102: LU1112771255 | T102: =SUM(C102:S102) | U102: =T102/T$7 | V102: 2 | W102: =T102*V102
A103: Helium Sélection B clean EUR | B103: LU1734046979 | T103: =SUM(C103:S103) | U103: =T103/T$7 | V103: 2 | W103: =T103*V103
A104: Helium Fund B EUR | B104: LU0912261624 | T104: =SUM(C104:S104) | U104: =T104/T$7 | V104: 2 | W104: =T104*V104
A105: Helium Global S EUR | B105: IE000F31HWX5 | T105: =SUM(C105:S105) | U105: =T105/T$7 | V105: 5 | W105: =T105*V105
A106: Helium Selection B-EUR | B106: LU1112771503 | T106: =SUM(C106:S106) | U106: =T106/T$7 | V106: 2 | W106: =T106*V106
A107: Helium Performance B EUR | B107: LU0912262275 | T107: =SUM(C107:S107) | U107: =T107/T$7 | V107: 2 | W107: =T107*V107
A108: Cypanga Diversified Portfolio A | B108: LU0672299830 | T108: =SUM(C108:S108) | U108: =T108/T$7 | V108: 4 | W108: =T108*V108
A109: Tikehau International Cross Assets R Acc EUR | B109: LU2147879543 | T109: =SUM(C109:S109) | U109: =T109/T$7 | V109: 3 | W109: =T109*V109
A110: H2O Adagio I | B110: FR0010929794 | T110: =SUM(C110:S110) | U110: =T110/T$7 | V110: 3 | W110: =T110*V110
A111: H2O Adagio NC | B111: FR0013186772 | T111: =SUM(C111:S111) | U111: =T111/T$7 | V111: 3 | W111: =T111*V111
A112: H2O Adagio RC | B112: FR0010923359 | T112: =SUM(C112:S112) | U112: =T112/T$7 | V112: 3 | W112: =T112*V112
... A122: JPMorgan Funds Europe Equity Absolute Alpha fund A | B122: LU1001747408 | T122: =SUM(C122:S122) | U122: =T122/T$7 | V122: 3 | W122: =T122*V122
T123: =SUM(C123:S123) | U123: =T123/T$7 | W123: =T123*V123
T124: =SUM(C124:S124) | U124: =T124/T$7 | W124: =T124*V124
T125: =SUM(C125:S125) | U125: =T125/T$7 | W125: =T125*V125
T126: =SUM(C126:S126) | U126: =T126/T$7 | W126: =T126*V126
T127: =SUM(C127:S127) | U127: =T127/T$7 | W127: =T127*V127
T128: =SUM(C128:S128) | U128: =T128/T$7 | W128: =T128*V128
T129: =SUM(C129:S129) | U129: =T129/T$7 | W129: =T129*V129
T130: =SUM(C130:S130) | U130: =T130/T$7 | W130: =T130*V130
T131: =SUM(C131:S131) | U131: =T131/T$7 | W131: =T131*V131
T132: =SUM(C132:S132) | U132: =T132/T$7 | W132: =T132*V132
T133: =SUM(C133:S133) | U133: =T133/T$7 | W133: =T133*V133
T134: =SUM(C134:S134) | U134: =T134/T$7 | W134: =T134*V134
... T138: =SUM(C138:S138) | U138: =T138/T$7 | W138: =T138*V138
A139: Immobilier | C139: =SUM(C140:C172) | D139: =SUM(D140:D172) | E139: =SUM(E140:E172) | F139: =SUM(F140:F172) | G139: =SUM(G140:G172) | H139: =SUM(H140:H172) | I139: =SUM(I140:I172) | J139: =SUM(J140:J172) | ... S139: =SUM(S140:S172) | T139: =SUM(C139:S139) | U139: =SUM(U140:U172)
A140: BK OPCI A | B140: FR0013144094 | T140: =SUM(C140:S140) | U140: =T140/T$7 | V140: 4 | W140: =T140*V140
A141: BK OPCI B | B141: FR0013182664 | T141: =SUM(C141:S141) | U141: =T141/T$7 | V141: 4 | W141: =T141*V141
A142: FIC PPG Retail | B142: ALZ013324662 | T142: =SUM(C142:S142) | U142: =T142/T$7 | V142: 4 | W142: =T142*V142
A143: OPPCI PPG Retail A | B143: FR0013324662 | T143: =SUM(C143:S143) | U143: =T143/T$7 | V143: 4 | W143: =T143*V143
A144: OPPCI PPG Retail B | B144: FR0013324670 | T144: =SUM(C144:S144) | U144: =T144/T$7 | V144: 4 | W144: =T144*V144
A145: PPG Croissance A | B145: FR0013265683 | T145: =SUM(C145:S145) | U145: =T145/T$7 | V145: 4 | W145: =T145*V145
...

Sheet Calendrier de sortie
A1: Consolidation ******
A3: Date à préciser
A6: Support | B6: ISIN & DIC | C6: Date d'investissement | D6: Prochain ordre — entrée | E6: Prochain ordre — sortie | F6: Prochaine réception du cash | G6: Pénalité de sortie
A8: Fonds prudents
A9: Fonds en euro garanti
A10: Fonds en euro | B10: / | D10: — | E10: — | F10: — | G10: —
A11: Fonds en euro CARDIF Lux | B11: / | D11: — | E11: — | F11: — | G11: —
A12: Actif Général Generali Vie | B12: / | D12: — | E12: — | F12: — | G12: —
A13: Allianz Fonds Euros | B13: / | D13: — | E13: — | F13: — | G13: —
A14: Fonds en euro Generali Luxembourg | B14: / | D14: — | E14: — | F14: — | G14: —
A15: Apicil Euro Garanti | B15: / | D15: — | E15: — | F15: — | G15: —
A16: Coralis Opportunité | B16: / | D16: — | E16: — | F16: — | G16: —
A23: Fonds monétaires
A24: Solde espèces | B24: / | D24: — | E24: — | F24: — | G24: —
A25: BNP Paribas Insticash EUR 1D Short Terme | B25: LU0094219127 | D25: — | E25: — | F25: — | G25: —
A26: BNP Paribas Mois ISR | B26: FR0007009808 | D26: — | E26: — | F26: — | G26: —
A27: Amundi Funds Cash EUR A2 C | B27: LU0568620560 | D27: — | E27: — | F27: — | G27: —
A28: Allianz Securicash SRI I (C) EUR | B28: FR0010017731 | D28: — | E28: — | F28: — | G28: —
A29: SG Monétaire Plus P-C | B29: FR0011362094 | D29: — | E29: — | F29: — | G29: —
A30: SLF (F) Bond ESG 6M | B30: FR0010914358 | D30: — | E30: — | F30: — | G30: —
A31: Generali trésorerie B EUR C | B31: FR0010233726 | D31: — | E31: — | F31: — | G31: —
A32: Apicil Trésorerie P | B32: FR0013328317 | D32: — | E32: — | F32: — | G32: —
A33: AXA Court Terme AC | B33: FR0000288946 | D33: — | E33: — | F33: — | G33: —
A34: Liquidités fonds de fonds | B34: / | D34: — | E34: — | F34: — | G34: —
A35: CIC Union Plus EUR | B35: / | D35: — | E35: — | F35: — | G35: —
A36: Union + TC CAP | B36: / | D36: — | E36: — | F36: — | G36: —
A43: Fonds obligataires
A44: IVO Emerging Markets Corporate Debt EUR-I | B44: LU1165637460 | D44: — | E44: — | F44: — | G44: —
A45: IVO Emerging Markets Corporate Debt EUR-R | B45: LU1165644672 | D45: — | E45: — | F45: — | G45: —
A46: IVO Emerging Markets Coporate Debt Short Duration SRI EUR | B46: LU2061939646 | D46: — | E46: — | F46: — | G46: —
A47: Ivo Emerging Markets Corporate Debt Short Duration SRI Z | B47: LU2061940222 | D47: — | E47: — | F47: — | G47: —
A48: IVO Emerging Markets Corporate Debt Short Duration SRI R | B48: LU2061939729 | D48: — | E48: — | F48: — | G48: —
A49: IVO IG 2030 I | B49: FR001400SJC8 | D49: — | E49: — | F49: — | G49: —
A50: IVO IG 2030 R | B50: FR001400SJA2 | D50: — | E50: — | F50: — | G50: —
A51: IVO 2028 I | B51: FR001400BJV4 | D51: — | E51: — | F51: — | G51: —
A52: IVO 2028 R | B52: FR001400BJT8 | D52: — | E52: — | F52: — | G52: —
A53: Sycoyield 2030 RC | B53: FR001400MCQ6 | D53: — | E53: — | F53: — | G53: —
A54: Sycoyield 2032 RC | B54: FR0014010IG3 | D54: — | E54: — | F54: — | G54: —
A55: Sycoyield 2026 IC | B55: FR001400A6X2 | D55: — | E55: — | F55: — | G55: —
... A81: Omnibond R | B81: FR0011147594 | D81: — | E81: — | F81: — | G81: —
A100: Hedge Fund
A101: Helium Performance A EUR | B101: LU0912261970 | D101: =IF(H101=0,"Calendrier non disponible pour ce fonds — contacter la société de gestion.",IF(I101="","Calendrier connu jusqu'au "&TEXT(K101,"dd/mm/yyyy")&" — demander le calendrier à jour.","Cut-off : "&TEXT(I101,"dd/mm/yyyy")&" | VL : "&TEXT(J101,"dd/mm/yyyy"))) | E101: =IF(L101=0,"Calendrier non disponible pour ce fonds — contacter la société de gestion.",IF(M101="","Calendrier connu jusqu'au "&TEXT(P101,"dd/mm/yyyy")&" — demander le calendrier à jour.","Cut-off : "&TEXT(M101,"dd/mm/yyyy")&" | VL : "&TEXT(N101,"dd/mm/yyyy"))) | F101: =IF(L101=0,"Calendrier non disponible pour ce fonds.",IF(M101="","Calendrier connu jusqu'au "&TEXT(P101,"dd/mm/yyyy")&".",IF(O101="","Non précisé dans le calendrier pour cette échéance.","Réception : "&TEXT(O101,"dd/mm/yyyy")&" (suite au rachat du "&TEXT(N101,"dd/mm/yyyy")&")"))) | G101: =_xlfn.IFS(S101="aucune","Aucune pénalité de sortie."&IF(T101<>""," ("&T101&")",""),S101="manuel","⚠️ À VÉRIFIER MANUELLEMENT : "&T101,S101="inconnue","Pénalité non renseignée — vérifier la notice / DICI du fonds.",$C101="","Saisir une date d'investissement pour statuer sur la pénalité.",Q101="FUTUR","Date d'investissement postérieure à aujourd'hui — vérifier la saisie.",AD101>0,"⚠️ CONCERNÉ : pénalité de "&AD101&"% (détention "&Q101&" mois). "&T101,TRUE,"Non concerné (détention "&Q101&" mois). "&T101) | H101: =COUNTIFS(BDD_Calendrier!$A$2:$A$616,$B101,BDD_Calendrier!$C$2:$C$616,"Souscription") | I101: =IF(H101=0,"",IFERROR(_xlfn.MINIFS(BDD_Calendrier!$D$2:$D$616,BDD_Calendrier!$A$2:$A$616,$B101,BDD_Calendrier!$C$2:$C$616,"Souscription",BDD_Calendrier!$D$2:$D$616,">="&TODAY()),"")) | J101: =IF(I101="","",IFERROR(INDEX(BDD_Calendrier!$E$2:$E$616,MATCH($B101&"|Souscription|"&TEXT(I101,"yyyy-mm-dd"),BDD_Calendrier!$I$2:$I$616,0)),"")) | K101: =IF(H101=0,"",_xlfn.MAXIFS(BDD_Calendrier!$D$2:$D$616,BDD_Calendrier!$A$2:$A$616,$B101,BDD_Calendrier!$C$2:$C$616,"Souscription")) | L101: =COUNTIFS(BDD_Calendrier!$A$2:$A$616,$B101,BDD_Calendrier!$C$2:$C$616,"Rachat") | M101: =IF(L101=0,"",IFERROR(_xlfn.MINIFS(BDD_Calendrier!$D$2:$D$616,BDD_Calendrier!$A$2:$A$616,$B101,BDD_Calendrier!$C$2:$C$616,"Rachat",BDD_Calendrier!$D$2:$D$616,">="&TODAY()),"")) | N101: =IF(M101="","",IFERROR(INDEX(BDD_Calendrier!$E$2:$E$616,MATCH($B101&"|Rachat|"&TEXT(M101,"yyyy-mm-dd"),BDD_Calendrier!$I$2:$I$616,0)),"")) | O101: =IF(M101="","",IFERROR(INDEX(BDD_Calendrier!$H$2:$H$616,MATCH($B101&"|Rachat|"&TEXT(M101,"yyyy-mm-dd"),BDD_Calendrier!$I$2:$I$616,0)),"")) | P101: =IF(L101=0,"",_xlfn.MAXIFS(BDD_Calendrier!$D$2:$D$616,BDD_Calendrier!$A$2:$A$616,$B101,BDD_Calendrier!$C$2:$C$616,"Rachat")) | Q101: =IF($C101="","",IF($C101>TODAY(),"FUTUR",DATEDIF($C101,TODAY(),"m"))) | R101: =COUNTIF(BDD_Penalites!$A$2:$A$130,$B101) | S101: =IF(R101=0,"inconnue",INDEX(BDD_Penalites!$C$2:$C$130,MATCH($B101,BDD_Penalites!$A$2:$A$130,0))) | T101: =IF(R101=0,"",INDEX(BDD_Penalites!$M$2:$M$130,MATCH($B101,BDD_Penalites!$A$2:$A$130,0))) | U101: =IF(R101=0,0,INDEX(BDD_Penalites!$D$2:$D$130,MATCH($B101,BDD_Penalites!$A$2:$A$130,0))) | V101: =IF(R101=0,0,INDEX(BDD_Penalites!$E$2:$E$130,MATCH($B101,BDD_Penalites!$A$2:$A$130,0))) | W101: =IF(R101=0,0,INDEX(BDD_Penalites!$F$2:$F$130,MATCH($B101,BDD_Penalites!$A$2:$A$130,0))) | X101: =IF(R101=0,0,INDEX(BDD_Penalites!$G$2:$G$130,MATCH($B101,BDD_Penalites!$A$2:$A$130,0))) | Y101: =IF(R101=0,0,INDEX(BDD_Penalites!$H$2:$H$130,MATCH($B101,BDD_Penalites!$A$2:$A$130,0))) | Z101: =IF(R101=0,0,INDEX(BDD_Penalites!$I$2:$I$130,MATCH($B101,BDD_Penalites!$A$2:$A$130,0))) | AA101: =IF(R101=0,0,INDEX(BDD_Penalites!$J$2:$J$130,MATCH($B101,BDD_Penalites!$A$2:$A$130,0))) | AB101: =IF(R101=0,0,INDEX(BDD_Penalites!$K$2:$K$130,MATCH($B101,BDD_Penalites!$A$2:$A$130,0))) | AC101: =IF(R101=0,0,INDEX(BDD_Penalites!$L$2:$L$130,MATCH($B101,BDD_Penalites!$A$2:$A$130,0))) | AD101: =IF(OR($C101="",Q101="FUTUR"),"",_xlfn.IFS(Q101<U101,V101,Q101<W101,X101,Q101<Y101,Z101,Q101<AA101,AB101,TRUE,AC101))
A102: Helium Sélection A EUR | B102: LU1112771255 | D102: =IF(H102=0,"Calendrier non disponible pour ce fonds — contacter la société de gestion.",IF(I102="","Calendrier connu jusqu'au "&TEXT(K102,"dd/mm/yyyy")&" — demander le calendrier à jour.","Cut-off : "&TEXT(I102,"dd/mm/yyyy")&" | VL : "&TEXT(J102,"dd/mm/yyyy"))) | E102: =IF(L102=0,"Calendrier non disponible pour ce fonds — contacter la société de gestion.",IF(M102="","Calendrier connu jusqu'au "&TEXT(P102,"dd/mm/yyyy")&" — demander le calendrier à jour.","Cut-off : "&TEXT(M102,"dd/mm/yyyy")&" | VL : "&TEXT(N102,"dd/mm/yyyy"))) | F102: =IF(L102=0,"Calendrier non disponible pour ce fonds.",IF(M102="","Calendrier connu jusqu'au "&TEXT(P102,"dd/mm/yyyy")&".",IF(O102="","Non précisé dans le calendrier pour cette échéance.","Réception : "&TEXT(O102,"dd/mm/yyyy")&" (suite au rachat du "&TEXT(N102,"dd/mm/yyyy")&")"))) | G102: =_xlfn.IFS(S102="aucune","Aucune pénalité de sortie."&IF(T102<>""," ("&T102&")",""),S102="manuel","⚠️ À VÉRIFIER MANUELLEMENT : "&T102,S102="inconnue","Pénalité non renseignée — vérifier la notice / DICI du fonds.",$C102="","Saisir une date d'investissement pour statuer sur la pénalité.",Q102="FUTUR","Date d'investissement postérieure à aujourd'hui — vérifier la saisie.",AD102>0,"⚠️ CONCERNÉ : pénalité de "&AD102&"% (détention "&Q102&" mois). "&T102,TRUE,"Non concerné (détention "&Q102&" mois). "&T102) | H102: =COUNTIFS(BDD_Calendrier!$A$2:$A$616,$B102,BDD_Calendrier!$C$2:$C$616,"Souscription") | I102: =IF(H102=0,"",IFERROR(_xlfn.MINIFS(BDD_Calendrier!$D$2:$D$616,BDD_Calendrier!$A$2:$A$616,$B102,BDD_Calendrier!$C$2:$C$616,"Souscription",BDD_Calendrier!$D$2:$D$616,">="&TODAY()),"")) | J102: =IF(I102="","",IFERROR(INDEX(BDD_Calendrier!$E$2:$E$616,MATCH($B102&"|Souscription|"&TEXT(I102,"yyyy-mm-dd"),BDD_Calendrier!$I$2:$I$616,0)),"")) | K102: =IF(H102=0,"",_xlfn.MAXIFS(BDD_Calendrier!$D$2:$D$616,BDD_Calendrier!$A$2:$A$616,$B102,BDD_Calendrier!$C$2:$C$616,"Souscription")) | L102: =COUNTIFS(BDD_Calendrier!$A$2:$A$616,$B102,BDD_Calendrier!$C$2:$C$616,"Rachat") | M102: =IF(L102=0,"",IFERROR(_xlfn.MINIFS(BDD_Calendrier!$D$2:$D$616,BDD_Calendrier!$A$2:$A$616,$B102,BDD_Calendrier!$C$2:$C$616,"Rachat",BDD_Calendrier!$D$2:$D$616,">="&TODAY()),"")) | N102: =IF(M102="","",IFERROR(INDEX(BDD_Calendrier!$E$2:$E$616,MATCH($B102&"|Rachat|"&TEXT(M102,"yyyy-mm-dd"),BDD_Calendrier!$I$2:$I$616,0)),"")) | O102: =IF(M102="","",IFERROR(INDEX(BDD_Calendrier!$H$2:$H$616,MATCH($B102&"|Rachat|"&TEXT(M102,"yyyy-mm-dd"),BDD_Calendrier!$I$2:$I$616,0)),"")) | P102: =IF(L102=0,"",_xlfn.MAXIFS(BDD_Calendrier!$D$2:$D$616,BDD_Calendrier!$A$2:$A$616,$B102,BDD_Calendrier!$C$2:$C$616,"Rachat")) | Q102: =IF($C102="","",IF($C102>TODAY(),"FUTUR",DATEDIF($C102,TODAY(),"m"))) | R102: =COUNTIF(BDD_Penalites!$A$2:$A$130,$B102) | S102: =IF(R102=0,"inconnue",INDEX(BDD_Penalites!$C$2:$C$130,MATCH($B102,BDD_Penalites!$A$2:$A$130,0))) | T102: =IF(R102=0,"",INDEX(BDD_Penalites!$M$2:$M$130,MATCH($B102,BDD_Penalites!$A$2:$A$130,0))) | U102: =IF(R102=0,0,INDEX(BDD_Penalites!$D$2:$D$130,MATCH($B102,BDD_Penalites!$A$2:$A$130,0))) | V102: =IF(R102=0,0,INDEX(BDD_Penalites!$E$2:$E$130,MATCH($B102,BDD_Penalites!$A$2:$A$130,0))) | W102: =IF(R102=0,0,INDEX(BDD_Penalites!$F$2:$F$130,MATCH($B102,BDD_Penalites!$A$2:$A$130,0))) | X102: =IF(R102=0,0,INDEX(BDD_Penalites!$G$2:$G$130,MATCH($B102,BDD_Penalites!$A$2:$A$130,0))) | Y102: =IF(R102=0,0,INDEX(BDD_Penalites!$H$2:$H$130,MATCH($B102,BDD_Penalites!$A$2:$A$130,0))) | Z102: =IF(R102=0,0,INDEX(BDD_Penalites!$I$2:$I$130,MATCH($B102,BDD_Penalites!$A$2:$A$130,0))) | AA102: =IF(R102=0,0,INDEX(BDD_Penalites!$J$2:$J$130,MATCH($B102,BDD_Penalites!$A$2:$A$130,0))) | AB102: =IF(R102=0,0,INDEX(BDD_Penalites!$K$2:$K$130,MATCH($B102,BDD_Penalites!$A$2:$A$130,0))) | AC102: =IF(R102=0,0,INDEX(BDD_Penalites!$L$2:$L$130,MATCH($B102,BDD_Penalites!$A$2:$A$130,0))) | AD102: =IF(OR($C102="",Q102="FUTUR"),"",_xlfn.IFS(Q102<U102,V102,Q102<W102,X102,Q102<Y102,Z102,Q102<AA102,AB102,TRUE,AC102))
A103: Helium Sélection B clean EUR | B103: LU1734046979 | D103: =IF(H103=0,"Calendrier non disponible pour ce fonds — contacter la société de gestion.",IF(I103="","Calendrier connu jusqu'au "&TEXT(K103,"dd/mm/yyyy")&" — demander le calendrier à jour.","Cut-off : "&TEXT(I103,"dd/mm/yyyy")&" | VL : "&TEXT(J103,"dd/mm/yyyy"))) | E103: =IF(L103=0,"Calendrier non disponible pour ce fonds — contacter la société de gestion.",IF(M103="","Calendrier connu jusqu'au "&TEXT(P103,"dd/mm/yyyy")&" — demander le calendrier à jour.","Cut-off : "&TEXT(M103,"dd/mm/yyyy")&" | VL : "&TEXT(N103,"dd/mm/yyyy"))) | F103: =IF(L103=0,"Calendrier non disponible pour ce fonds.",IF(M103="","Calendrier connu jusqu'au "&TEXT(P103,"dd/mm/yyyy")&".",IF(O103="","Non précisé dans le calendrier pour cette échéance.","Réception : "&TEXT(O103,"dd/mm/yyyy")&" (suite au rachat du "&TEXT(N103,"dd/mm/yyyy")&")"))) | G103: =_xlfn.IFS(S103="aucune","Aucune pénalité de sortie."&IF(T103<>""," ("&T103&")",""),S103="manuel","⚠️ À VÉRIFIER MANUELLEMENT : "&T103,S103="inconnue","Pénalité non renseignée — vérifier la notice / DICI du fonds.",$C103="","Saisir une date d'investissement pour statuer sur la pénalité.",Q103="FUTUR","Date d'investissement postérieure à aujourd'hui — vérifier la saisie.",AD103>0,"⚠️ CONCERNÉ : pénalité de "&AD103&"% (détention "&Q103&" mois). "&T103,TRUE,"Non concerné (détention "&Q103&" mois). "&T103) | H103: =COUNTIFS(BDD_Calendrier!$A$2:$A$616,$B103,BDD_Calendrier!$C$2:$C$616,"Souscription") | I103: =IF(H103=0,"",IFERROR(_xlfn.MINIFS(BDD_Calendrier!$D$2:$D$616,BDD_Calendrier!$A$2:$A$616,$B103,BDD_Calendrier!$C$2:$C$616,"Souscription",BDD_Calendrier!$D$2:$D$616,">="&TODAY()),"")) | J103: =IF(I103="","",IFERROR(INDEX(BDD_Calendrier!$E$2:$E$616,MATCH($B103&"|Souscription|"&TEXT(I103,"yyyy-mm-dd"),BDD_Calendrier!$I$2:$I$616,0)),"")) | K103: =IF(H103=0,"",_xlfn.MAXIFS(BDD_Calendrier!$D$2:$D$616,BDD_Calendrier!$A$2:$A$616,$B103,BDD_Calendrier!$C$2:$C$616,"Souscription")) | L103: =COUNTIFS(BDD_Calendrier!$A$2:$A$616,$B103,BDD_Calendrier!$C$2:$C$616,"Rachat") | M103: =IF(L103=0,"",IFERROR(_xlfn.MINIFS(BDD_Calendrier!$D$2:$D$616,BDD_Calendrier!$A$2:$A$616,$B103,BDD_Calendrier!$C$2:$C$616,"Rachat",BDD_Calendrier!$D$2:$D$616,">="&TODAY()),"")) | N103: =IF(M103="","",IFERROR(INDEX(BDD_Calendrier!$E$2:$E$616,MATCH($B103&"|Rachat|"&TEXT(M103,"yyyy-mm-dd"),BDD_Calendrier!$I$2:$I$616,0)),"")) | O103: =IF(M103="","",IFERROR(INDEX(BDD_Calendrier!$H$2:$H$616,MATCH($B103&"|Rachat|"&TEXT(M103,"yyyy-mm-dd"),BDD_Calendrier!$I$2:$I$616,0)),"")) | P103: =IF(L103=0,"",_xlfn.MAXIFS(BDD_Calendrier!$D$2:$D$616,BDD_Calendrier!$A$2:$A$616,$B103,BDD_Calendrier!$C$2:$C$616,"Rachat")) | Q103: =IF($C103="","",IF($C103>TODAY(),"FUTUR",DATEDIF($C103,TODAY(),"m"))) | R103: =COUNTIF(BDD_Penalites!$A$2:$A$130,$B103) | S103: =IF(R103=0,"inconnue",INDEX(BDD_Penalites!$C$2:$C$130,MATCH($B103,BDD_Penalites!$A$2:$A$130,0))) | T103: =IF(R103=0,"",INDEX(BDD_Penalites!$M$2:$M$130,MATCH($B103,BDD_Penalites!$A$2:$A$130,0))) | U103: =IF(R103=0,0,INDEX(BDD_Penalites!$D$2:$D$130,MATCH($B103,BDD_Penalites!$A$2:$A$130,0))) | V103: =IF(R103=0,0,INDEX(BDD_Penalites!$E$2:$E$130,MATCH($B103,BDD_Penalites!$A$2:$A$130,0))) | W103: =IF(R103=0,0,INDEX(BDD_Penalites!$F$2:$F$130,MATCH($B103,BDD_Penalites!$A$2:$A$130,0))) | X103: =IF(R103=0,0,INDEX(BDD_Penalites!$G$2:$G$130,MATCH($B103,BDD_Penalites!$A$2:$A$130,0))) | Y103: =IF(R103=0,0,INDEX(BDD_Penalites!$H$2:$H$130,MATCH($B103,BDD_Penalites!$A$2:$A$130,0))) | Z103: =IF(R103=0,0,INDEX(BDD_Penalites!$I$2:$I$130,MATCH($B103,BDD_Penalites!$A$2:$A$130,0))) | AA103: =IF(R103=0,0,INDEX(BDD_Penalites!$J$2:$J$130,MATCH($B103,BDD_Penalites!$A$2:$A$130,0))) | AB103: =IF(R103=0,0,INDEX(BDD_Penalites!$K$2:$K$130,MATCH($B103,BDD_Penalites!$A$2:$A$130,0))) | AC103: =IF(R103=0,0,INDEX(BDD_Penalites!$L$2:$L$130,MATCH($B103,BDD_Penalites!$A$2:$A$130,0))) | AD103: =IF(OR($C103="",Q103="FUTUR"),"",_xlfn.IFS(Q103<U103,V103,Q103<W103,X103,Q103<Y103,Z103,Q103<AA103,AB103,TRUE,AC103))
A104: Helium Fund B EUR | B104: LU0912261624 | D104: =IF(H104=0,"Calendrier non disponible pour ce fonds — contacter la société de gestion.",IF(I104="","Calendrier connu jusqu'au "&TEXT(K104,"dd/mm/yyyy")&" — demander le calendrier à jour.","Cut-off : "&TEXT(I104,"dd/mm/yyyy")&" | VL : "&TEXT(J104,"dd/mm/yyyy"))) | E104: =IF(L104=0,"Calendrier non disponible pour ce fonds — contacter la société de gestion.",IF(M104="","Calendrier connu jusqu'au "&TEXT(P104,"dd/mm/yyyy")&" — demander le calendrier à jour.","Cut-off : "&TEXT(M104,"dd/mm/yyyy")&" | VL : "&TEXT(N104,"dd/mm/yyyy"))) | F104: =IF(L104=0,"Calendrier non disponible pour ce fonds.",IF(M104="","Calendrier connu jusqu'au "&TEXT(P104,"dd/mm/yyyy")&".",IF(O104="","Non précisé dans le calendrier pour cette échéance.","Réception : "&TEXT(O104,"dd/mm/yyyy")&" (suite au rachat du "&TEXT(N104,"dd/mm/yyyy")&")"))) | G104: =_xlfn.IFS(S104="aucune","Aucune pénalité de sortie."&IF(T104<>""," ("&T104&")",""),S104="manuel","⚠️ À VÉRIFIER MANUELLEMENT : "&T104,S104="inconnue","Pénalité non renseignée — vérifier la notice / DICI du fonds.",$C104="","Saisir une date d'investissement pour statuer sur la pénalité.",Q104="FUTUR","Date d'investissement postérieure à aujourd'hui — vérifier la saisie.",AD104>0,"⚠️ CONCERNÉ : pénalité de "&AD104&"% (détention "&Q104&" mois). "&T104,TRUE,"Non concerné (détention "&Q104&" mois). "&T104) | H104: =COUNTIFS(BDD_Calendrier!$A$2:$A$616,$B104,BDD_Calendrier!$C$2:$C$616,"Souscription") | I104: =IF(H104=0,"",IFERROR(_xlfn.MINIFS(BDD_Calendrier!$D$2:$D$616,BDD_Calendrier!$A$2:$A$616,$B104,BDD_Calendrier!$C$2:$C$616,"Souscription",BDD_Calendrier!$D$2:$D$616,">="&TODAY()),"")) | J104: =IF(I104="","",IFERROR(INDEX(BDD_Calendrier!$E$2:$E$616,MATCH($B104&"|Souscription|"&TEXT(I104,"yyyy-mm-dd"),BDD_Calendrier!$I$2:$I$616,0)),"")) | K104: =IF(H104=0,"",_xlfn.MAXIFS(BDD_Calendrier!$D$2:$D$616,BDD_Calendrier!$A$2:$A$616,$B104,BDD_Calendrier!$C$2:$C$616,"Souscription")) | L104: =COUNTIFS(BDD_Calendrier!$A$2:$A$616,$B104,BDD_Calendrier!$C$2:$C$616,"Rachat") | M104: =IF(L104=0,"",IFERROR(_xlfn.MINIFS(BDD_Calendrier!$D$2:$D$616,BDD_Calendrier!$A$2:$A$616,$B104,BDD_Calendrier!$C$2:$C$616,"Rachat",BDD_Calendrier!$D$2:$D$616,">="&TODAY()),"")) | N104: =IF(M104="","",IFERROR(INDEX(BDD_Calendrier!$E$2:$E$616,MATCH($B104&"|Rachat|"&TEXT(M104,"yyyy-mm-dd"),BDD_Calendrier!$I$2:$I$616,0)),"")) | O104: =IF(M104="","",IFERROR(INDEX(BDD_Calendrier!$H$2:$H$616,MATCH($B104&"|Rachat|"&TEXT(M104,"yyyy-mm-dd"),BDD_Calendrier!$I$2:$I$616,0)),"")) | P104: =IF(L104=0,"",_xlfn.MAXIFS(BDD_Calendrier!$D$2:$D$616,BDD_Calendrier!$A$2:$A$616,$B104,BDD_Calendrier!$C$2:$C$616,"Rachat")) | Q104: =IF($C104="","",IF($C104>TODAY(),"FUTUR",DATEDIF($C104,TODAY(),"m"))) | R104: =COUNTIF(BDD_Penalites!$A$2:$A$130,$B104) | S104: =IF(R104=0,"inconnue",INDEX(BDD_Penalites!$C$2:$C$130,MATCH($B104,BDD_Penalites!$A$2:$A$130,0))) | T104: =IF(R104=0,"",INDEX(BDD_Penalites!$M$2:$M$130,MATCH($B104,BDD_Penalites!$A$2:$A$130,0))) | U104: =IF(R104=0,0,INDEX(BDD_Penalites!$D$2:$D$130,MATCH($B104,BDD_Penalites!$A$2:$A$130,0))) | V104: =IF(R104=0,0,INDEX(BDD_Penalites!$E$2:$E$130,MATCH($B104,BDD_Penalites!$A$2:$A$130,0))) | W104: =IF(R104=0,0,INDEX(BDD_Penalites!$F$2:$F$130,MATCH($B104,BDD_Penalites!$A$2:$A$130,0))) | X104: =IF(R104=0,0,INDEX(BDD_Penalites!$G$2:$G$130,MATCH($B104,BDD_Penalites!$A$2:$A$130,0))) | Y104: =IF(R104=0,0,INDEX(BDD_Penalites!$H$2:$H$130,MATCH($B104,BDD_Penalites!$A$2:$A$130,0))) | Z104: =IF(R104=0,0,INDEX(BDD_Penalites!$I$2:$I$130,MATCH($B104,BDD_Penalites!$A$2:$A$130,0))) | AA104: =IF(R104=0,0,INDEX(BDD_Penalites!$J$2:$J$130,MATCH($B104,BDD_Penalites!$A$2:$A$130,0))) | AB104: =IF(R104=0,0,INDEX(BDD_Penalites!$K$2:$K$130,MATCH($B104,BDD_Penalites!$A$2:$A$130,0))) | AC104: =IF(R104=0,0,INDEX(BDD_Penalites!$L$2:$L$130,MATCH($B104,BDD_Penalites!$A$2:$A$130,0))) | AD104: =IF(OR($C104="",Q104="FUTUR"),"",_xlfn.IFS(Q104<U104,V104,Q104<W104,X104,Q104<Y104,Z104,Q104<AA104,AB104,TRUE,AC104))
A105: Helium Global S EUR | B105: IE000F31HWX5 | D105: =IF(H105=0,"Calendrier non disponible pour ce fonds — contacter la société de gestion.",IF(I105="","Calendrier connu jusqu'au "&TEXT(K105,"dd/mm/yyyy")&" — demander le calendrier à jour.","Cut-off : "&TEXT(I105,"dd/mm/yyyy")&" | VL : "&TEXT(J105,"dd/mm/yyyy"))) | E105: =IF(L105=0,"Calendrier non disponible pour ce fonds — contacter la société de gestion.",IF(M105="","Calendrier connu jusqu'au "&TEXT(P105,"dd/mm/yyyy")&" — demander le calendrier à jour.","Cut-off : "&TEXT(M105,"dd/mm/yyyy")&" | VL : "&TEXT(N105,"dd/mm/yyyy"))) | F105: =IF(L105=0,"Calendrier non disponible pour ce fonds.",IF(M105="","Calendrier connu jusqu'au "&TEXT(P105,"dd/mm/yyyy")&".",IF(O105="","Non précisé dans le calendrier pour cette échéance.","Réception : "&TEXT(O105,"dd/mm/yyyy")&" (suite au rachat du "&TEXT(N105,"dd/mm/yyyy")&")"))) | G105: =_xlfn.IFS(S105="aucune","Aucune pénalité de sortie."&IF(T105<>""," ("&T105&")",""),S105="manuel","⚠️ À VÉRIFIER MANUELLEMENT : "&T105,S105="inconnue","Pénalité non renseignée — vérifier la notice / DICI du fonds.",$C105="","Saisir une date d'investissement pour statuer sur la pénalité.",Q105="FUTUR","Date d'investissement postérieure à aujourd'hui — vérifier la saisie.",AD105>0,"⚠️ CONCERNÉ : pénalité de "&AD105&"% (détention "&Q105&" mois). "&T105,TRUE,"Non concerné (détention "&Q105&" mois). "&T105) | H105: =COUNTIFS(BDD_Calendrier!$A$2:$A$616,$B105,BDD_Calendrier!$C$2:$C$616,"Souscription") | I105: =IF(H105=0,"",IFERROR(_xlfn.MINIFS(BDD_Calendrier!$D$2:$D$616,BDD_Calendrier!$A$2:$A$616,$B105,BDD_Calendrier!$C$2:$C$616,"Souscription",BDD_Calendrier!$D$2:$D$616,">="&TODAY()),"")) | J105: =IF(I105="","",IFERROR(INDEX(BDD_Calendrier!$E$2:$E$616,MATCH($B105&"|Souscription|"&TEXT(I105,"yyyy-mm-dd"),BDD_Calendrier!$I$2:$I$616,0)),"")) | K105: =IF(H105=0,"",_xlfn.MAXIFS(BDD_Calendrier!$D$2:$D$616,BDD_Calendrier!$A$2:$A$616,$B105,BDD_Calendrier!$C$2:$C$616,"Souscription")) | L105: =COUNTIFS(BDD_Calendrier!$A$2:$A$616,$B105,BDD_Calendrier!$C$2:$C$616,"Rachat") | M105: =IF(L105=0,"",IFERROR(_xlfn.MINIFS(BDD_Calendrier!$D$2:$D$616,BDD_Calendrier!$A$2:$A$616,$B105,BDD_Calendrier!$C$2:$C$616,"Rachat",BDD_Calendrier!$D$2:$D$616,">="&TODAY()),"")) | N105: =IF(M105="","",IFERROR(INDEX(BDD_Calendrier!$E$2:$E$616,MATCH($B105&"|Rachat|"&TEXT(M105,"yyyy-mm-dd"),BDD_Calendrier!$I$2:$I$616,0)),"")) | O105: =IF(M105="","",IFERROR(INDEX(BDD_Calendrier!$H$2:$H$616,MATCH($B105&"|Rachat|"&TEXT(M105,"yyyy-mm-dd"),BDD_Calendrier!$I$2:$I$616,0)),"")) | P105: =IF(L105=0,"",_xlfn.MAXIFS(BDD_Calendrier!$D$2:$D$616,BDD_Calendrier!$A$2:$A$616,$B105,BDD_Calendrier!$C$2:$C$616,"Rachat")) | Q105: =IF($C105="","",IF($C105>TODAY(),"FUTUR",DATEDIF($C105,TODAY(),"m"))) | R105: =COUNTIF(BDD_Penalites!$A$2:$A$130,$B105) | S105: =IF(R105=0,"inconnue",INDEX(BDD_Penalites!$C$2:$C$130,MATCH($B105,BDD_Penalites!$A$2:$A$130,0))) | T105: =IF(R105=0,"",INDEX(BDD_Penalites!$M$2:$M$130,MATCH($B105,BDD_Penalites!$A$2:$A$130,0))) | U105: =IF(R105=0,0,INDEX(BDD_Penalites!$D$2:$D$130,MATCH($B105,BDD_Penalites!$A$2:$A$130,0))) | V105: =IF(R105=0,0,INDEX(BDD_Penalites!$E$2:$E$130,MATCH($B105,BDD_Penalites!$A$2:$A$130,0))) | W105: =IF(R105=0,0,INDEX(BDD_Penalites!$F$2:$F$130,MATCH($B105,BDD_Penalites!$A$2:$A$130,0))) | X105: =IF(R105=0,0,INDEX(BDD_Penalites!$G$2:$G$130,MATCH($B105,BDD_Penalites!$A$2:$A$130,0))) | Y105: =IF(R105=0,0,INDEX(BDD_Penalites!$H$2:$H$130,MATCH($B105,BDD_Penalites!$A$2:$A$130,0))) | Z105: =IF(R105=0,0,INDEX(BDD_Penalites!$I$2:$I$130,MATCH($B105,BDD_Penalites!$A$2:$A$130,0))) | AA105: =IF(R105=0,0,INDEX(BDD_Penalites!$J$2:$J$130,MATCH($B105,BDD_Penalites!$A$2:$A$130,0))) | AB105: =IF(R105=0,0,INDEX(BDD_Penalites!$K$2:$K$130,MATCH($B105,BDD_Penalites!$A$2:$A$130,0))) | AC105: =IF(R105=0,0,INDEX(BDD_Penalites!$L$2:$L$130,MATCH($B105,BDD_Penalites!$A$2:$A$130,0))) | AD105: =IF(OR($C105="",Q105="FUTUR"),"",_xlfn.IFS(Q105<U105,V105,Q105<W105,X105,Q105<Y105,Z105,Q105<AA105,AB105,TRUE,AC105))
A106: Helium Selection B-EUR | B106: LU1112771503 | D106: =IF(H106=0,"Calendrier non disponible pour ce fonds — contacter la société de gestion.",IF(I106="","Calendrier connu jusqu'au "&TEXT(K106,"dd/mm/yyyy")&" — demander le calendrier à jour.","Cut-off : "&TEXT(I106,"dd/mm/yyyy")&" | VL : "&TEXT(J106,"dd/mm/yyyy"))) | E106: =IF(L106=0,"Calendrier non disponible pour ce fonds — contacter la société de gestion.",IF(M106="","Calendrier connu jusqu'au "&TEXT(P106,"dd/mm/yyyy")&" — demander le calendrier à jour.","Cut-off : "&TEXT(M106,"dd/mm/yyyy")&" | VL : "&TEXT(N106,"dd/mm/yyyy"))) | F106: =IF(L106=0,"Calendrier non disponible pour ce fonds.",IF(M106="","Calendrier connu jusqu'au "&TEXT(P106,"dd/mm/yyyy")&".",IF(O106="","Non précisé dans le calendrier pour cette échéance.","Réception : "&TEXT(O106,"dd/mm/yyyy")&" (suite au rachat du "&TEXT(N106,"dd/mm/yyyy")&")"))) | G106: =_xlfn.IFS(S106="aucune","Aucune pénalité de sortie."&IF(T106<>""," ("&T106&")",""),S106="manuel","⚠️ À VÉRIFIER MANUELLEMENT : "&T106,S106="inconnue","Pénalité non renseignée — vérifier la notice / DICI du fonds.",$C106="","Saisir une date d'investissement pour statuer sur la pénalité.",Q106="FUTUR","Date d'investissement postérieure à aujourd'hui — vérifier la saisie.",AD106>0,"⚠️ CONCERNÉ : pénalité de "&AD106&"% (détention "&Q106&" mois). "&T106,TRUE,"Non concerné (détention "&Q106&" mois). "&T106) | H106: =COUNTIFS(BDD_Calendrier!$A$2:$A$616,$B106,BDD_Calendrier!$C$2:$C$616,"Souscription") | I106: =IF(H106=0,"",IFERROR(_xlfn.MINIFS(BDD_Calendrier!$D$2:$D$616,BDD_Calendrier!$A$2:$A$616,$B106,BDD_Calendrier!$C$2:$C$616,"Souscription",BDD_Calendrier!$D$2:$D$616,">="&TODAY()),"")) | J106: =IF(I106="","",IFERROR(INDEX(BDD_Calendrier!$E$2:$E$616,MATCH($B106&"|Souscription|"&TEXT(I106,"yyyy-mm-dd"),BDD_Calendrier!$I$2:$I$616,0)),"")) | K106: =IF(H106=0,"",_xlfn.MAXIFS(BDD_Calendrier!$D$2:$D$616,BDD_Calendrier!$A$2:$A$616,$B106,BDD_Calendrier!$C$2:$C$616,"Souscription")) | L106: =COUNTIFS(BDD_Calendrier!$A$2:$A$616,$B106,BDD_Calendrier!$C$2:$C$616,"Rachat") | M106: =IF(L106=0,"",IFERROR(_xlfn.MINIFS(BDD_Calendrier!$D$2:$D$616,BDD_Calendrier!$A$2:$A$616,$B106,BDD_Calendrier!$C$2:$C$616,"Rachat",BDD_Calendrier!$D$2:$D$616,">="&TODAY()),"")) | N106: =IF(M106="","",IFERROR(INDEX(BDD_Calendrier!$E$2:$E$616,MATCH($B106&"|Rachat|"&TEXT(M106,"yyyy-mm-dd"),BDD_Calendrier!$I$2:$I$616,0)),"")) | O106: =IF(M106="","",IFERROR(INDEX(BDD_Calendrier!$H$2:$H$616,MATCH($B106&"|Rachat|"&TEXT(M106,"yyyy-mm-dd"),BDD_Calendrier!$I$2:$I$616,0)),"")) | P106: =IF(L106=0,"",_xlfn.MAXIFS(BDD_Calendrier!$D$2:$D$616,BDD_Calendrier!$A$2:$A$616,$B106,BDD_Calendrier!$C$2:$C$616,"Rachat")) | Q106: =IF($C106="","",IF($C106>TODAY(),"FUTUR",DATEDIF($C106,TODAY(),"m"))) | R106: =COUNTIF(BDD_Penalites!$A$2:$A$130,$B106) | S106: =IF(R106=0,"inconnue",INDEX(BDD_Penalites!$C$2:$C$130,MATCH($B106,BDD_Penalites!$A$2:$A$130,0))) | T106: =IF(R106=0,"",INDEX(BDD_Penalites!$M$2:$M$130,MATCH($B106,BDD_Penalites!$A$2:$A$130,0))) | U106: =IF(R106=0,0,INDEX(BDD_Penalites!$D$2:$D$130,MATCH($B106,BDD_Penalites!$A$2:$A$130,0))) | V106: =IF(R106=0,0,INDEX(BDD_Penalites!$E$2:$E$130,MATCH($B106,BDD_Penalites!$A$2:$A$130,0))) | W106: =IF(R106=0,0,INDEX(BDD_Penalites!$F$2:$F$130,MATCH($B106,BDD_Penalites!$A$2:$A$130,0))) | X106: =IF(R106=0,0,INDEX(BDD_Penalites!$G$2:$G$130,MATCH($B106,BDD_Penalites!$A$2:$A$130,0))) | Y106: =IF(R106=0,0,INDEX(BDD_Penalites!$H$2:$H$130,MATCH($B106,BDD_Penalites!$A$2:$A$130,0))) | Z106: =IF(R106=0,0,INDEX(BDD_Penalites!$I$2:$I$130,MATCH($B106,BDD_Penalites!$A$2:$A$130,0))) | AA106: =IF(R106=0,0,INDEX(BDD_Penalites!$J$2:$J$130,MATCH($B106,BDD_Penalites!$A$2:$A$130,0))) | AB106: =IF(R106=0,0,INDEX(BDD_Penalites!$K$2:$K$130,MATCH($B106,BDD_Penalites!$A$2:$A$130,0))) | AC106: =IF(R106=0,0,INDEX(BDD_Penalites!$L$2:$L$130,MATCH($B106,BDD_Penalites!$A$2:$A$130,0))) | AD106: =IF(OR($C106="",Q106="FUTUR"),"",_xlfn.IFS(Q106<U106,V106,Q106<W106,X106,Q106<Y106,Z106,Q106<AA106,AB106,TRUE,AC106))
A107: Helium Performance B EUR | B107: LU0912262275 | D107: =IF(H107=0,"Calendrier non disponible pour ce fonds — contacter la société de gestion.",IF(I107="","Calendrier connu jusqu'au "&TEXT(K107,"dd/mm/yyyy")&" — demander le calendrier à jour.","Cut-off : "&TEXT(I107,"dd/mm/yyyy")&" | VL : "&TEXT(J107,"dd/mm/yyyy"))) | E107: =IF(L107=0,"Calendrier non disponible pour ce fonds — contacter la société de gestion.",IF(M107="","Calendrier connu jusqu'au "&TEXT(P107,"dd/mm/yyyy")&" — demander le calendrier à jour.","Cut-off : "&TEXT(M107,"dd/mm/yyyy")&" | VL : "&TEXT(N107,"dd/mm/yyyy"))) | F107: =IF(L107=0,"Calendrier non disponible pour ce fonds.",IF(M107="","Calendrier connu jusqu'au "&TEXT(P107,"dd/mm/yyyy")&".",IF(O107="","Non précisé dans le calendrier pour cette échéance.","Réception : "&TEXT(O107,"dd/mm/yyyy")&" (suite au rachat du "&TEXT(N107,"dd/mm/yyyy")&")"))) | G107: =_xlfn.IFS(S107="aucune","Aucune pénalité de sortie."&IF(T107<>""," ("&T107&")",""),S107="manuel","⚠️ À VÉRIFIER MANUELLEMENT : "&T107,S107="inconnue","Pénalité non renseignée — vérifier la notice / DICI du fonds.",$C107="","Saisir une date d'investissement pour statuer sur la pénalité.",Q107="FUTUR","Date d'investissement postérieure à aujourd'hui — vérifier la saisie.",AD107>0,"⚠️ CONCERNÉ : pénalité de "&AD107&"% (détention "&Q107&" mois). "&T107,TRUE,"Non concerné (détention "&Q107&" mois). "&T107) | H107: =COUNTIFS(BDD_Calendrier!$A$2:$A$616,$B107,BDD_Calendrier!$C$2:$C$616,"Souscription") | I107: =IF(H107=0,"",IFERROR(_xlfn.MINIFS(BDD_Calendrier!$D$2:$D$616,BDD_Calendrier!$A$2:$A$616,$B107,BDD_Calendrier!$C$2:$C$616,"Souscription",BDD_Calendrier!$D$2:$D$616,">="&TODAY()),"")) | J107: =IF(I107="","",IFERROR(INDEX(BDD_Calendrier!$E$2:$E$616,MATCH($B107&"|Souscription|"&TEXT(I107,"yyyy-mm-dd"),BDD_Calendrier!$I$2:$I$616,0)),"")) | K107: =IF(H107=0,"",_xlfn.MAXIFS(BDD_Calendrier!$D$2:$D$616,BDD_Calendrier!$A$2:$A$616,$B107,BDD_Calendrier!$C$2:$C$616,"Souscription")) | L107: =COUNTIFS(BDD_Calendrier!$A$2:$A$616,$B107,BDD_Calendrier!$C$2:$C$616,"Rachat") | M107: =IF(L107=0,"",IFERROR(_xlfn.MINIFS(BDD_Calendrier!$D$2:$D$616,BDD_Calendrier!$A$2:$A$616,$B107,BDD_Calendrier!$C$2:$C$616,"Rachat",BDD_Calendrier!$D$2:$D$616,">="&TODAY()),"")) | N107: =IF(M107="","",IFERROR(INDEX(BDD_Calendrier!$E$2:$E$616,MATCH($B107&"|Rachat|"&TEXT(M107,"yyyy-mm-dd"),BDD_Calendrier!$I$2:$I$616,0)),"")) | O107: =IF(M107="","",IFERROR(INDEX(BDD_Calendrier!$H$2:$H$616,MATCH($B107&"|Rachat|"&TEXT(M107,"yyyy-mm-dd"),BDD_Calendrier!$I$2:$I$616,0)),"")) | P107: =IF(L107=0,"",_xlfn.MAXIFS(BDD_Calendrier!$D$2:$D$616,BDD_Calendrier!$A$2:$A$616,$B107,BDD_Calendrier!$C$2:$C$616,"Rachat")) | Q107: =IF($C107="","",IF($C107>TODAY(),"FUTUR",DATEDIF($C107,TODAY(),"m"))) | R107: =COUNTIF(BDD_Penalites!$A$2:$A$130,$B107) | S107: =IF(R107=0,"inconnue",INDEX(BDD_Penalites!$C$2:$C$130,MATCH($B107,BDD_Penalites!$A$2:$A$130,0))) | T107: =IF(R107=0,"",INDEX(BDD_Penalites!$M$2:$M$130,MATCH($B107,BDD_Penalites!$A$2:$A$130,0))) | U107: =IF(R107=0,0,INDEX(BDD_Penalites!$D$2:$D$130,MATCH($B107,BDD_Penalites!$A$2:$A$130,0))) | V107: =IF(R107=0,0,INDEX(BDD_Penalites!$E$2:$E$130,MATCH($B107,BDD_Penalites!$A$2:$A$130,0))) | W107: =IF(R107=0,0,INDEX(BDD_Penalites!$F$2:$F$130,MATCH($B107,BDD_Penalites!$A$2:$A$130,0))) | X107: =IF(R107=0,0,INDEX(BDD_Penalites!$G$2:$G$130,MATCH($B107,BDD_Penalites!$A$2:$A$130,0))) | Y107: =IF(R107=0,0,INDEX(BDD_Penalites!$H$2:$H$130,MATCH($B107,BDD_Penalites!$A$2:$A$130,0))) | Z107: =IF(R107=0,0,INDEX(BDD_Penalites!$I$2:$I$130,MATCH($B107,BDD_Penalites!$A$2:$A$130,0))) | AA107: =IF(R107=0,0,INDEX(BDD_Penalites!$J$2:$J$130,MATCH($B107,BDD_Penalites!$A$2:$A$130,0))) | AB107: =IF(R107=0,0,INDEX(BDD_Penalites!$K$2:$K$130,MATCH($B107,BDD_Penalites!$A$2:$A$130,0))) | AC107: =IF(R107=0,0,INDEX(BDD_Penalites!$L$2:$L$130,MATCH($B107,BDD_Penalites!$A$2:$A$130,0))) | AD107: =IF(OR($C107="",Q107="FUTUR"),"",_xlfn.IFS(Q107<U107,V107,Q107<W107,X107,Q107<Y107,Z107,Q107<AA107,AB107,TRUE,AC107))
A108: Cypanga Diversified Portfolio A | B108: LU0672299830 | D108: =IF(H108=0,"Calendrier non disponible pour ce fonds — contacter la société de gestion.",IF(I108="","Calendrier connu jusqu'au "&TEXT(K108,"dd/mm/yyyy")&" — demander le calendrier à jour.","Cut-off : "&TEXT(I108,"dd/mm/yyyy")&" | VL : "&TEXT(J108,"dd/mm/yyyy"))) | E108: =IF(L108=0,"Calendrier non disponible pour ce fonds — contacter la société de gestion.",IF(M108="","Calendrier connu jusqu'au "&TEXT(P108,"dd/mm/yyyy")&" — demander le calendrier à jour.","Cut-off : "&TEXT(M108,"dd/mm/yyyy")&" | VL : "&TEXT(N108,"dd/mm/yyyy"))) | F108: =IF(L108=0,"Calendrier non disponible pour ce fonds.",IF(M108="","Calendrier connu jusqu'au "&TEXT(P108,"dd/mm/yyyy")&".",IF(O108="","Non précisé dans le calendrier pour cette échéance.","Réception : "&TEXT(O108,"dd/mm/yyyy")&" (suite au rachat du "&TEXT(N108,"dd/mm/yyyy")&")"))) | G108: =_xlfn.IFS(S108="aucune","Aucune pénalité de sortie."&IF(T108<>""," ("&T108&")",""),S108="manuel","⚠️ À VÉRIFIER MANUELLEMENT : "&T108,S108="inconnue","Pénalité non renseignée — vérifier la notice / DICI du fonds.",$C108="","Saisir une date d'investissement pour statuer sur la pénalité.",Q108="FUTUR","Date d'investissement postérieure à aujourd'hui — vérifier la saisie.",AD108>0,"⚠️ CONCERNÉ : pénalité de "&AD108&"% (détention "&Q108&" mois). "&T108,TRUE,"Non concerné (détention "&Q108&" mois). "&T108) | H108: =COUNTIFS(BDD_Calendrier!$A$2:$A$616,$B108,BDD_Calendrier!$C$2:$C$616,"Souscription") | I108: =IF(H108=0,"",IFERROR(_xlfn.MINIFS(BDD_Calendrier!$D$2:$D$616,BDD_Calendrier!$A$2:$A$616,$B108,BDD_Calendrier!$C$2:$C$616,"Souscription",BDD_Calendrier!$D$2:$D$616,">="&TODAY()),"")) | J108: =IF(I108="","",IFERROR(INDEX(BDD_Calendrier!$E$2:$E$616,MATCH($B108&"|Souscription|"&TEXT(I108,"yyyy-mm-dd"),BDD_Calendrier!$I$2:$I$616,0)),"")) | K108: =IF(H108=0,"",_xlfn.MAXIFS(BDD_Calendrier!$D$2:$D$616,BDD_Calendrier!$A$2:$A$616,$B108,BDD_Calendrier!$C$2:$C$616,"Souscription")) | L108: =COUNTIFS(BDD_Calendrier!$A$2:$A$616,$B108,BDD_Calendrier!$C$2:$C$616,"Rachat") | M108: =IF(L108=0,"",IFERROR(_xlfn.MINIFS(BDD_Calendrier!$D$2:$D$616,BDD_Calendrier!$A$2:$A$616,$B108,BDD_Calendrier!$C$2:$C$616,"Rachat",BDD_Calendrier!$D$2:$D$616,">="&TODAY()),"")) | N108: =IF(M108="","",IFERROR(INDEX(BDD_Calendrier!$E$2:$E$616,MATCH($B108&"|Rachat|"&TEXT(M108,"yyyy-mm-dd"),BDD_Calendrier!$I$2:$I$616,0)),"")) | O108: =IF(M108="","",IFERROR(INDEX(BDD_Calendrier!$H$2:$H$616,MATCH($B108&"|Rachat|"&TEXT(M108,"yyyy-mm-dd"),BDD_Calendrier!$I$2:$I$616,0)),"")) | P108: =IF(L108=0,"",_xlfn.MAXIFS(BDD_Calendrier!$D$2:$D$616,BDD_Calendrier!$A$2:$A$616,$B108,BDD_Calendrier!$C$2:$C$616,"Rachat")) | Q108: =IF($C108="","",IF($C108>TODAY(),"FUTUR",DATEDIF($C108,TODAY(),"m"))) | R108: =COUNTIF(BDD_Penalites!$A$2:$A$130,$B108) | S108: =IF(R108=0,"inconnue",INDEX(BDD_Penalites!$C$2:$C$130,MATCH($B108,BDD_Penalites!$A$2:$A$130,0))) | T108: =IF(R108=0,"",INDEX(BDD_Penalites!$M$2:$M$130,MATCH($B108,BDD_Penalites!$A$2:$A$130,0))) | U108: =IF(R108=0,0,INDEX(BDD_Penalites!$D$2:$D$130,MATCH($B108,BDD_Penalites!$A$2:$A$130,0))) | V108: =IF(R108=0,0,INDEX(BDD_Penalites!$E$2:$E$130,MATCH($B108,BDD_Penalites!$A$2:$A$130,0))) | W108: =IF(R108=0,0,INDEX(BDD_Penalites!$F$2:$F$130,MATCH($B108,BDD_Penalites!$A$2:$A$130,0))) | X108: =IF(R108=0,0,INDEX(BDD_Penalites!$G$2:$G$130,MATCH($B108,BDD_Penalites!$A$2:$A$130,0))) | Y108: =IF(R108=0,0,INDEX(BDD_Penalites!$H$2:$H$130,MATCH($B108,BDD_Penalites!$A$2:$A$130,0))) | Z108: =IF(R108=0,0,INDEX(BDD_Penalites!$I$2:$I$130,MATCH($B108,BDD_Penalites!$A$2:$A$130,0))) | AA108: =IF(R108=0,0,INDEX(BDD_Penalites!$J$2:$J$130,MATCH($B108,BDD_Penalites!$A$2:$A$130,0))) | AB108: =IF(R108=0,0,INDEX(BDD_Penalites!$K$2:$K$130,MATCH($B108,BDD_Penalites!$A$2:$A$130,0))) | AC108: =IF(R108=0,0,INDEX(BDD_Penalites!$L$2:$L$130,MATCH($B108,BDD_Penalites!$A$2:$A$130,0))) | AD108: =IF(OR($C108="",Q108="FUTUR"),"",_xlfn.IFS(Q108<U108,V108,Q108<W108,X108,Q108<Y108,Z108,Q108<AA108,AB108,TRUE,AC108))
A109: Tikehau International Cross Assets R Acc EUR | B109: LU2147879543 | D109: =IF(H109=0,"Calendrier non disponible pour ce fonds — contacter la société de gestion.",IF(I109="","Calendrier connu jusqu'au "&TEXT(K109,"dd/mm/yyyy")&" — demander le calendrier à jour.","Cut-off : "&TEXT(I109,"dd/mm/yyyy")&" | VL : "&TEXT(J109,"dd/mm/yyyy"))) | E109: =IF(L109=0,"Calendrier non disponible pour ce fonds — contacter la société de gestion.",IF(M109="","Calendrier connu jusqu'au "&TEXT(P109,"dd/mm/yyyy")&" — demander le calendrier à jour.","Cut-off : "&TEXT(M109,"dd/mm/yyyy")&" | VL : "&TEXT(N109,"dd/mm/yyyy"))) | F109: =IF(L109=0,"Calendrier non disponible pour ce fonds.",IF(M109="","Calendrier connu jusqu'au "&TEXT(P109,"dd/mm/yyyy")&".",IF(O109="","Non précisé dans le calendrier pour cette échéance.","Réception : "&TEXT(O109,"dd/mm/yyyy")&" (suite au rachat du "&TEXT(N109,"dd/mm/yyyy")&")"))) | G109: =_xlfn.IFS(S109="aucune","Aucune pénalité de sortie."&IF(T109<>""," ("&T109&")",""),S109="manuel","⚠️ À VÉRIFIER MANUELLEMENT : "&T109,S109="inconnue","Pénalité non renseignée — vérifier la notice / DICI du fonds.",$C109="","Saisir une date d'investissement pour statuer sur la pénalité.",Q109="FUTUR","Date d'investissement postérieure à aujourd'hui — vérifier la saisie.",AD109>0,"⚠️ CONCERNÉ : pénalité de "&AD109&"% (détention "&Q109&" mois). "&T109,TRUE,"Non concerné (détention "&Q109&" mois). "&T109) | H109: =COUNTIFS(BDD_Calendrier!$A$2:$A$616,$B109,BDD_Calendrier!$C$2:$C$616,"Souscription") | I109: =IF(H109=0,"",IFERROR(_xlfn.MINIFS(BDD_Calendrier!$D$2:$D$616,BDD_Calendrier!$A$2:$A$616,$B109,BDD_Calendrier!$C$2:$C$616,"Souscription",BDD_Calendrier!$D$2:$D$616,">="&TODAY()),"")) | J109: =IF(I109="","",IFERROR(INDEX(BDD_Calendrier!$E$2:$E$616,MATCH($B109&"|Souscription|"&TEXT(I109,"yyyy-mm-dd"),BDD_Calendrier!$I$2:$I$616,0)),"")) | K109: =IF(H109=0,"",_xlfn.MAXIFS(BDD_Calendrier!$D$2:$D$616,BDD_Calendrier!$A$2:$A$616,$B109,BDD_Calendrier!$C$2:$C$616,"Souscription")) | L109: =COUNTIFS(BDD_Calendrier!$A$2:$A$616,$B109,BDD_Calendrier!$C$2:$C$616,"Rachat") | M109: =IF(L109=0,"",IFERROR(_xlfn.MINIFS(BDD_Calendrier!$D$2:$D$616,BDD_Calendrier!$A$2:$A$616,$B109,BDD_Calendrier!$C$2:$C$616,"Rachat",BDD_Calendrier!$D$2:$D$616,">="&TODAY()),"")) | N109: =IF(M109="","",IFERROR(INDEX(BDD_Calendrier!$E$2:$E$616,MATCH($B109&"|Rachat|"&TEXT(M109,"yyyy-mm-dd"),BDD_Calendrier!$I$2:$I$616,0)),"")) | O109: =IF(M109="","",IFERROR(INDEX(BDD_Calendrier!$H$2:$H$616,MATCH($B109&"|Rachat|"&TEXT(M109,"yyyy-mm-dd"),BDD_Calendrier!$I$2:$I$616,0)),"")) | P109: =IF(L109=0,"",_xlfn.MAXIFS(BDD_Calendrier!$D$2:$D$616,BDD_Calendrier!$A$2:$A$616,$B109,BDD_Calendrier!$C$2:$C$616,"Rachat")) | Q109: =IF($C109="","",IF($C109>TODAY(),"FUTUR",DATEDIF($C109,TODAY(),"m"))) | R109: =COUNTIF(BDD_Penalites!$A$2:$A$130,$B109) | S109: =IF(R109=0,"inconnue",INDEX(BDD_Penalites!$C$2:$C$130,MATCH($B109,BDD_Penalites!$A$2:$A$130,0))) | T109: =IF(R109=0,"",INDEX(BDD_Penalites!$M$2:$M$130,MATCH($B109,BDD_Penalites!$A$2:$A$130,0))) | U109: =IF(R109=0,0,INDEX(BDD_Penalites!$D$2:$D$130,MATCH($B109,BDD_Penalites!$A$2:$A$130,0))) | V109: =IF(R109=0,0,INDEX(BDD_Penalites!$E$2:$E$130,MATCH($B109,BDD_Penalites!$A$2:$A$130,0))) | W109: =IF(R109=0,0,INDEX(BDD_Penalites!$F$2:$F$130,MATCH($B109,BDD_Penalites!$A$2:$A$130,0))) | X109: =IF(R109=0,0,INDEX(BDD_Penalites!$G$2:$G$130,MATCH($B109,BDD_Penalites!$A$2:$A$130,0))) | Y109: =IF(R109=0,0,INDEX(BDD_Penalites!$H$2:$H$130,MATCH($B109,BDD_Penalites!$A$2:$A$130,0))) | Z109: =IF(R109=0,0,INDEX(BDD_Penalites!$I$2:$I$130,MATCH($B109,BDD_Penalites!$A$2:$A$130,0))) | AA109: =IF(R109=0,0,INDEX(BDD_Penalites!$J$2:$J$130,MATCH($B109,BDD_Penalites!$A$2:$A$130,0))) | AB109: =IF(R109=0,0,INDEX(BDD_Penalites!$K$2:$K$130,MATCH($B109,BDD_Penalites!$A$2:$A$130,0))) | AC109: =IF(R109=0,0,INDEX(BDD_Penalites!$L$2:$L$130,MATCH($B109,BDD_Penalites!$A$2:$A$130,0))) | AD109: =IF(OR($C109="",Q109="FUTUR"),"",_xlfn.IFS(Q109<U109,V109,Q109<W109,X109,Q109<Y109,Z109,Q109<AA109,AB109,TRUE,AC109))
A110: H2O Adagio I | B110: FR0010929794 | D110: =IF(H110=0,"Calendrier non disponible pour ce fonds — contacter la société de gestion.",IF(I110="","Calendrier connu jusqu'au "&TEXT(K110,"dd/mm/yyyy")&" — demander le calendrier à jour.","Cut-off : "&TEXT(I110,"dd/mm/yyyy")&" | VL : "&TEXT(J110,"dd/mm/yyyy"))) | E110: =IF(L110=0,"Calendrier non disponible pour ce fonds — contacter la société de gestion.",IF(M110="","Calendrier connu jusqu'au "&TEXT(P110,"dd/mm/yyyy")&" — demander le calendrier à jour.","Cut-off : "&TEXT(M110,"dd/mm/yyyy")&" | VL : "&TEXT(N110,"dd/mm/yyyy"))) | F110: =IF(L110=0,"Calendrier non disponible pour ce fonds.",IF(M110="","Calendrier connu jusqu'au "&TEXT(P110,"dd/mm/yyyy")&".",IF(O110="","Non précisé dans le calendrier pour cette échéance.","Réception : "&TEXT(O110,"dd/mm/yyyy")&" (suite au rachat du "&TEXT(N110,"dd/mm/yyyy")&")"))) | G110: =_xlfn.IFS(S110="aucune","Aucune pénalité de sortie."&IF(T110<>""," ("&T110&")",""),S110="manuel","⚠️ À VÉRIFIER MANUELLEMENT : "&T110,S110="inconnue","Pénalité non renseignée — vérifier la notice / DICI du fonds.",$C110="","Saisir une date d'investissement pour statuer sur la pénalité.",Q110="FUTUR","Date d'investissement postérieure à aujourd'hui — vérifier la saisie.",AD110>0,"⚠️ CONCERNÉ : pénalité de "&AD110&"% (détention "&Q110&" mois). "&T110,TRUE,"Non concerné (détention "&Q110&" mois). "&T110) | H110: =COUNTIFS(BDD_Calendrier!$A$2:$A$616,$B110,BDD_Calendrier!$C$2:$C$616,"Souscription") | I110: =IF(H110=0,"",IFERROR(_xlfn.MINIFS(BDD_Calendrier!$D$2:$D$616,BDD_Calendrier!$A$2:$A$616,$B110,BDD_Calendrier!$C$2:$C$616,"Souscription",BDD_Calendrier!$D$2:$D$616,">="&TODAY()),"")) | J110: =IF(I110="","",IFERROR(INDEX(BDD_Calendrier!$E$2:$E$616,MATCH($B110&"|Souscription|"&TEXT(I110,"yyyy-mm-dd"),BDD_Calendrier!$I$2:$I$616,0)),"")) | K110: =IF(H110=0,"",_xlfn.MAXIFS(BDD_Calendrier!$D$2:$D$616,BDD_Calendrier!$A$2:$A$616,$B110,BDD_Calendrier!$C$2:$C$616,"Souscription")) | L110: =COUNTIFS(BDD_Calendrier!$A$2:$A$616,$B110,BDD_Calendrier!$C$2:$C$616,"Rachat") | M110: =IF(L110=0,"",IFERROR(_xlfn.MINIFS(BDD_Calendrier!$D$2:$D$616,BDD_Calendrier!$A$2:$A$616,$B110,BDD_Calendrier!$C$2:$C$616,"Rachat",BDD_Calendrier!$D$2:$D$616,">="&TODAY()),"")) | N110: =IF(M110="","",IFERROR(INDEX(BDD_Calendrier!$E$2:$E$616,MATCH($B110&"|Rachat|"&TEXT(M110,"yyyy-mm-dd"),BDD_Calendrier!$I$2:$I$616,0)),"")) | O110: =IF(M110="","",IFERROR(INDEX(BDD_Calendrier!$H$2:$H$616,MATCH($B110&"|Rachat|"&TEXT(M110,"yyyy-mm-dd"),BDD_Calendrier!$I$2:$I$616,0)),"")) | P110: =IF(L110=0,"",_xlfn.MAXIFS(BDD_Calendrier!$D$2:$D$616,BDD_Calendrier!$A$2:$A$616,$B110,BDD_Calendrier!$C$2:$C$616,"Rachat")) | Q110: =IF($C110="","",IF($C110>TODAY(),"FUTUR",DATEDIF($C110,TODAY(),"m"))) | R110: =COUNTIF(BDD_Penalites!$A$2:$A$130,$B110) | S110: =IF(R110=0,"inconnue",INDEX(BDD_Penalites!$C$2:$C$130,MATCH($B110,BDD_Penalites!$A$2:$A$130,0))) | T110: =IF(R110=0,"",INDEX(BDD_Penalites!$M$2:$M$130,MATCH($B110,BDD_Penalites!$A$2:$A$130,0))) | U110: =IF(R110=0,0,INDEX(BDD_Penalites!$D$2:$D$130,MATCH($B110,BDD_Penalites!$A$2:$A$130,0))) | V110: =IF(R110=0,0,INDEX(BDD_Penalites!$E$2:$E$130,MATCH($B110,BDD_Penalites!$A$2:$A$130,0))) | W110: =IF(R110=0,0,INDEX(BDD_Penalites!$F$2:$F$130,MATCH($B110,BDD_Penalites!$A$2:$A$130,0))) | X110: =IF(R110=0,0,INDEX(BDD_Penalites!$G$2:$G$130,MATCH($B110,BDD_Penalites!$A$2:$A$130,0))) | Y110: =IF(R110=0,0,INDEX(BDD_Penalites!$H$2:$H$130,MATCH($B110,BDD_Penalites!$A$2:$A$130,0))) | Z110: =IF(R110=0,0,INDEX(BDD_Penalites!$I$2:$I$130,MATCH($B110,BDD_Penalites!$A$2:$A$130,0))) | AA110: =IF(R110=0,0,INDEX(BDD_Penalites!$J$2:$J$130,MATCH($B110,BDD_Penalites!$A$2:$A$130,0))) | AB110: =IF(R110=0,0,INDEX(BDD_Penalites!$K$2:$K$130,MATCH($B110,BDD_Penalites!$A$2:$A$130,0))) | AC110: =IF(R110=0,0,INDEX(BDD_Penalites!$L$2:$L$130,MATCH($B110,BDD_Penalites!$A$2:$A$130,0))) | AD110: =IF(OR($C110="",Q110="FUTUR"),"",_xlfn.IFS(Q110<U110,V110,Q110<W110,X110,Q110<Y110,Z110,Q110<AA110,AB110,TRUE,AC110))
A111: H2O Adagio NC | B111: FR0013186772 | D111: =IF(H111=0,"Calendrier non disponible pour ce fonds — contacter la société de gestion.",IF(I111="","Calendrier connu jusqu'au "&TEXT(K111,"dd/mm/yyyy")&" — demander le calendrier à jour.","Cut-off : "&TEXT(I111,"dd/mm/yyyy")&" | VL : "&TEXT(J111,"dd/mm/yyyy"))) | E111: =IF(L111=0,"Calendrier non disponible pour ce fonds — contacter la société de gestion.",IF(M111="","Calendrier connu jusqu'au "&TEXT(P111,"dd/mm/yyyy")&" — demander le calendrier à jour.","Cut-off : "&TEXT(M111,"dd/mm/yyyy")&" | VL : "&TEXT(N111,"dd/mm/yyyy"))) | F111: =IF(L111=0,"Calendrier non disponible pour ce fonds.",IF(M111="","Calendrier connu jusqu'au "&TEXT(P111,"dd/mm/yyyy")&".",IF(O111="","Non précisé dans le calendrier pour cette échéance.","Réception : "&TEXT(O111,"dd/mm/yyyy")&" (suite au rachat du "&TEXT(N111,"dd/mm/yyyy")&")"))) | G111: =_xlfn.IFS(S111="aucune","Aucune pénalité de sortie."&IF(T111<>""," ("&T111&")",""),S111="manuel","⚠️ À VÉRIFIER MANUELLEMENT : "&T111,S111="inconnue","Pénalité non renseignée — vérifier la notice / DICI du fonds.",$C111="","Saisir une date d'investissement pour statuer sur la pénalité.",Q111="FUTUR","Date d'investissement postérieure à aujourd'hui — vérifier la saisie.",AD111>0,"⚠️ CONCERNÉ : pénalité de "&AD111&"% (détention "&Q111&" mois). "&T111,TRUE,"Non concerné (détention "&Q111&" mois). "&T111) | H111: =COUNTIFS(BDD_Calendrier!$A$2:$A$616,$B111,BDD_Calendrier!$C$2:$C$616,"Souscription") | I111: =IF(H111=0,"",IFERROR(_xlfn.MINIFS(BDD_Calendrier!$D$2:$D$616,BDD_Calendrier!$A$2:$A$616,$B111,BDD_Calendrier!$C$2:$C$616,"Souscription",BDD_Calendrier!$D$2:$D$616,">="&TODAY()),"")) | J111: =IF(I111="","",IFERROR(INDEX(BDD_Calendrier!$E$2:$E$616,MATCH($B111&"|Souscription|"&TEXT(I111,"yyyy-mm-dd"),BDD_Calendrier!$I$2:$I$616,0)),"")) | K111: =IF(H111=0,"",_xlfn.MAXIFS(BDD_Calendrier!$D$2:$D$616,BDD_Calendrier!$A$2:$A$616,$B111,BDD_Calendrier!$C$2:$C$616,"Souscription")) | L111: =COUNTIFS(BDD_Calendrier!$A$2:$A$616,$B111,BDD_Calendrier!$C$2:$C$616,"Rachat") | M111: =IF(L111=0,"",IFERROR(_xlfn.MINIFS(BDD_Calendrier!$D$2:$D$616,BDD_Calendrier!$A$2:$A$616,$B111,BDD_Calendrier!$C$2:$C$616,"Rachat",BDD_Calendrier!$D$2:$D$616,">="&TODAY()),"")) | N111: =IF(M111="","",IFERROR(INDEX(BDD_Calendrier!$E$2:$E$616,MATCH($B111&"|Rachat|"&TEXT(M111,"yyyy-mm-dd"),BDD_Calendrier!$I$2:$I$616,0)),"")) | O111: =IF(M111="","",IFERROR(INDEX(BDD_Calendrier!$H$2:$H$616,MATCH($B111&"|Rachat|"&TEXT(M111,"yyyy-mm-dd"),BDD_Calendrier!$I$2:$I$616,0)),"")) | P111: =IF(L111=0,"",_xlfn.MAXIFS(BDD_Calendrier!$D$2:$D$616,BDD_Calendrier!$A$2:$A$616,$B111,BDD_Calendrier!$C$2:$C$616,"Rachat")) | Q111: =IF($C111="","",IF($C111>TODAY(),"FUTUR",DATEDIF($C111,TODAY(),"m"))) | R111: =COUNTIF(BDD_Penalites!$A$2:$A$130,$B111) | S111: =IF(R111=0,"inconnue",INDEX(BDD_Penalites!$C$2:$C$130,MATCH($B111,BDD_Penalites!$A$2:$A$130,0))) | T111: =IF(R111=0,"",INDEX(BDD_Penalites!$M$2:$M$130,MATCH($B111,BDD_Penalites!$A$2:$A$130,0))) | U111: =IF(R111=0,0,INDEX(BDD_Penalites!$D$2:$D$130,MATCH($B111,BDD_Penalites!$A$2:$A$130,0))) | V111: =IF(R111=0,0,INDEX(BDD_Penalites!$E$2:$E$130,MATCH($B111,BDD_Penalites!$A$2:$A$130,0))) | W111: =IF(R111=0,0,INDEX(BDD_Penalites!$F$2:$F$130,MATCH($B111,BDD_Penalites!$A$2:$A$130,0))) | X111: =IF(R111=0,0,INDEX(BDD_Penalites!$G$2:$G$130,MATCH($B111,BDD_Penalites!$A$2:$A$130,0))) | Y111: =IF(R111=0,0,INDEX(BDD_Penalites!$H$2:$H$130,MATCH($B111,BDD_Penalites!$A$2:$A$130,0))) | Z111: =IF(R111=0,0,INDEX(BDD_Penalites!$I$2:$I$130,MATCH($B111,BDD_Penalites!$A$2:$A$130,0))) | AA111: =IF(R111=0,0,INDEX(BDD_Penalites!$J$2:$J$130,MATCH($B111,BDD_Penalites!$A$2:$A$130,0))) | AB111: =IF(R111=0,0,INDEX(BDD_Penalites!$K$2:$K$130,MATCH($B111,BDD_Penalites!$A$2:$A$130,0))) | AC111: =IF(R111=0,0,INDEX(BDD_Penalites!$L$2:$L$130,MATCH($B111,BDD_Penalites!$A$2:$A$130,0))) | AD111: =IF(OR($C111="",Q111="FUTUR"),"",_xlfn.IFS(Q111<U111,V111,Q111<W111,X111,Q111<Y111,Z111,Q111<AA111,AB111,TRUE,AC111))
A112: H2O Adagio RC | B112: FR0010923359 | D112: =IF(H112=0,"Calendrier non disponible pour ce fonds — contacter la société de gestion.",IF(I112="","Calendrier connu jusqu'au "&TEXT(K112,"dd/mm/yyyy")&" — demander le calendrier à jour.","Cut-off : "&TEXT(I112,"dd/mm/yyyy")&" | VL : "&TEXT(J112,"dd/mm/yyyy"))) | E112: =IF(L112=0,"Calendrier non disponible pour ce fonds — contacter la société de gestion.",IF(M112="","Calendrier connu jusqu'au "&TEXT(P112,"dd/mm/yyyy")&" — demander le calendrier à jour.","Cut-off : "&TEXT(M112,"dd/mm/yyyy")&" | VL : "&TEXT(N112,"dd/mm/yyyy"))) | F112: =IF(L112=0,"Calendrier non disponible pour ce fonds.",IF(M112="","Calendrier connu jusqu'au "&TEXT(P112,"dd/mm/yyyy")&".",IF(O112="","Non précisé dans le calendrier pour cette échéance.","Réception : "&TEXT(O112,"dd/mm/yyyy")&" (suite au rachat du "&TEXT(N112,"dd/mm/yyyy")&")"))) | G112: =_xlfn.IFS(S112="aucune","Aucune pénalité de sortie."&IF(T112<>""," ("&T112&")",""),S112="manuel","⚠️ À VÉRIFIER MANUELLEMENT : "&T112,S112="inconnue","Pénalité non renseignée — vérifier la notice / DICI du fonds.",$C112="","Saisir une date d'investissement pour statuer sur la pénalité.",Q112="FUTUR","Date d'investissement postérieure à aujourd'hui — vérifier la saisie.",AD112>0,"⚠️ CONCERNÉ : pénalité de "&AD112&"% (détention "&Q112&" mois). "&T112,TRUE,"Non concerné (détention "&Q112&" mois). "&T112) | H112: =COUNTIFS(BDD_Calendrier!$A$2:$A$616,$B112,BDD_Calendrier!$C$2:$C$616,"Souscription") | I112: =IF(H112=0,"",IFERROR(_xlfn.MINIFS(BDD_Calendrier!$D$2:$D$616,BDD_Calendrier!$A$2:$A$616,$B112,BDD_Calendrier!$C$2:$C$616,"Souscription",BDD_Calendrier!$D$2:$D$616,">="&TODAY()),"")) | J112: =IF(I112="","",IFERROR(INDEX(BDD_Calendrier!$E$2:$E$616,MATCH($B112&"|Souscription|"&TEXT(I112,"yyyy-mm-dd"),BDD_Calendrier!$I$2:$I$616,0)),"")) | K112: =IF(H112=0,"",_xlfn.MAXIFS(BDD_Calendrier!$D$2:$D$616,BDD_Calendrier!$A$2:$A$616,$B112,BDD_Calendrier!$C$2:$C$616,"Souscription")) | L112: =COUNTIFS(BDD_Calendrier!$A$2:$A$616,$B112,BDD_Calendrier!$C$2:$C$616,"Rachat") | M112: =IF(L112=0,"",IFERROR(_xlfn.MINIFS(BDD_Calendrier!$D$2:$D$616,BDD_Calendrier!$A$2:$A$616,$B112,BDD_Calendrier!$C$2:$C$616,"Rachat",BDD_Calendrier!$D$2:$D$616,">="&TODAY()),"")) | N112: =IF(M112="","",IFERROR(INDEX(BDD_Calendrier!$E$2:$E$616,MATCH($B112&"|Rachat|"&TEXT(M112,"yyyy-mm-dd"),BDD_Calendrier!$I$2:$I$616,0)),"")) | O112: =IF(M112="","",IFERROR(INDEX(BDD_Calendrier!$H$2:$H$616,MATCH($B112&"|Rachat|"&TEXT(M112,"yyyy-mm-dd"),BDD_Calendrier!$I$2:$I$616,0)),"")) | P112: =IF(L112=0,"",_xlfn.MAXIFS(BDD_Calendrier!$D$2:$D$616,BDD_Calendrier!$A$2:$A$616,$B112,BDD_Calendrier!$C$2:$C$616,"Rachat")) | Q112: =IF($C112="","",IF($C112>TODAY(),"FUTUR",DATEDIF($C112,TODAY(),"m"))) | R112: =COUNTIF(BDD_Penalites!$A$2:$A$130,$B112) | S112: =IF(R112=0,"inconnue",INDEX(BDD_Penalites!$C$2:$C$130,MATCH($B112,BDD_Penalites!$A$2:$A$130,0))) | T112: =IF(R112=0,"",INDEX(BDD_Penalites!$M$2:$M$130,MATCH($B112,BDD_Penalites!$A$2:$A$130,0))) | U112: =IF(R112=0,0,INDEX(BDD_Penalites!$D$2:$D$130,MATCH($B112,BDD_Penalites!$A$2:$A$130,0))) | V112: =IF(R112=0,0,INDEX(BDD_Penalites!$E$2:$E$130,MATCH($B112,BDD_Penalites!$A$2:$A$130,0))) | W112: =IF(R112=0,0,INDEX(BDD_Penalites!$F$2:$F$130,MATCH($B112,BDD_Penalites!$A$2:$A$130,0))) | X112: =IF(R112=0,0,INDEX(BDD_Penalites!$G$2:$G$130,MATCH($B112,BDD_Penalites!$A$2:$A$130,0))) | Y112: =IF(R112=0,0,INDEX(BDD_Penalites!$H$2:$H$130,MATCH($B112,BDD_Penalites!$A$2:$A$130,0))) | Z112: =IF(R112=0,0,INDEX(BDD_Penalites!$I$2:$I$130,MATCH($B112,BDD_Penalites!$A$2:$A$130,0))) | AA112: =IF(R112=0,0,INDEX(BDD_Penalites!$J$2:$J$130,MATCH($B112,BDD_Penalites!$A$2:$A$130,0))) | AB112: =IF(R112=0,0,INDEX(BDD_Penalites!$K$2:$K$130,MATCH($B112,BDD_Penalites!$A$2:$A$130,0))) | AC112: =IF(R112=0,0,INDEX(BDD_Penalites!$L$2:$L$130,MATCH($B112,BDD_Penalites!$A$2:$A$130,0))) | AD112: =IF(OR($C112="",Q112="FUTUR"),"",_xlfn.IFS(Q112<U112,V112,Q112<W112,X112,Q112<Y112,Z112,Q112<AA112,AB112,TRUE,AC112))
... A122: JPMorgan Funds Europe Equity Absolute Alpha fund A | B122: LU1001747408 | D122: =IF(H122=0,"Calendrier non disponible pour ce fonds — contacter la société de gestion.",IF(I122="","Calendrier connu jusqu'au "&TEXT(K122,"dd/mm/yyyy")&" — demander le calendrier à jour.","Cut-off : "&TEXT(I122,"dd/mm/yyyy")&" | VL : "&TEXT(J122,"dd/mm/yyyy"))) | E122: =IF(L122=0,"Calendrier non disponible pour ce fonds — contacter la société de gestion.",IF(M122="","Calendrier connu jusqu'au "&TEXT(P122,"dd/mm/yyyy")&" — demander le calendrier à jour.","Cut-off : "&TEXT(M122,"dd/mm/yyyy")&" | VL : "&TEXT(N122,"dd/mm/yyyy"))) | F122: =IF(L122=0,"Calendrier non disponible pour ce fonds.",IF(M122="","Calendrier connu jusqu'au "&TEXT(P122,"dd/mm/yyyy")&".",IF(O122="","Non précisé dans le calendrier pour cette échéance.","Réception : "&TEXT(O122,"dd/mm/yyyy")&" (suite au rachat du "&TEXT(N122,"dd/mm/yyyy")&")"))) | G122: =_xlfn.IFS(S122="aucune","Aucune pénalité de sortie."&IF(T122<>""," ("&T122&")",""),S122="manuel","⚠️ À VÉRIFIER MANUELLEMENT : "&T122,S122="inconnue","Pénalité non renseignée — vérifier la notice / DICI du fonds.",$C122="","Saisir une date d'investissement pour statuer sur la pénalité.",Q122="FUTUR","Date d'investissement postérieure à aujourd'hui — vérifier la saisie.",AD122>0,"⚠️ CONCERNÉ : pénalité de "&AD122&"% (détention "&Q122&" mois). "&T122,TRUE,"Non concerné (détention "&Q122&" mois). "&T122) | H122: =COUNTIFS(BDD_Calendrier!$A$2:$A$616,$B122,BDD_Calendrier!$C$2:$C$616,"Souscription") | I122: =IF(H122=0,"",IFERROR(_xlfn.MINIFS(BDD_Calendrier!$D$2:$D$616,BDD_Calendrier!$A$2:$A$616,$B122,BDD_Calendrier!$C$2:$C$616,"Souscription",BDD_Calendrier!$D$2:$D$616,">="&TODAY()),"")) | J122: =IF(I122="","",IFERROR(INDEX(BDD_Calendrier!$E$2:$E$616,MATCH($B122&"|Souscription|"&TEXT(I122,"yyyy-mm-dd"),BDD_Calendrier!$I$2:$I$616,0)),"")) | K122: =IF(H122=0,"",_xlfn.MAXIFS(BDD_Calendrier!$D$2:$D$616,BDD_Calendrier!$A$2:$A$616,$B122,BDD_Calendrier!$C$2:$C$616,"Souscription")) | L122: =COUNTIFS(BDD_Calendrier!$A$2:$A$616,$B122,BDD_Calendrier!$C$2:$C$616,"Rachat") | M122: =IF(L122=0,"",IFERROR(_xlfn.MINIFS(BDD_Calendrier!$D$2:$D$616,BDD_Calendrier!$A$2:$A$616,$B122,BDD_Calendrier!$C$2:$C$616,"Rachat",BDD_Calendrier!$D$2:$D$616,">="&TODAY()),"")) | N122: =IF(M122="","",IFERROR(INDEX(BDD_Calendrier!$E$2:$E$616,MATCH($B122&"|Rachat|"&TEXT(M122,"yyyy-mm-dd"),BDD_Calendrier!$I$2:$I$616,0)),"")) | O122: =IF(M122="","",IFERROR(INDEX(BDD_Calendrier!$H$2:$H$616,MATCH($B122&"|Rachat|"&TEXT(M122,"yyyy-mm-dd"),BDD_Calendrier!$I$2:$I$616,0)),"")) | P122: =IF(L122=0,"",_xlfn.MAXIFS(BDD_Calendrier!$D$2:$D$616,BDD_Calendrier!$A$2:$A$616,$B122,BDD_Calendrier!$C$2:$C$616,"Rachat")) | Q122: =IF($C122="","",IF($C122>TODAY(),"FUTUR",DATEDIF($C122,TODAY(),"m"))) | R122: =COUNTIF(BDD_Penalites!$A$2:$A$130,$B122) | S122: =IF(R122=0,"inconnue",INDEX(BDD_Penalites!$C$2:$C$130,MATCH($B122,BDD_Penalites!$A$2:$A$130,0))) | T122: =IF(R122=0,"",INDEX(BDD_Penalites!$M$2:$M$130,MATCH($B122,BDD_Penalites!$A$2:$A$130,0))) | U122: =IF(R122=0,0,INDEX(BDD_Penalites!$D$2:$D$130,MATCH($B122,BDD_Penalites!$A$2:$A$130,0))) | V122: =IF(R122=0,0,INDEX(BDD_Penalites!$E$2:$E$130,MATCH($B122,BDD_Penalites!$A$2:$A$130,0))) | W122: =IF(R122=0,0,INDEX(BDD_Penalites!$F$2:$F$130,MATCH($B122,BDD_Penalites!$A$2:$A$130,0))) | X122: =IF(R122=0,0,INDEX(BDD_Penalites!$G$2:$G$130,MATCH($B122,BDD_Penalites!$A$2:$A$130,0))) | Y122: =IF(R122=0,0,INDEX(BDD_Penalites!$H$2:$H$130,MATCH($B122,BDD_Penalites!$A$2:$A$130,0))) | Z122: =IF(R122=0,0,INDEX(BDD_Penalites!$I$2:$I$130,MATCH($B122,BDD_Penalites!$A$2:$A$130,0))) | AA122: =IF(R122=0,0,INDEX(BDD_Penalites!$J$2:$J$130,MATCH($B122,BDD_Penalites!$A$2:$A$130,0))) | AB122: =IF(R122=0,0,INDEX(BDD_Penalites!$K$2:$K$130,MATCH($B122,BDD_Penalites!$A$2:$A$130,0))) | AC122: =IF(R122=0,0,INDEX(BDD_Penalites!$L$2:$L$130,MATCH($B122,BDD_Penalites!$A$2:$A$130,0))) | AD122: =IF(OR($C122="",Q122="FUTUR"),"",_xlfn.IFS(Q122<U122,V122,Q122<W122,X122,Q122<Y122,Z122,Q122<AA122,AB122,TRUE,AC122))
A139: Immobilier
A140: BK OPCI A | B140: FR0013144094 | D140: =IF(H140=0,"Calendrier non disponible pour ce fonds — contacter la société de gestion.",IF(I140="","Calendrier connu jusqu'au "&TEXT(K140,"dd/mm/yyyy")&" — demander le calendrier à jour.","Cut-off : "&TEXT(I140,"dd/mm/yyyy")&" | VL : "&TEXT(J140,"dd/mm/yyyy"))) | E140: =IF(L140=0,"Calendrier non disponible pour ce fonds — contacter la société de gestion.",IF(M140="","Calendrier connu jusqu'au "&TEXT(P140,"dd/mm/yyyy")&" — demander le calendrier à jour.","Cut-off : "&TEXT(M140,"dd/mm/yyyy")&" | VL : "&TEXT(N140,"dd/mm/yyyy"))) | F140: =IF(L140=0,"Calendrier non disponible pour ce fonds.",IF(M140="","Calendrier connu jusqu'au "&TEXT(P140,"dd/mm/yyyy")&".",IF(O140="","Non précisé dans le calendrier pour cette échéance.","Réception : "&TEXT(O140,"dd/mm/yyyy")&" (suite au rachat du "&TEXT(N140,"dd/mm/yyyy")&")"))) | G140: =_xlfn.IFS(S140="aucune","Aucune pénalité de sortie."&IF(T140<>""," ("&T140&")",""),S140="manuel","⚠️ À VÉRIFIER MANUELLEMENT : "&T140,S140="inconnue","Pénalité non renseignée — vérifier la notice / DICI du fonds.",$C140="","Saisir une date d'investissement pour statuer sur la pénalité.",Q140="FUTUR","Date d'investissement postérieure à aujourd'hui — vérifier la saisie.",AD140>0,"⚠️ CONCERNÉ : pénalité de "&AD140&"% (détention "&Q140&" mois). "&T140,TRUE,"Non concerné (détention "&Q140&" mois). "&T140) | H140: =COUNTIFS(BDD_Calendrier!$A$2:$A$616,$B140,BDD_Calendrier!$C$2:$C$616,"Souscription") | I140: =IF(H140=0,"",IFERROR(_xlfn.MINIFS(BDD_Calendrier!$D$2:$D$616,BDD_Calendrier!$A$2:$A$616,$B140,BDD_Calendrier!$C$2:$C$616,"Souscription",BDD_Calendrier!$D$2:$D$616,">="&TODAY()),"")) | J140: =IF(I140="","",IFERROR(INDEX(BDD_Calendrier!$E$2:$E$616,MATCH($B140&"|Souscription|"&TEXT(I140,"yyyy-mm-dd"),BDD_Calendrier!$I$2:$I$616,0)),"")) | K140: =IF(H140=0,"",_xlfn.MAXIFS(BDD_Calendrier!$D$2:$D$616,BDD_Calendrier!$A$2:$A$616,$B140,BDD_Calendrier!$C$2:$C$616,"Souscription")) | L140: =COUNTIFS(BDD_Calendrier!$A$2:$A$616,$B140,BDD_Calendrier!$C$2:$C$616,"Rachat") | M140: =IF(L140=0,"",IFERROR(_xlfn.MINIFS(BDD_Calendrier!$D$2:$D$616,BDD_Calendrier!$A$2:$A$616,$B140,BDD_Calendrier!$C$2:$C$616,"Rachat",BDD_Calendrier!$D$2:$D$616,">="&TODAY()),"")) | N140: =IF(M140="","",IFERROR(INDEX(BDD_Calendrier!$E$2:$E$616,MATCH($B140&"|Rachat|"&TEXT(M140,"yyyy-mm-dd"),BDD_Calendrier!$I$2:$I$616,0)),"")) | O140: =IF(M140="","",IFERROR(INDEX(BDD_Calendrier!$H$2:$H$616,MATCH($B140&"|Rachat|"&TEXT(M140,"yyyy-mm-dd"),BDD_Calendrier!$I$2:$I$616,0)),"")) | P140: =IF(L140=0,"",_xlfn.MAXIFS(BDD_Calendrier!$D$2:$D$616,BDD_Calendrier!$A$2:$A$616,$B140,BDD_Calendrier!$C$2:$C$616,"Rachat")) | Q140: =IF($C140="","",IF($C140>TODAY(),"FUTUR",DATEDIF($C140,TODAY(),"m"))) | R140: =COUNTIF(BDD_Penalites!$A$2:$A$130,$B140) | S140: =IF(R140=0,"inconnue",INDEX(BDD_Penalites!$C$2:$C$130,MATCH($B140,BDD_Penalites!$A$2:$A$130,0))) | T140: =IF(R140=0,"",INDEX(BDD_Penalites!$M$2:$M$130,MATCH($B140,BDD_Penalites!$A$2:$A$130,0))) | U140: =IF(R140=0,0,INDEX(BDD_Penalites!$D$2:$D$130,MATCH($B140,BDD_Penalites!$A$2:$A$130,0))) | V140: =IF(R140=0,0,INDEX(BDD_Penalites!$E$2:$E$130,MATCH($B140,BDD_Penalites!$A$2:$A$130,0))) | W140: =IF(R140=0,0,INDEX(BDD_Penalites!$F$2:$F$130,MATCH($B140,BDD_Penalites!$A$2:$A$130,0))) | X140: =IF(R140=0,0,INDEX(BDD_Penalites!$G$2:$G$130,MATCH($B140,BDD_Penalites!$A$2:$A$130,0))) | Y140: =IF(R140=0,0,INDEX(BDD_Penalites!$H$2:$H$130,MATCH($B140,BDD_Penalites!$A$2:$A$130,0))) | Z140: =IF(R140=0,0,INDEX(BDD_Penalites!$I$2:$I$130,MATCH($B140,BDD_Penalites!$A$2:$A$130,0))) | AA140: =IF(R140=0,0,INDEX(BDD_Penalites!$J$2:$J$130,MATCH($B140,BDD_Penalites!$A$2:$A$130,0))) | AB140: =IF(R140=0,0,INDEX(BDD_Penalites!$K$2:$K$130,MATCH($B140,BDD_Penalites!$A$2:$A$130,0))) | AC140: =IF(R140=0,0,INDEX(BDD_Penalites!$L$2:$L$130,MATCH($B140,BDD_Penalites!$A$2:$A$130,0))) | AD140: =IF(OR($C140="",Q140="FUTUR"),"",_xlfn.IFS(Q140<U140,V140,Q140<W140,X140,Q140<Y140,Z140,Q140<AA140,AB140,TRUE,AC140))
A141: BK OPCI B | B141: FR0013182664 | D141: =IF(H141=0,"Calendrier non disponible pour ce fonds — contacter la société de gestion.",IF(I141="","Calendrier connu jusqu'au "&TEXT(K141,"dd/mm/yyyy")&" — demander le calendrier à jour.","Cut-off : "&TEXT(I141,"dd/mm/yyyy")&" | VL : "&TEXT(J141,"dd/mm/yyyy"))) | E141: =IF(L141=0,"Calendrier non disponible pour ce fonds — contacter la société de gestion.",IF(M141="","Calendrier connu jusqu'au "&TEXT(P141,"dd/mm/yyyy")&" — demander le calendrier à jour.","Cut-off : "&TEXT(M141,"dd/mm/yyyy")&" | VL : "&TEXT(N141,"dd/mm/yyyy"))) | F141: =IF(L141=0,"Calendrier non disponible pour ce fonds.",IF(M141="","Calendrier connu jusqu'au "&TEXT(P141,"dd/mm/yyyy")&".",IF(O141="","Non précisé dans le calendrier pour cette échéance.","Réception : "&TEXT(O141,"dd/mm/yyyy")&" (suite au rachat du "&TEXT(N141,"dd/mm/yyyy")&")"))) | G141: =_xlfn.IFS(S141="aucune","Aucune pénalité de sortie."&IF(T141<>""," ("&T141&")",""),S141="manuel","⚠️ À VÉRIFIER MANUELLEMENT : "&T141,S141="inconnue","Pénalité non renseignée — vérifier la notice / DICI du fonds.",$C141="","Saisir une date d'investissement pour statuer sur la pénalité.",Q141="FUTUR","Date d'investissement postérieure à aujourd'hui — vérifier la saisie.",AD141>0,"⚠️ CONCERNÉ : pénalité de "&AD141&"% (détention "&Q141&" mois). "&T141,TRUE,"Non concerné (détention "&Q141&" mois). "&T141) | H141: =COUNTIFS(BDD_Calendrier!$A$2:$A$616,$B141,BDD_Calendrier!$C$2:$C$616,"Souscription") | I141: =IF(H141=0,"",IFERROR(_xlfn.MINIFS(BDD_Calendrier!$D$2:$D$616,BDD_Calendrier!$A$2:$A$616,$B141,BDD_Calendrier!$C$2:$C$616,"Souscription",BDD_Calendrier!$D$2:$D$616,">="&TODAY()),"")) | J141: =IF(I141="","",IFERROR(INDEX(BDD_Calendrier!$E$2:$E$616,MATCH($B141&"|Souscription|"&TEXT(I141,"yyyy-mm-dd"),BDD_Calendrier!$I$2:$I$616,0)),"")) | K141: =IF(H141=0,"",_xlfn.MAXIFS(BDD_Calendrier!$D$2:$D$616,BDD_Calendrier!$A$2:$A$616,$B141,BDD_Calendrier!$C$2:$C$616,"Souscription")) | L141: =COUNTIFS(BDD_Calendrier!$A$2:$A$616,$B141,BDD_Calendrier!$C$2:$C$616,"Rachat") | M141: =IF(L141=0,"",IFERROR(_xlfn.MINIFS(BDD_Calendrier!$D$2:$D$616,BDD_Calendrier!$A$2:$A$616,$B141,BDD_Calendrier!$C$2:$C$616,"Rachat",BDD_Calendrier!$D$2:$D$616,">="&TODAY()),"")) | N141: =IF(M141="","",IFERROR(INDEX(BDD_Calendrier!$E$2:$E$616,MATCH($B141&"|Rachat|"&TEXT(M141,"yyyy-mm-dd"),BDD_Calendrier!$I$2:$I$616,0)),"")) | O141: =IF(M141="","",IFERROR(INDEX(BDD_Calendrier!$H$2:$H$616,MATCH($B141&"|Rachat|"&TEXT(M141,"yyyy-mm-dd"),BDD_Calendrier!$I$2:$I$616,0)),"")) | P141: =IF(L141=0,"",_xlfn.MAXIFS(BDD_Calendrier!$D$2:$D$616,BDD_Calendrier!$A$2:$A$616,$B141,BDD_Calendrier!$C$2:$C$616,"Rachat")) | Q141: =IF($C141="","",IF($C141>TODAY(),"FUTUR",DATEDIF($C141,TODAY(),"m"))) | R141: =COUNTIF(BDD_Penalites!$A$2:$A$130,$B141) | S141: =IF(R141=0,"inconnue",INDEX(BDD_Penalites!$C$2:$C$130,MATCH($B141,BDD_Penalites!$A$2:$A$130,0))) | T141: =IF(R141=0,"",INDEX(BDD_Penalites!$M$2:$M$130,MATCH($B141,BDD_Penalites!$A$2:$A$130,0))) | U141: =IF(R141=0,0,INDEX(BDD_Penalites!$D$2:$D$130,MATCH($B141,BDD_Penalites!$A$2:$A$130,0))) | V141: =IF(R141=0,0,INDEX(BDD_Penalites!$E$2:$E$130,MATCH($B141,BDD_Penalites!$A$2:$A$130,0))) | W141: =IF(R141=0,0,INDEX(BDD_Penalites!$F$2:$F$130,MATCH($B141,BDD_Penalites!$A$2:$A$130,0))) | X141: =IF(R141=0,0,INDEX(BDD_Penalites!$G$2:$G$130,MATCH($B141,BDD_Penalites!$A$2:$A$130,0))) | Y141: =IF(R141=0,0,INDEX(BDD_Penalites!$H$2:$H$130,MATCH($B141,BDD_Penalites!$A$2:$A$130,0))) | Z141: =IF(R141=0,0,INDEX(BDD_Penalites!$I$2:$I$130,MATCH($B141,BDD_Penalites!$A$2:$A$130,0))) | AA141: =IF(R141=0,0,INDEX(BDD_Penalites!$J$2:$J$130,MATCH($B141,BDD_Penalites!$A$2:$A$130,0))) | AB141: =IF(R141=0,0,INDEX(BDD_Penalites!$K$2:$K$130,MATCH($B141,BDD_Penalites!$A$2:$A$130,0))) | AC141: =IF(R141=0,0,INDEX(BDD_Penalites!$L$2:$L$130,MATCH($B141,BDD_Penalites!$A$2:$A$130,0))) | AD141: =IF(OR($C141="",Q141="FUTUR"),"",_xlfn.IFS(Q141<U141,V141,Q141<W141,X141,Q141<Y141,Z141,Q141<AA141,AB141,TRUE,AC141))
A142: FIC PPG Retail | B142: ALZ013324662 | D142: =IF(H142=0,"Calendrier non disponible pour ce fonds — contacter la société de gestion.",IF(I142="","Calendrier connu jusqu'au "&TEXT(K142,"dd/mm/yyyy")&" — demander le calendrier à jour.","Cut-off : "&TEXT(I142,"dd/mm/yyyy")&" | VL : "&TEXT(J142,"dd/mm/yyyy"))) | E142: =IF(L142=0,"Calendrier non disponible pour ce fonds — contacter la société de gestion.",IF(M142="","Calendrier connu jusqu'au "&TEXT(P142,"dd/mm/yyyy")&" — demander le calendrier à jour.","Cut-off : "&TEXT(M142,"dd/mm/yyyy")&" | VL : "&TEXT(N142,"dd/mm/yyyy"))) | F142: =IF(L142=0,"Calendrier non disponible pour ce fonds.",IF(M142="","Calendrier connu jusqu'au "&TEXT(P142,"dd/mm/yyyy")&".",IF(O142="","Non précisé dans le calendrier pour cette échéance.","Réception : "&TEXT(O142,"dd/mm/yyyy")&" (suite au rachat du "&TEXT(N142,"dd/mm/yyyy")&")"))) | G142: =_xlfn.IFS(S142="aucune","Aucune pénalité de sortie."&IF(T142<>""," ("&T142&")",""),S142="manuel","⚠️ À VÉRIFIER MANUELLEMENT : "&T142,S142="inconnue","Pénalité non renseignée — vérifier la notice / DICI du fonds.",$C142="","Saisir une date d'investissement pour statuer sur la pénalité.",Q142="FUTUR","Date d'investissement postérieure à aujourd'hui — vérifier la saisie.",AD142>0,"⚠️ CONCERNÉ : pénalité de "&AD142&"% (détention "&Q142&" mois). "&T142,TRUE,"Non concerné (détention "&Q142&" mois). "&T142) | H142: =COUNTIFS(BDD_Calendrier!$A$2:$A$616,$B142,BDD_Calendrier!$C$2:$C$616,"Souscription") | I142: =IF(H142=0,"",IFERROR(_xlfn.MINIFS(BDD_Calendrier!$D$2:$D$616,BDD_Calendrier!$A$2:$A$616,$B142,BDD_Calendrier!$C$2:$C$616,"Souscription",BDD_Calendrier!$D$2:$D$616,">="&TODAY()),"")) | J142: =IF(I142="","",IFERROR(INDEX(BDD_Calendrier!$E$2:$E$616,MATCH($B142&"|Souscription|"&TEXT(I142,"yyyy-mm-dd"),BDD_Calendrier!$I$2:$I$616,0)),"")) | K142: =IF(H142=0,"",_xlfn.MAXIFS(BDD_Calendrier!$D$2:$D$616,BDD_Calendrier!$A$2:$A$616,$B142,BDD_Calendrier!$C$2:$C$616,"Souscription")) | L142: =COUNTIFS(BDD_Calendrier!$A$2:$A$616,$B142,BDD_Calendrier!$C$2:$C$616,"Rachat") | M142: =IF(L142=0,"",IFERROR(_xlfn.MINIFS(BDD_Calendrier!$D$2:$D$616,BDD_Calendrier!$A$2:$A$616,$B142,BDD_Calendrier!$C$2:$C$616,"Rachat",BDD_Calendrier!$D$2:$D$616,">="&TODAY()),"")) | N142: =IF(M142="","",IFERROR(INDEX(BDD_Calendrier!$E$2:$E$616,MATCH($B142&"|Rachat|"&TEXT(M142,"yyyy-mm-dd"),BDD_Calendrier!$I$2:$I$616,0)),"")) | O142: =IF(M142="","",IFERROR(INDEX(BDD_Calendrier!$H$2:$H$616,MATCH($B142&"|Rachat|"&TEXT(M142,"yyyy-mm-dd"),BDD_Calendrier!$I$2:$I$616,0)),"")) | P142: =IF(L142=0,"",_xlfn.MAXIFS(BDD_Calendrier!$D$2:$D$616,BDD_Calendrier!$A$2:$A$616,$B142,BDD_Calendrier!$C$2:$C$616,"Rachat")) | Q142: =IF($C142="","",IF($C142>TODAY(),"FUTUR",DATEDIF($C142,TODAY(),"m"))) | R142: =COUNTIF(BDD_Penalites!$A$2:$A$130,$B142) | S142: =IF(R142=0,"inconnue",INDEX(BDD_Penalites!$C$2:$C$130,MATCH($B142,BDD_Penalites!$A$2:$A$130,0))) | T142: =IF(R142=0,"",INDEX(BDD_Penalites!$M$2:$M$130,MATCH($B142,BDD_Penalites!$A$2:$A$130,0))) | U142: =IF(R142=0,0,INDEX(BDD_Penalites!$D$2:$D$130,MATCH($B142,BDD_Penalites!$A$2:$A$130,0))) | V142: =IF(R142=0,0,INDEX(BDD_Penalites!$E$2:$E$130,MATCH($B142,BDD_Penalites!$A$2:$A$130,0))) | W142: =IF(R142=0,0,INDEX(BDD_Penalites!$F$2:$F$130,MATCH($B142,BDD_Penalites!$A$2:$A$130,0))) | X142: =IF(R142=0,0,INDEX(BDD_Penalites!$G$2:$G$130,MATCH($B142,BDD_Penalites!$A$2:$A$130,0))) | Y142: =IF(R142=0,0,INDEX(BDD_Penalites!$H$2:$H$130,MATCH($B142,BDD_Penalites!$A$2:$A$130,0))) | Z142: =IF(R142=0,0,INDEX(BDD_Penalites!$I$2:$I$130,MATCH($B142,BDD_Penalites!$A$2:$A$130,0))) | AA142: =IF(R142=0,0,INDEX(BDD_Penalites!$J$2:$J$130,MATCH($B142,BDD_Penalites!$A$2:$A$130,0))) | AB142: =IF(R142=0,0,INDEX(BDD_Penalites!$K$2:$K$130,MATCH($B142,BDD_Penalites!$A$2:$A$130,0))) | AC142: =IF(R142=0,0,INDEX(BDD_Penalites!$L$2:$L$130,MATCH($B142,BDD_Penalites!$A$2:$A$130,0))) | AD142: =IF(OR($C142="",Q142="FUTUR"),"",_xlfn.IFS(Q142<U142,V142,Q142<W142,X142,Q142<Y142,Z142,Q142<AA142,AB142,TRUE,AC142))
A143: OPPCI PPG Retail A | B143: FR0013324662 | D143: =IF(H143=0,"Calendrier non disponible pour ce fonds — contacter la société de gestion.",IF(I143="","Calendrier connu jusqu'au "&TEXT(K143,"dd/mm/yyyy")&" — demander le calendrier à jour.","Cut-off : "&TEXT(I143,"dd/mm/yyyy")&" | VL : "&TEXT(J143,"dd/mm/yyyy"))) | E143: =IF(L143=0,"Calendrier non disponible pour ce fonds — contacter la société de gestion.",IF(M143="","Calendrier connu jusqu'au "&TEXT(P143,"dd/mm/yyyy")&" — demander le calendrier à jour.","Cut-off : "&TEXT(M143,"dd/mm/yyyy")&" | VL : "&TEXT(N143,"dd/mm/yyyy"))) | F143: =IF(L143=0,"Calendrier non disponible pour ce fonds.",IF(M143="","Calendrier connu jusqu'au "&TEXT(P143,"dd/mm/yyyy")&".",IF(O143="","Non précisé dans le calendrier pour cette échéance.","Réception : "&TEXT(O143,"dd/mm/yyyy")&" (suite au rachat du "&TEXT(N143,"dd/mm/yyyy")&")"))) | G143: =_xlfn.IFS(S143="aucune","Aucune pénalité de sortie."&IF(T143<>""," ("&T143&")",""),S143="manuel","⚠️ À VÉRIFIER MANUELLEMENT : "&T143,S143="inconnue","Pénalité non renseignée — vérifier la notice / DICI du fonds.",$C143="","Saisir une date d'investissement pour statuer sur la pénalité.",Q143="FUTUR","Date d'investissement postérieure à aujourd'hui — vérifier la saisie.",AD143>0,"⚠️ CONCERNÉ : pénalité de "&AD143&"% (détention "&Q143&" mois). "&T143,TRUE,"Non concerné (détention "&Q143&" mois). "&T143) | H143: =COUNTIFS(BDD_Calendrier!$A$2:$A$616,$B143,BDD_Calendrier!$C$2:$C$616,"Souscription") | I143: =IF(H143=0,"",IFERROR(_xlfn.MINIFS(BDD_Calendrier!$D$2:$D$616,BDD_Calendrier!$A$2:$A$616,$B143,BDD_Calendrier!$C$2:$C$616,"Souscription",BDD_Calendrier!$D$2:$D$616,">="&TODAY()),"")) | J143: =IF(I143="","",IFERROR(INDEX(BDD_Calendrier!$E$2:$E$616,MATCH($B143&"|Souscription|"&TEXT(I143,"yyyy-mm-dd"),BDD_Calendrier!$I$2:$I$616,0)),"")) | K143: =IF(H143=0,"",_xlfn.MAXIFS(BDD_Calendrier!$D$2:$D$616,BDD_Calendrier!$A$2:$A$616,$B143,BDD_Calendrier!$C$2:$C$616,"Souscription")) | L143: =COUNTIFS(BDD_Calendrier!$A$2:$A$616,$B143,BDD_Calendrier!$C$2:$C$616,"Rachat") | M143: =IF(L143=0,"",IFERROR(_xlfn.MINIFS(BDD_Calendrier!$D$2:$D$616,BDD_Calendrier!$A$2:$A$616,$B143,BDD_Calendrier!$C$2:$C$616,"Rachat",BDD_Calendrier!$D$2:$D$616,">="&TODAY()),"")) | N143: =IF(M143="","",IFERROR(INDEX(BDD_Calendrier!$E$2:$E$616,MATCH($B143&"|Rachat|"&TEXT(M143,"yyyy-mm-dd"),BDD_Calendrier!$I$2:$I$616,0)),"")) | O143: =IF(M143="","",IFERROR(INDEX(BDD_Calendrier!$H$2:$H$616,MATCH($B143&"|Rachat|"&TEXT(M143,"yyyy-mm-dd"),BDD_Calendrier!$I$2:$I$616,0)),"")) | P143: =IF(L143=0,"",_xlfn.MAXIFS(BDD_Calendrier!$D$2:$D$616,BDD_Calendrier!$A$2:$A$616,$B143,BDD_Calendrier!$C$2:$C$616,"Rachat")) | Q143: =IF($C143="","",IF($C143>TODAY(),"FUTUR",DATEDIF($C143,TODAY(),"m"))) | R143: =COUNTIF(BDD_Penalites!$A$2:$A$130,$B143) | S143: =IF(R143=0,"inconnue",INDEX(BDD_Penalites!$C$2:$C$130,MATCH($B143,BDD_Penalites!$A$2:$A$130,0))) | T143: =IF(R143=0,"",INDEX(BDD_Penalites!$M$2:$M$130,MATCH($B143,BDD_Penalites!$A$2:$A$130,0))) | U143: =IF(R143=0,0,INDEX(BDD_Penalites!$D$2:$D$130,MATCH($B143,BDD_Penalites!$A$2:$A$130,0))) | V143: =IF(R143=0,0,INDEX(BDD_Penalites!$E$2:$E$130,MATCH($B143,BDD_Penalites!$A$2:$A$130,0))) | W143: =IF(R143=0,0,INDEX(BDD_Penalites!$F$2:$F$130,MATCH($B143,BDD_Penalites!$A$2:$A$130,0))) | X143: =IF(R143=0,0,INDEX(BDD_Penalites!$G$2:$G$130,MATCH($B143,BDD_Penalites!$A$2:$A$130,0))) | Y143: =IF(R143=0,0,INDEX(BDD_Penalites!$H$2:$H$130,MATCH($B143,BDD_Penalites!$A$2:$A$130,0))) | Z143: =IF(R143=0,0,INDEX(BDD_Penalites!$I$2:$I$130,MATCH($B143,BDD_Penalites!$A$2:$A$130,0))) | AA143: =IF(R143=0,0,INDEX(BDD_Penalites!$J$2:$J$130,MATCH($B143,BDD_Penalites!$A$2:$A$130,0))) | AB143: =IF(R143=0,0,INDEX(BDD_Penalites!$K$2:$K$130,MATCH($B143,BDD_Penalites!$A$2:$A$130,0))) | AC143: =IF(R143=0,0,INDEX(BDD_Penalites!$L$2:$L$130,MATCH($B143,BDD_Penalites!$A$2:$A$130,0))) | AD143: =IF(OR($C143="",Q143="FUTUR"),"",_xlfn.IFS(Q143<U143,V143,Q143<W143,X143,Q143<Y143,Z143,Q143<AA143,AB143,TRUE,AC143))
A144: OPPCI PPG Retail B | B144: FR0013324670 | D144: =IF(H144=0,"Calendrier non disponible pour ce fonds — contacter la société de gestion.",IF(I144="","Calendrier connu jusqu'au "&TEXT(K144,"dd/mm/yyyy")&" — demander le calendrier à jour.","Cut-off : "&TEXT(I144,"dd/mm/yyyy")&" | VL : "&TEXT(J144,"dd/mm/yyyy"))) | E144: =IF(L144=0,"Calendrier non disponible pour ce fonds — contacter la société de gestion.",IF(M144="","Calendrier connu jusqu'au "&TEXT(P144,"dd/mm/yyyy")&" — demander le calendrier à jour.","Cut-off : "&TEXT(M144,"dd/mm/yyyy")&" | VL : "&TEXT(N144,"dd/mm/yyyy"))) | F144: =IF(L144=0,"Calendrier non disponible pour ce fonds.",IF(M144="","Calendrier connu jusqu'au "&TEXT(P144,"dd/mm/yyyy")&".",IF(O144="","Non précisé dans le calendrier pour cette échéance.","Réception : "&TEXT(O144,"dd/mm/yyyy")&" (suite au rachat du "&TEXT(N144,"dd/mm/yyyy")&")"))) | G144: =_xlfn.IFS(S144="aucune","Aucune pénalité de sortie."&IF(T144<>""," ("&T144&")",""),S144="manuel","⚠️ À VÉRIFIER MANUELLEMENT : "&T144,S144="inconnue","Pénalité non renseignée — vérifier la notice / DICI du fonds.",$C144="","Saisir une date d'investissement pour statuer sur la pénalité.",Q144="FUTUR","Date d'investissement postérieure à aujourd'hui — vérifier la saisie.",AD144>0,"⚠️ CONCERNÉ : pénalité de "&AD144&"% (détention "&Q144&" mois). "&T144,TRUE,"Non concerné (détention "&Q144&" mois). "&T144) | H144: =COUNTIFS(BDD_Calendrier!$A$2:$A$616,$B144,BDD_Calendrier!$C$2:$C$616,"Souscription") | I144: =IF(H144=0,"",IFERROR(_xlfn.MINIFS(BDD_Calendrier!$D$2:$D$616,BDD_Calendrier!$A$2:$A$616,$B144,BDD_Calendrier!$C$2:$C$616,"Souscription",BDD_Calendrier!$D$2:$D$616,">="&TODAY()),"")) | J144: =IF(I144="","",IFERROR(INDEX(BDD_Calendrier!$E$2:$E$616,MATCH($B144&"|Souscription|"&TEXT(I144,"yyyy-mm-dd"),BDD_Calendrier!$I$2:$I$616,0)),"")) | K144: =IF(H144=0,"",_xlfn.MAXIFS(BDD_Calendrier!$D$2:$D$616,BDD_Calendrier!$A$2:$A$616,$B144,BDD_Calendrier!$C$2:$C$616,"Souscription")) | L144: =COUNTIFS(BDD_Calendrier!$A$2:$A$616,$B144,BDD_Calendrier!$C$2:$C$616,"Rachat") | M144: =IF(L144=0,"",IFERROR(_xlfn.MINIFS(BDD_Calendrier!$D$2:$D$616,BDD_Calendrier!$A$2:$A$616,$B144,BDD_Calendrier!$C$2:$C$616,"Rachat",BDD_Calendrier!$D$2:$D$616,">="&TODAY()),"")) | N144: =IF(M144="","",IFERROR(INDEX(BDD_Calendrier!$E$2:$E$616,MATCH($B144&"|Rachat|"&TEXT(M144,"yyyy-mm-dd"),BDD_Calendrier!$I$2:$I$616,0)),"")) | O144: =IF(M144="","",IFERROR(INDEX(BDD_Calendrier!$H$2:$H$616,MATCH($B144&"|Rachat|"&TEXT(M144,"yyyy-mm-dd"),BDD_Calendrier!$I$2:$I$616,0)),"")) | P144: =IF(L144=0,"",_xlfn.MAXIFS(BDD_Calendrier!$D$2:$D$616,BDD_Calendrier!$A$2:$A$616,$B144,BDD_Calendrier!$C$2:$C$616,"Rachat")) | Q144: =IF($C144="","",IF($C144>TODAY(),"FUTUR",DATEDIF($C144,TODAY(),"m"))) | R144: =COUNTIF(BDD_Penalites!$A$2:$A$130,$B144) | S144: =IF(R144=0,"inconnue",INDEX(BDD_Penalites!$C$2:$C$130,MATCH($B144,BDD_Penalites!$A$2:$A$130,0))) | T144: =IF(R144=0,"",INDEX(BDD_Penalites!$M$2:$M$130,MATCH($B144,BDD_Penalites!$A$2:$A$130,0))) | U144: =IF(R144=0,0,INDEX(BDD_Penalites!$D$2:$D$130,MATCH($B144,BDD_Penalites!$A$2:$A$130,0))) | V144: =IF(R144=0,0,INDEX(BDD_Penalites!$E$2:$E$130,MATCH($B144,BDD_Penalites!$A$2:$A$130,0))) | W144: =IF(R144=0,0,INDEX(BDD_Penalites!$F$2:$F$130,MATCH($B144,BDD_Penalites!$A$2:$A$130,0))) | X144: =IF(R144=0,0,INDEX(BDD_Penalites!$G$2:$G$130,MATCH($B144,BDD_Penalites!$A$2:$A$130,0))) | Y144: =IF(R144=0,0,INDEX(BDD_Penalites!$H$2:$H$130,MATCH($B144,BDD_Penalites!$A$2:$A$130,0))) | Z144: =IF(R144=0,0,INDEX(BDD_Penalites!$I$2:$I$130,MATCH($B144,BDD_Penalites!$A$2:$A$130,0))) | AA144: =IF(R144=0,0,INDEX(BDD_Penalites!$J$2:$J$130,MATCH($B144,BDD_Penalites!$A$2:$A$130,0))) | AB144: =IF(R144=0,0,INDEX(BDD_Penalites!$K$2:$K$130,MATCH($B144,BDD_Penalites!$A$2:$A$130,0))) | AC144: =IF(R144=0,0,INDEX(BDD_Penalites!$L$2:$L$130,MATCH($B144,BDD_Penalites!$A$2:$A$130,0))) | AD144: =IF(OR($C144="",Q144="FUTUR"),"",_xlfn.IFS(Q144<U144,V144,Q144<W144,X144,Q144<Y144,Z144,Q144<AA144,AB144,TRUE,AC144))
A145: PPG Croissance A | B145: FR0013265683 | D145: =IF(H145=0,"Calendrier non disponible pour ce fonds — contacter la société de gestion.",IF(I145="","Calendrier connu jusqu'au "&TEXT(K145,"dd/mm/yyyy")&" — demander le calendrier à jour.","Cut-off : "&TEXT(I145,"dd/mm/yyyy")&" | VL : "&TEXT(J145,"dd/mm/yyyy"))) | E145: =IF(L145=0,"Calendrier non disponible pour ce fonds — contacter la société de gestion.",IF(M145="","Calendrier connu jusqu'au "&TEXT(P145,"dd/mm/yyyy")&" — demander le calendrier à jour.","Cut-off : "&TEXT(M145,"dd/mm/yyyy")&" | VL : "&TEXT(N145,"dd/mm/yyyy"))) | F145: =IF(L145=0,"Calendrier non disponible pour ce fonds.",IF(M145="","Calendrier connu jusqu'au "&TEXT(P145,"dd/mm/yyyy")&".",IF(O145="","Non précisé dans le calendrier pour cette échéance.","Réception : "&TEXT(O145,"dd/mm/yyyy")&" (suite au rachat du "&TEXT(N145,"dd/mm/yyyy")&")"))) | G145: =_xlfn.IFS(S145="aucune","Aucune pénalité de sortie."&IF(T145<>""," ("&T145&")",""),S145="manuel","⚠️ À VÉRIFIER MANUELLEMENT : "&T145,S145="inconnue","Pénalité non renseignée — vérifier la notice / DICI du fonds.",$C145="","Saisir une date d'investissement pour statuer sur la pénalité.",Q145="FUTUR","Date d'investissement postérieure à aujourd'hui — vérifier la saisie.",AD145>0,"⚠️ CONCERNÉ : pénalité de "&AD145&"% (détention "&Q145&" mois). "&T145,TRUE,"Non concerné (détention "&Q145&" mois). "&T145) | H145: =COUNTIFS(BDD_Calendrier!$A$2:$A$616,$B145,BDD_Calendrier!$C$2:$C$616,"Souscription") | I145: =IF(H145=0,"",IFERROR(_xlfn.MINIFS(BDD_Calendrier!$D$2:$D$616,BDD_Calendrier!$A$2:$A$616,$B145,BDD_Calendrier!$C$2:$C$616,"Souscription",BDD_Calendrier!$D$2:$D$616,">="&TODAY()),"")) | J145: =IF(I145="","",IFERROR(INDEX(BDD_Calendrier!$E$2:$E$616,MATCH($B145&"|Souscription|"&TEXT(I145,"yyyy-mm-dd"),BDD_Calendrier!$I$2:$I$616,0)),"")) | K145: =IF(H145=0,"",_xlfn.MAXIFS(BDD_Calendrier!$D$2:$D$616,BDD_Calendrier!$A$2:$A$616,$B145,BDD_Calendrier!$C$2:$C$616,"Souscription")) | L145: =COUNTIFS(BDD_Calendrier!$A$2:$A$616,$B145,BDD_Calendrier!$C$2:$C$616,"Rachat") | M145: =IF(L145=0,"",IFERROR(_xlfn.MINIFS(BDD_Calendrier!$D$2:$D$616,BDD_Calendrier!$A$2:$A$616,$B145,BDD_Calendrier!$C$2:$C$616,"Rachat",BDD_Calendrier!$D$2:$D$616,">="&TODAY()),"")) | N145: =IF(M145="","",IFERROR(INDEX(BDD_Calendrier!$E$2:$E$616,MATCH($B145&"|Rachat|"&TEXT(M145,"yyyy-mm-dd"),BDD_Calendrier!$I$2:$I$616,0)),"")) | O145: =IF(M145="","",IFERROR(INDEX(BDD_Calendrier!$H$2:$H$616,MATCH($B145&"|Rachat|"&TEXT(M145,"yyyy-mm-dd"),BDD_Calendrier!$I$2:$I$616,0)),"")) | P145: =IF(L145=0,"",_xlfn.MAXIFS(BDD_Calendrier!$D$2:$D$616,BDD_Calendrier!$A$2:$A$616,$B145,BDD_Calendrier!$C$2:$C$616,"Rachat")) | Q145: =IF($C145="","",IF($C145>TODAY(),"FUTUR",DATEDIF($C145,TODAY(),"m"))) | R145: =COUNTIF(BDD_Penalites!$A$2:$A$130,$B145) | S145: =IF(R145=0,"inconnue",INDEX(BDD_Penalites!$C$2:$C$130,MATCH($B145,BDD_Penalites!$A$2:$A$130,0))) | T145: =IF(R145=0,"",INDEX(BDD_Penalites!$M$2:$M$130,MATCH($B145,BDD_Penalites!$A$2:$A$130,0))) | U145: =IF(R145=0,0,INDEX(BDD_Penalites!$D$2:$D$130,MATCH($B145,BDD_Penalites!$A$2:$A$130,0))) | V145: =IF(R145=0,0,INDEX(BDD_Penalites!$E$2:$E$130,MATCH($B145,BDD_Penalites!$A$2:$A$130,0))) | W145: =IF(R145=0,0,INDEX(BDD_Penalites!$F$2:$F$130,MATCH($B145,BDD_Penalites!$A$2:$A$130,0))) | X145: =IF(R145=0,0,INDEX(BDD_Penalites!$G$2:$G$130,MATCH($B145,BDD_Penalites!$A$2:$A$130,0))) | Y145: =IF(R145=0,0,INDEX(BDD_Penalites!$H$2:$H$130,MATCH($B145,BDD_Penalites!$A$2:$A$130,0))) | Z145: =IF(R145=0,0,INDEX(BDD_Penalites!$I$2:$I$130,MATCH($B145,BDD_Penalites!$A$2:$A$130,0))) | AA145: =IF(R145=0,0,INDEX(BDD_Penalites!$J$2:$J$130,MATCH($B145,BDD_Penalites!$A$2:$A$130,0))) | AB145: =IF(R145=0,0,INDEX(BDD_Penalites!$K$2:$K$130,MATCH($B145,BDD_Penalites!$A$2:$A$130,0))) | AC145: =IF(R145=0,0,INDEX(BDD_Penalites!$L$2:$L$130,MATCH($B145,BDD_Penalites!$A$2:$A$130,0))) | AD145: =IF(OR($C145="",Q145="FUTUR"),"",_xlfn.IFS(Q145<U145,V145,Q145<W145,X145,Q145<Y145,Z145,Q145<AA145,AB145,TRUE,AC145))
A146: PPG Croissance B | B146: FR001400LW94 | D146: =IF(H146=0,"Calendrier non disponible pour ce fonds — contacter la société de gestion.",IF(I146="","Calendrier connu jusqu'au "&TEXT(K146,"dd/mm/yyyy")&" — demander le calendrier à jour.","Cut-off : "&TEXT(I146,"dd/mm/yyyy")&" | VL : "&TEXT(J146,"dd/mm/yyyy"))) | E146: =IF(L146=0,"Calendrier non disponible pour ce fonds — contacter la société de gestion.",IF(M146="","Calendrier connu jusqu'au "&TEXT(P146,"dd/mm/yyyy")&" — demander le calendrier à jour.","Cut-off : "&TEXT(M146,"dd/mm/yyyy")&" | VL : "&TEXT(N146,"dd/mm/yyyy"))) | F146: =IF(L146=0,"Calendrier non disponible pour ce fonds.",IF(M146="","Calendrier connu jusqu'au "&TEXT(P146,"dd/mm/yyyy")&".",IF(O146="","Non précisé dans le calendrier pour cette échéance.","Réception : "&TEXT(O146,"dd/mm/yyyy")&" (suite au rachat du "&TEXT(N146,"dd/mm/yyyy")&")"))) | G146: =_xlfn.IFS(S146="aucune","Aucune pénalité de sortie."&IF(T146<>""," ("&T146&")",""),S146="manuel","⚠️ À VÉRIFIER MANUELLEMENT : "&T146,S146="inconnue","Pénalité non renseignée — vérifier la notice / DICI du fonds.",$C146="","Saisir une date d'investissement pour statuer sur la pénalité.",Q146="FUTUR","Date d'investissement postérieure à aujourd'hui — vérifier la saisie.",AD146>0,"⚠️ CONCERNÉ : pénalité de "&AD146&"% (détention "&Q146&" mois). "&T146,TRUE,"Non concerné (détention "&Q146&" mois). "&T146) | H146: =COUNTIFS(BDD_Calendrier!$A$2:$A$616,$B146,BDD_Calendrier!$C$2:$C$616,"Souscription") | I146: =IF(H146=0,"",IFERROR(_xlfn.MINIFS(BDD_Calendrier!$D$2:$D$616,BDD_Calendrier!$A$2:$A$616,$B146,BDD_Calendrier!$C$2:$C$616,"Souscription",BDD_Calendrier!$D$2:$D$616,">="&TODAY()),"")) | J146: =IF(I146="","",IFERROR(INDEX(BDD_Calendrier!$E$2:$E$616,MATCH($B146&"|Souscription|"&TEXT(I146,"yyyy-mm-dd"),BDD_Calendrier!$I$2:$I$616,0)),"")) | K146: =IF(H146=0,"",_xlfn.MAXIFS(BDD_Calendrier!$D$2:$D$616,BDD_Calendrier!$A$2:$A$616,$B146,BDD_Calendrier!$C$2:$C$616,"Souscription")) | L146: =COUNTIFS(BDD_Calendrier!$A$2:$A$616,$B146,BDD_Calendrier!$C$2:$C$616,"Rachat") | M146: =IF(L146=0,"",IFERROR(_xlfn.MINIFS(BDD_Calendrier!$D$2:$D$616,BDD_Calendrier!$A$2:$A$616,$B146,BDD_Calendrier!$C$2:$C$616,"Rachat",BDD_Calendrier!$D$2:$D$616,">="&TODAY()),"")) | N146: =IF(M146="","",IFERROR(INDEX(BDD_Calendrier!$E$2:$E$616,MATCH($B146&"|Rachat|"&TEXT(M146,"yyyy-mm-dd"),BDD_Calendrier!$I$2:$I$616,0)),"")) | O146: =IF(M146="","",IFERROR(INDEX(BDD_Calendrier!$H$2:$H$616,MATCH($B146&"|Rachat|"&TEXT(M146,"yyyy-mm-dd"),BDD_Calendrier!$I$2:$I$616,0)),"")) | P146: =IF(L146=0,"",_xlfn.MAXIFS(BDD_Calendrier!$D$2:$D$616,BDD_Calendrier!$A$2:$A$616,$B146,BDD_Calendrier!$C$2:$C$616,"Rachat")) | Q146: =IF($C146="","",IF($C146>TODAY(),"FUTUR",DATEDIF($C146,TODAY(),"m"))) | R146: =COUNTIF(BDD_Penalites!$A$2:$A$130,$B146) | S146: =IF(R146=0,"inconnue",INDEX(BDD_Penalites!$C$2:$C$130,MATCH($B146,BDD_Penalites!$A$2:$A$130,0))) | T146: =IF(R146=0,"",INDEX(BDD_Penalites!$M$2:$M$130,MATCH($B146,BDD_Penalites!$A$2:$A$130,0))) | U146: =IF(R146=0,0,INDEX(BDD_Penalites!$D$2:$D$130,MATCH($B146,BDD_Penalites!$A$2:$A$130,0))) | V146: =IF(R146=0,0,INDEX(BDD_Penalites!$E$2:$E$130,MATCH($B146,BDD_Penalites!$A$2:$A$130,0))) | W146: =IF(R146=0,0,INDEX(BDD_Penalites!$F$2:$F$130,MATCH($B146,BDD_Penalites!$A$2:$A$130,0))) | X146: =IF(R146=0,0,INDEX(BDD_Penalites!$G$2:$G$130,MATCH($B146,BDD_Penalites!$A$2:$A$130,0))) | Y146: =IF(R146=0,0,INDEX(BDD_Penalites!$H$2:$H$130,MATCH($B146,BDD_Penalites!$A$2:$A$130,0))) | Z146: =IF(R146=0,0,INDEX(BDD_Penalites!$I$2:$I$130,MATCH($B146,BDD_Penalites!$A$2:$A$130,0))) | AA146: =IF(R146=0,0,INDEX(BDD_Penalites!$J$2:$J$130,MATCH($B146,BDD_Penalites!$A$2:$A$130,0))) | AB146: =IF(R146=0,0,INDEX(BDD_Penalites!$K$2:$K$130,MATCH($B146,BDD_Penalites!$A$2:$A$130,0))) | AC146: =IF(R146=0,0,INDEX(BDD_Penalites!$L$2:$L$130,MATCH($B146,BDD_Penalites!$A$2:$A$130,0))) | AD146: =IF(OR($C146="",Q146="FUTUR"),"",_xlfn.IFS(Q146<U146,V146,Q146<W146,X146,Q146<Y146,Z146,Q146<AA146,AB146,TRUE,AC146))
A147: FCPR PPG Valeur Immo - Part A - EUR | B147: FR001400C5U8 | D147: =IF(H147=0,"Calendrier non disponible pour ce fonds — contacter la société de gestion.",IF(I147="","Calendrier connu jusqu'au "&TEXT(K147,"dd/mm/yyyy")&" — demander le calendrier à jour.","Cut-off : "&TEXT(I147,"dd/mm/yyyy")&" | VL : "&TEXT(J147,"dd/mm/yyyy"))) | E147: =IF(L147=0,"Calendrier non disponible pour ce fonds — contacter la société de gestion.",IF(M147="","Calendrier connu jusqu'au "&TEXT(P147,"dd/mm/yyyy")&" — demander le calendrier à jour.","Cut-off : "&TEXT(M147,"dd/mm/yyyy")&" | VL : "&TEXT(N147,"dd/mm/yyyy"))) | F147: =IF(L147=0,"Calendrier non disponible pour ce fonds.",IF(M147="","Calendrier connu jusqu'au "&TEXT(P147,"dd/mm/yyyy")&".",IF(O147="","Non précisé dans le calendrier pour cette échéance.","Réception : "&TEXT(O147,"dd/mm/yyyy")&" (suite au rachat du "&TEXT(N147,"dd/mm/yyyy")&")"))) | G147: =_xlfn.IFS(S147="aucune","Aucune pénalité de sortie."&IF(T147<>""," ("&T147&")",""),S147="manuel","⚠️ À VÉRIFIER MANUELLEMENT : "&T147,S147="inconnue","Pénalité non renseignée — vérifier la notice / DICI du fonds.",$C147="","Saisir une date d'investissement pour statuer sur la pénalité.",Q147="FUTUR","Date d'investissement postérieure à aujourd'hui — vérifier la saisie.",AD147>0,"⚠️ CONCERNÉ : pénalité de "&AD147&"% (détention "&Q147&" mois). "&T147,TRUE,"Non concerné (détention "&Q147&" mois). "&T147) | H147: =COUNTIFS(BDD_Calendrier!$A$2:$A$616,$B147,BDD_Calendrier!$C$2:$C$616,"Souscription") | I147: =IF(H147=0,"",IFERROR(_xlfn.MINIFS(BDD_Calendrier!$D$2:$D$616,BDD_Calendrier!$A$2:$A$616,$B147,BDD_Calendrier!$C$2:$C$616,"Souscription",BDD_Calendrier!$D$2:$D$616,">="&TODAY()),"")) | J147: =IF(I147="","",IFERROR(INDEX(BDD_Calendrier!$E$2:$E$616,MATCH($B147&"|Souscription|"&TEXT(I147,"yyyy-mm-dd"),BDD_Calendrier!$I$2:$I$616,0)),"")) | K147: =IF(H147=0,"",_xlfn.MAXIFS(BDD_Calendrier!$D$2:$D$616,BDD_Calendrier!$A$2:$A$616,$B147,BDD_Calendrier!$C$2:$C$616,"Souscription")) | L147: =COUNTIFS(BDD_Calendrier!$A$2:$A$616,$B147,BDD_Calendrier!$C$2:$C$616,"Rachat") | M147: =IF(L147=0,"",IFERROR(_xlfn.MINIFS(BDD_Calendrier!$D$2:$D$616,BDD_Calendrier!$A$2:$A$616,$B147,BDD_Calendrier!$C$2:$C$616,"Rachat",BDD_Calendrier!$D$2:$D$616,">="&TODAY()),"")) | N147: =IF(M147="","",IFERROR(INDEX(BDD_Calendrier!$E$2:$E$616,MATCH($B147&"|Rachat|"&TEXT(M147,"yyyy-mm-dd"),BDD_Calendrier!$I$2:$I$616,0)),"")) | O147: =IF(M147="","",IFERROR(INDEX(BDD_Calendrier!$H$2:$H$616,MATCH($B147&"|Rachat|"&TEXT(M147,"yyyy-mm-dd"),BDD_Calendrier!$I$2:$I$616,0)),"")) | P147: =IF(L147=0,"",_xlfn.MAXIFS(BDD_Calendrier!$D$2:$D$616,BDD_Calendrier!$A$2:$A$616,$B147,BDD_Calendrier!$C$2:$C$616,"Rachat")) | Q147: =IF($C147="","",IF($C147>TODAY(),"FUTUR",DATEDIF($C147,TODAY(),"m"))) | R147: =COUNTIF(BDD_Penalites!$A$2:$A$130,$B147) | S147: =IF(R147=0,"inconnue",INDEX(BDD_Penalites!$C$2:$C$130,MATCH($B147,BDD_Penalites!$A$2:$A$130,0))) | T147: =IF(R147=0,"",INDEX(BDD_Penalites!$M$2:$M$130,MATCH($B147,BDD_Penalites!$A$2:$A$130,0))) | U147: =IF(R147=0,0,INDEX(BDD_Penalites!$D$2:$D$130,MATCH($B147,BDD_Penalites!$A$2:$A$130,0))) | V147: =IF(R147=0,0,INDEX(BDD_Penalites!$E$2:$E$130,MATCH($B147,BDD_Penalites!$A$2:$A$130,0))) | W147: =IF(R147=0,0,INDEX(BDD_Penalites!$F$2:$F$130,MATCH($B147,BDD_Penalites!$A$2:$A$130,0))) | X147: =IF(R147=0,0,INDEX(BDD_Penalites!$G$2:$G$130,MATCH($B147,BDD_Penalites!$A$2:$A$130,0))) | Y147: =IF(R147=0,0,INDEX(BDD_Penalites!$H$2:$H$130,MATCH($B147,BDD_Penalites!$A$2:$A$130,0))) | Z147: =IF(R147=0,0,INDEX(BDD_Penalites!$I$2:$I$130,MATCH($B147,BDD_Penalites!$A$2:$A$130,0))) | AA147: =IF(R147=0,0,INDEX(BDD_Penalites!$J$2:$J$130,MATCH($B147,BDD_Penalites!$A$2:$A$130,0))) | AB147: =IF(R147=0,0,INDEX(BDD_Penalites!$K$2:$K$130,MATCH($B147,BDD_Penalites!$A$2:$A$130,0))) | AC147: =IF(R147=0,0,INDEX(BDD_Penalites!$L$2:$L$130,MATCH($B147,BDD_Penalites!$A$2:$A$130,0))) | AD147: =IF(OR($C147="",Q147="FUTUR"),"",_xlfn.IFS(Q147<U147,V147,Q147<W147,X147,Q147<Y147,Z147,Q147<AA147,AB147,TRUE,AC147))
A148: FCPR PPG Valeur Immo - Part B | B148: FR001400C5V6 | D148: =IF(H148=0,"Calendrier non disponible pour ce fonds — contacter la société de gestion.",IF(I148="","Calendrier connu jusqu'au "&TEXT(K148,"dd/mm/yyyy")&" — demander le calendrier à jour.","Cut-off : "&TEXT(I148,"dd/mm/yyyy")&" | VL : "&TEXT(J148,"dd/mm/yyyy"))) | E148: =IF(L148=0,"Calendrier non disponible pour ce fonds — contacter la société de gestion.",IF(M148="","Calendrier connu jusqu'au "&TEXT(P148,"dd/mm/yyyy")&" — demander le calendrier à jour.","Cut-off : "&TEXT(M148,"dd/mm/yyyy")&" | VL : "&TEXT(N148,"dd/mm/yyyy"))) | F148: =IF(L148=0,"Calendrier non disponible pour ce fonds.",IF(M148="","Calendrier connu jusqu'au "&TEXT(P148,"dd/mm/yyyy")&".",IF(O148="","Non précisé dans le calendrier pour cette échéance.","Réception : "&TEXT(O148,"dd/mm/yyyy")&" (suite au rachat du "&TEXT(N148,"dd/mm/yyyy")&")"))) | G148: =_xlfn.IFS(S148="aucune","Aucune pénalité de sortie."&IF(T148<>""," ("&T148&")",""),S148="manuel","⚠️ À VÉRIFIER MANUELLEMENT : "&T148,S148="inconnue","Pénalité non renseignée — vérifier la notice / DICI du fonds.",$C148="","Saisir une date d'investissement pour statuer sur la pénalité.",Q148="FUTUR","Date d'investissement postérieure à aujourd'hui — vérifier la saisie.",AD148>0,"⚠️ CONCERNÉ : pénalité de "&AD148&"% (détention "&Q148&" mois). "&T148,TRUE,"Non concerné (détention "&Q148&" mois). "&T148) | H148: =COUNTIFS(BDD_Calendrier!$A$2:$A$616,$B148,BDD_Calendrier!$C$2:$C$616,"Souscription") | I148: =IF(H148=0,"",IFERROR(_xlfn.MINIFS(BDD_Calendrier!$D$2:$D$616,BDD_Calendrier!$A$2:$A$616,$B148,BDD_Calendrier!$C$2:$C$616,"Souscription",BDD_Calendrier!$D$2:$D$616,">="&TODAY()),"")) | J148: =IF(I148="","",IFERROR(INDEX(BDD_Calendrier!$E$2:$E$616,MATCH($B148&"|Souscription|"&TEXT(I148,"yyyy-mm-dd"),BDD_Calendrier!$I$2:$I$616,0)),"")) | K148: =IF(H148=0,"",_xlfn.MAXIFS(BDD_Calendrier!$D$2:$D$616,BDD_Calendrier!$A$2:$A$616,$B148,BDD_Calendrier!$C$2:$C$616,"Souscription")) | L148: =COUNTIFS(BDD_Calendrier!$A$2:$A$616,$B148,BDD_Calendrier!$C$2:$C$616,"Rachat") | M148: =IF(L148=0,"",IFERROR(_xlfn.MINIFS(BDD_Calendrier!$D$2:$D$616,BDD_Calendrier!$A$2:$A$616,$B148,BDD_Calendrier!$C$2:$C$616,"Rachat",BDD_Calendrier!$D$2:$D$616,">="&TODAY()),"")) | N148: =IF(M148="","",IFERROR(INDEX(BDD_Calendrier!$E$2:$E$616,MATCH($B148&"|Rachat|"&TEXT(M148,"yyyy-mm-dd"),BDD_Calendrier!$I$2:$I$616,0)),"")) | O148: =IF(M148="","",IFERROR(INDEX(BDD_Calendrier!$H$2:$H$616,MATCH($B148&"|Rachat|"&TEXT(M148,"yyyy-mm-dd"),BDD_Calendrier!$I$2:$I$616,0)),"")) | P148: =IF(L148=0,"",_xlfn.MAXIFS(BDD_Calendrier!$D$2:$D$616,BDD_Calendrier!$A$2:$A$616,$B148,BDD_Calendrier!$C$2:$C$616,"Rachat")) | Q148: =IF($C148="","",IF($C148>TODAY(),"FUTUR",DATEDIF($C148,TODAY(),"m"))) | R148: =COUNTIF(BDD_Penalites!$A$2:$A$130,$B148) | S148: =IF(R148=0,"inconnue",INDEX(BDD_Penalites!$C$2:$C$130,MATCH($B148,BDD_Penalites!$A$2:$A$130,0))) | T148: =IF(R148=0,"",INDEX(BDD_Penalites!$M$2:$M$130,MATCH($B148,BDD_Penalites!$A$2:$A$130,0))) | U148: =IF(R148=0,0,INDEX(BDD_Penalites!$D$2:$D$130,MATCH($B148,BDD_Penalites!$A$2:$A$130,0))) | V148: =IF(R148=0,0,INDEX(BDD_Penalites!$E$2:$E$130,MATCH($B148,BDD_Penalites!$A$2:$A$130,0))) | W148: =IF(R148=0,0,INDEX(BDD_Penalites!$F$2:$F$130,MATCH($B148,BDD_Penalites!$A$2:$A$130,0))) | X148: =IF(R148=0,0,INDEX(BDD_Penalites!$G$2:$G$130,MATCH($B148,BDD_Penalites!$A$2:$A$130,0))) | Y148: =IF(R148=0,0,INDEX(BDD_Penalites!$H$2:$H$130,MATCH($B148,BDD_Penalites!$A$2:$A$130,0))) | Z148: =IF(R148=0,0,INDEX(BDD_Penalites!$I$2:$I$130,MATCH($B148,BDD_Penalites!$A$2:$A$130,0))) | AA148: =IF(R148=0,0,INDEX(BDD_Penalites!$J$2:$J$130,MATCH($B148,BDD_Penalites!$A$2:$A$130,0))) | AB148: =IF(R148=0,0,INDEX(BDD_Penalites!$K$2:$K$130,MATCH($B148,BDD_Penalites!$A$2:$A$130,0))) | AC148: =IF(R148=0,0,INDEX(BDD_Penalites!$L$2:$L$130,MATCH($B148,BDD_Penalites!$A$2:$A$130,0))) | AD148: =IF(OR($C148="",Q148="FUTUR"),"",_xlfn.IFS(Q148<U148,V148,Q148<W148,X148,Q148<Y148,Z148,Q148<AA148,AB148,TRUE,AC148))
A149: PPG Valeur Immo I | B149: FR001400C5W4 | D149: =IF(H149=0,"Calendrier non disponible pour ce fonds — contacter la société de gestion.",IF(I149="","Calendrier connu jusqu'au "&TEXT(K149,"dd/mm/yyyy")&" — demander le calendrier à jour.","Cut-off : "&TEXT(I149,"dd/mm/yyyy")&" | VL : "&TEXT(J149,"dd/mm/yyyy"))) | E149: =IF(L149=0,"Calendrier non disponible pour ce fonds — contacter la société de gestion.",IF(M149="","Calendrier connu jusqu'au "&TEXT(P149,"dd/mm/yyyy")&" — demander le calendrier à jour.","Cut-off : "&TEXT(M149,"dd/mm/yyyy")&" | VL : "&TEXT(N149,"dd/mm/yyyy"))) | F149: =IF(L149=0,"Calendrier non disponible pour ce fonds.",IF(M149="","Calendrier connu jusqu'au "&TEXT(P149,"dd/mm/yyyy")&".",IF(O149="","Non précisé dans le calendrier pour cette échéance.","Réception : "&TEXT(O149,"dd/mm/yyyy")&" (suite au rachat du "&TEXT(N149,"dd/mm/yyyy")&")"))) | G149: =_xlfn.IFS(S149="aucune","Aucune pénalité de sortie."&IF(T149<>""," ("&T149&")",""),S149="manuel","⚠️ À VÉRIFIER MANUELLEMENT : "&T149,S149="inconnue","Pénalité non renseignée — vérifier la notice / DICI du fonds.",$C149="","Saisir une date d'investissement pour statuer sur la pénalité.",Q149="FUTUR","Date d'investissement postérieure à aujourd'hui — vérifier la saisie.",AD149>0,"⚠️ CONCERNÉ : pénalité de "&AD149&"% (détention "&Q149&" mois). "&T149,TRUE,"Non concerné (détention "&Q149&" mois). "&T149) | H149: =COUNTIFS(BDD_Calendrier!$A$2:$A$616,$B149,BDD_Calendrier!$C$2:$C$616,"Souscription") | I149: =IF(H149=0,"",IFERROR(_xlfn.MINIFS(BDD_Calendrier!$D$2:$D$616,BDD_Calendrier!$A$2:$A$616,$B149,BDD_Calendrier!$C$2:$C$616,"Souscription",BDD_Calendrier!$D$2:$D$616,">="&TODAY()),"")) | J149: =IF(I149="","",IFERROR(INDEX(BDD_Calendrier!$E$2:$E$616,MATCH($B149&"|Souscription|"&TEXT(I149,"yyyy-mm-dd"),BDD_Calendrier!$I$2:$I$616,0)),"")) | K149: =IF(H149=0,"",_xlfn.MAXIFS(BDD_Calendrier!$D$2:$D$616,BDD_Calendrier!$A$2:$A$616,$B149,BDD_Calendrier!$C$2:$C$616,"Souscription")) | L149: =COUNTIFS(BDD_Calendrier!$A$2:$A$616,$B149,BDD_Calendrier!$C$2:$C$616,"Rachat") | M149: =IF(L149=0,"",IFERROR(_xlfn.MINIFS(BDD_Calendrier!$D$2:$D$616,BDD_Calendrier!$A$2:$A$616,$B149,BDD_Calendrier!$C$2:$C$616,"Rachat",BDD_Calendrier!$D$2:$D$616,">="&TODAY()),"")) | N149: =IF(M149="","",IFERROR(INDEX(BDD_Calendrier!$E$2:$E$616,MATCH($B149&"|Rachat|"&TEXT(M149,"yyyy-mm-dd"),BDD_Calendrier!$I$2:$I$616,0)),"")) | O149: =IF(M149="","",IFERROR(INDEX(BDD_Calendrier!$H$2:$H$616,MATCH($B149&"|Rachat|"&TEXT(M149,"yyyy-mm-dd"),BDD_Calendrier!$I$2:$I$616,0)),"")) | P149: =IF(L149=0,"",_xlfn.MAXIFS(BDD_Calendrier!$D$2:$D$616,BDD_Calendrier!$A$2:$A$616,$B149,BDD_Calendrier!$C$2:$C$616,"Rachat")) | Q149: =IF($C149="","",IF($C149>TODAY(),"FUTUR",DATEDIF($C149,TODAY(),"m"))) | R149: =COUNTIF(BDD_Penalites!$A$2:$A$130,$B149) | S149: =IF(R149=0,"inconnue",INDEX(BDD_Penalites!$C$2:$C$130,MATCH($B149,BDD_Penalites!$A$2:$A$130,0))) | T149: =IF(R149=0,"",INDEX(BDD_Penalites!$M$2:$M$130,MATCH($B149,BDD_Penalites!$A$2:$A$130,0))) | U149: =IF(R149=0,0,INDEX(BDD_Penalites!$D$2:$D$130,MATCH($B149,BDD_Penalites!$A$2:$A$130,0))) | V149: =IF(R149=0,0,INDEX(BDD_Penalites!$E$2:$E$130,MATCH($B149,BDD_Penalites!$A$2:$A$130,0))) | W149: =IF(R149=0,0,INDEX(BDD_Penalites!$F$2:$F$130,MATCH($B149,BDD_Penalites!$A$2:$A$130,0))) | X149: =IF(R149=0,0,INDEX(BDD_Penalites!$G$2:$G$130,MATCH($B149,BDD_Penalites!$A$2:$A$130,0))) | Y149: =IF(R149=0,0,INDEX(BDD_Penalites!$H$2:$H$130,MATCH($B149,BDD_Penalites!$A$2:$A$130,0))) | Z149: =IF(R149=0,0,INDEX(BDD_Penalites!$I$2:$I$130,MATCH($B149,BDD_Penalites!$A$2:$A$130,0))) | AA149: =IF(R149=0,0,INDEX(BDD_Penalites!$J$2:$J$130,MATCH($B149,BDD_Penalites!$A$2:$A$130,0))) | AB149: =IF(R149=0,0,INDEX(BDD_Penalites!$K$2:$K$130,MATCH($B149,BDD_Penalites!$A$2:$A$130,0))) | AC149: =IF(R149=0,0,INDEX(BDD_Penalites!$L$2:$L$130,MATCH($B149,BDD_Penalites!$A$2:$A$130,0))) | AD149: =IF(OR($C149="",Q149="FUTUR"),"",_xlfn.IFS(Q149<U149,V149,Q149<W149,X149,Q149<Y149,Z149,Q149<AA149,AB149,TRUE,AC149))
A150: Iroko Zen | B150: / | D150: =IF(H150=0,"Calendrier non disponible pour ce fonds — contacter la société de gestion.",IF(I150="","Calendrier connu jusqu'au "&TEXT(K150,"dd/mm/yyyy")&" — demander le calendrier à jour.","Cut-off : "&TEXT(I150,"dd/mm/yyyy")&" | VL : "&TEXT(J150,"dd/mm/yyyy"))) | E150: =IF(L150=0,"Calendrier non disponible pour ce fonds — contacter la société de gestion.",IF(M150="","Calendrier connu jusqu'au "&TEXT(P150,"dd/mm/yyyy")&" — demander le calendrier à jour.","Cut-off : "&TEXT(M150,"dd/mm/yyyy")&" | VL : "&TEXT(N150,"dd/mm/yyyy"))) | F150: =IF(L150=0,"Calendrier non disponible pour ce fonds.",IF(M150="","Calendrier connu jusqu'au "&TEXT(P150,"dd/mm/yyyy")&".",IF(O150="","Non précisé dans le calendrier pour cette échéance.","Réception : "&TEXT(O150,"dd/mm/yyyy")&" (suite au rachat du "&TEXT(N150,"dd/mm/yyyy")&")"))) | G150: =_xlfn.IFS(S150="aucune","Aucune pénalité de sortie."&IF(T150<>""," ("&T150&")",""),S150="manuel","⚠️ À VÉRIFIER MANUELLEMENT : "&T150,S150="inconnue","Pénalité non renseignée — vérifier la notice / DICI du fonds.",$C150="","Saisir une date d'investissement pour statuer sur la pénalité.",Q150="FUTUR","Date d'investissement postérieure à aujourd'hui — vérifier la saisie.",AD150>0,"⚠️ CONCERNÉ : pénalité de "&AD150&"% (détention "&Q150&" mois). "&T150,TRUE,"Non concerné (détention "&Q150&" mois). "&T150) | H150: =COUNTIFS(BDD_Calendrier!$A$2:$A$616,$B150,BDD_Calendrier!$C$2:$C$616,"Souscription") | I150: =IF(H150=0,"",IFERROR(_xlfn.MINIFS(BDD_Calendrier!$D$2:$D$616,BDD_Calendrier!$A$2:$A$616,$B150,BDD_Calendrier!$C$2:$C$616,"Souscription",BDD_Calendrier!$D$2:$D$616,">="&TODAY()),"")) | J150: =IF(I150="","",IFERROR(INDEX(BDD_Calendrier!$E$2:$E$616,MATCH($B150&"|Souscription|"&TEXT(I150,"yyyy-mm-dd"),BDD_Calendrier!$I$2:$I$616,0)),"")) | K150: =IF(H150=0,"",_xlfn.MAXIFS(BDD_Calendrier!$D$2:$D$616,BDD_Calendrier!$A$2:$A$616,$B150,BDD_Calendrier!$C$2:$C$616,"Souscription")) | L150: =COUNTIFS(BDD_Calendrier!$A$2:$A$616,$B150,BDD_Calendrier!$C$2:$C$616,"Rachat") | M150: =IF(L150=0,"",IFERROR(_xlfn.MINIFS(BDD_Calendrier!$D$2:$D$616,BDD_Calendrier!$A$2:$A$616,$B150,BDD_Calendrier!$C$2:$C$616,"Rachat",BDD_Calendrier!$D$2:$D$616,">="&TODAY()),"")) | N150: =IF(M150="","",IFERROR(INDEX(BDD_Calendrier!$E$2:$E$616,MATCH($B150&"|Rachat|"&TEXT(M150,"yyyy-mm-dd"),BDD_Calendrier!$I$2:$I$616,0)),"")) | O150: =IF(M150="","",IFERROR(INDEX(BDD_Calendrier!$H$2:$H$616,MATCH($B150&"|Rachat|"&TEXT(M150,"yyyy-mm-dd"),BDD_Calendrier!$I$2:$I$616,0)),"")) | P150: =IF(L150=0,"",_xlfn.MAXIFS(BDD_Calendrier!$D$2:$D$616,BDD_Calendrier!$A$2:$A$616,$B150,BDD_Calendrier!$C$2:$C$616,"Rachat")) | Q150: =IF($C150="","",IF($C150>TODAY(),"FUTUR",DATEDIF($C150,TODAY(),"m"))) | R150: =COUNTIF(BDD_Penalites!$A$2:$A$130,$B150) | S150: =IF(R150=0,"inconnue",INDEX(BDD_Penalites!$C$2:$C$130,MATCH($B150,BDD_Penalites!$A$2:$A$130,0))) | T150: =IF(R150=0,"",INDEX(BDD_Penalites!$M$2:$M$130,MATCH($B150,BDD_Penalites!$A$2:$A$130,0))) | U150: =IF(R150=0,0,INDEX(BDD_Penalites!$D$2:$D$130,MATCH($B150,BDD_Penalites!$A$2:$A$130,0))) | V150: =IF(R150=0,0,INDEX(BDD_Penalites!$E$2:$E$130,MATCH($B150,BDD_Penalites!$A$2:$A$130,0))) | W150: =IF(R150=0,0,INDEX(BDD_Penalites!$F$2:$F$130,MATCH($B150,BDD_Penalites!$A$2:$A$130,0))) | X150: =IF(R150=0,0,INDEX(BDD_Penalites!$G$2:$G$130,MATCH($B150,BDD_Penalites!$A$2:$A$130,0))) | Y150: =IF(R150=0,0,INDEX(BDD_Penalites!$H$2:$H$130,MATCH($B150,BDD_Penalites!$A$2:$A$130,0))) | Z150: =IF(R150=0,0,INDEX(BDD_Penalites!$I$2:$I$130,MATCH($B150,BDD_Penalites!$A$2:$A$130,0))) | AA150: =IF(R150=0,0,INDEX(BDD_Penalites!$J$2:$J$130,MATCH($B150,BDD_Penalites!$A$2:$A$130,0))) | AB150: =IF(R150=0,0,INDEX(BDD_Penalites!$K$2:$K$130,MATCH($B150,BDD_Penalites!$A$2:$A$130,0))) | AC150: =IF(R150=0,0,INDEX(BDD_Penalites!$L$2:$L$130,MATCH($B150,BDD_Penalites!$A$2:$A$130,0))) | AD150: =IF(OR($C150="",Q150="FUTUR"),"",_xlfn.IFS(Q150<U150,V150,Q150<W150,X150,Q150<Y150,Z150,Q150<AA150,AB150,TRUE,AC150))
A151: Iroko Atlas | B151: / | D151: =IF(H151=0,"Calendrier non disponible pour ce fonds — contacter la société de gestion.",IF(I151="","Calendrier connu jusqu'au "&TEXT(K151,"dd/mm/yyyy")&" — demander le calendrier à jour.","Cut-off : "&TEXT(I151,"dd/mm/yyyy")&" | VL : "&TEXT(J151,"dd/mm/yyyy"))) | E151: =IF(L151=0,"Calendrier non disponible pour ce fonds — contacter la société de gestion.",IF(M151="","Calendrier connu jusqu'au "&TEXT(P151,"dd/mm/yyyy")&" — demander le calendrier à jour.","Cut-off : "&TEXT(M151,"dd/mm/yyyy")&" | VL : "&TEXT(N151,"dd/mm/yyyy"))) | F151: =IF(L151=0,"Calendrier non disponible pour ce fonds.",IF(M151="","Calendrier connu jusqu'au "&TEXT(P151,"dd/mm/yyyy")&".",IF(O151="","Non précisé dans le calendrier pour cette échéance.","Réception : "&TEXT(O151,"dd/mm/yyyy")&" (suite au rachat du "&TEXT(N151,"dd/mm/yyyy")&")"))) | G151: =_xlfn.IFS(S151="aucune","Aucune pénalité de sortie."&IF(T151<>""," ("&T151&")",""),S151="manuel","⚠️ À VÉRIFIER MANUELLEMENT : "&T151,S151="inconnue","Pénalité non renseignée — vérifier la notice / DICI du fonds.",$C151="","Saisir une date d'investissement pour statuer sur la pénalité.",Q151="FUTUR","Date d'investissement postérieure à aujourd'hui — vérifier la saisie.",AD151>0,"⚠️ CONCERNÉ : pénalité de "&AD151&"% (détention "&Q151&" mois). "&T151,TRUE,"Non concerné (détention "&Q151&" mois). "&T151) | H151: =COUNTIFS(BDD_Calendrier!$A$2:$A$616,$B151,BDD_Calendrier!$C$2:$C$616,"Souscription") | I151: =IF(H151=0,"",IFERROR(_xlfn.MINIFS(BDD_Calendrier!$D$2:$D$616,BDD_Calendrier!$A$2:$A$616,$B151,BDD_Calendrier!$C$2:$C$616,"Souscription",BDD_Calendrier!$D$2:$D$616,">="&TODAY()),"")) | J151: =IF(I151="","",IFERROR(INDEX(BDD_Calendrier!$E$2:$E$616,MATCH($B151&"|Souscription|"&TEXT(I151,"yyyy-mm-dd"),BDD_Calendrier!$I$2:$I$616,0)),"")) | K151: =IF(H151=0,"",_xlfn.MAXIFS(BDD_Calendrier!$D$2:$D$616,BDD_Calendrier!$A$2:$A$616,$B151,BDD_Calendrier!$C$2:$C$616,"Souscription")) | L151: =COUNTIFS(BDD_Calendrier!$A$2:$A$616,$B151,BDD_Calendrier!$C$2:$C$616,"Rachat") | M151: =IF(L151=0,"",IFERROR(_xlfn.MINIFS(BDD_Calendrier!$D$2:$D$616,BDD_Calendrier!$A$2:$A$616,$B151,BDD_Calendrier!$C$2:$C$616,"Rachat",BDD_Calendrier!$D$2:$D$616,">="&TODAY()),"")) | N151: =IF(M151="","",IFERROR(INDEX(BDD_Calendrier!$E$2:$E$616,MATCH($B151&"|Rachat|"&TEXT(M151,"yyyy-mm-dd"),BDD_Calendrier!$I$2:$I$616,0)),"")) | O151: =IF(M151="","",IFERROR(INDEX(BDD_Calendrier!$H$2:$H$616,MATCH($B151&"|Rachat|"&TEXT(M151,"yyyy-mm-dd"),BDD_Calendrier!$I$2:$I$616,0)),"")) | P151: =IF(L151=0,"",_xlfn.MAXIFS(BDD_Calendrier!$D$2:$D$616,BDD_Calendrier!$A$2:$A$616,$B151,BDD_Calendrier!$C$2:$C$616,"Rachat")) | Q151: =IF($C151="","",IF($C151>TODAY(),"FUTUR",DATEDIF($C151,TODAY(),"m"))) | R151: =COUNTIF(BDD_Penalites!$A$2:$A$130,$B151) | S151: =IF(R151=0,"inconnue",INDEX(BDD_Penalites!$C$2:$C$130,MATCH($B151,BDD_Penalites!$A$2:$A$130,0))) | T151: =IF(R151=0,"",INDEX(BDD_Penalites!$M$2:$M$130,MATCH($B151,BDD_Penalites!$A$2:$A$130,0))) | U151: =IF(R151=0,0,INDEX(BDD_Penalites!$D$2:$D$130,MATCH($B151,BDD_Penalites!$A$2:$A$130,0))) | V151: =IF(R151=0,0,INDEX(BDD_Penalites!$E$2:$E$130,MATCH($B151,BDD_Penalites!$A$2:$A$130,0))) | W151: =IF(R151=0,0,INDEX(BDD_Penalites!$F$2:$F$130,MATCH($B151,BDD_Penalites!$A$2:$A$130,0))) | X151: =IF(R151=0,0,INDEX(BDD_Penalites!$G$2:$G$130,MATCH($B151,BDD_Penalites!$A$2:$A$130,0))) | Y151: =IF(R151=0,0,INDEX(BDD_Penalites!$H$2:$H$130,MATCH($B151,BDD_Penalites!$A$2:$A$130,0))) | Z151: =IF(R151=0,0,INDEX(BDD_Penalites!$I$2:$I$130,MATCH($B151,BDD_Penalites!$A$2:$A$130,0))) | AA151: =IF(R151=0,0,INDEX(BDD_Penalites!$J$2:$J$130,MATCH($B151,BDD_Penalites!$A$2:$A$130,0))) | AB151: =IF(R151=0,0,INDEX(BDD_Penalites!$K$2:$K$130,MATCH($B151,BDD_Penalites!$A$2:$A$130,0))) | AC151: =IF(R151=0,0,INDEX(BDD_Penalites!$L$2:$L$130,MATCH($B151,BDD_Penalites!$A$2:$A$130,0))) | AD151: =IF(OR($C151="",Q151="FUTUR"),"",_xlfn.IFS(Q151<U151,V151,Q151<W151,X151,Q151<Y151,Z151,Q151<AA151,AB151,TRUE,AC151))
... A164: SCI Convictions Immobilières | B164: / | D164: =IF(H164=0,"Calendrier non disponible pour ce fonds — contacter la société de gestion.",IF(I164="","Calendrier connu jusqu'au "&TEXT(K164,"dd/mm/yyyy")&" — demander le calendrier à jour.","Cut-off : "&TEXT(I164,"dd/mm/yyyy")&" | VL : "&TEXT(J164,"dd/mm/yyyy"))) | E164: =IF(L164=0,"Calendrier non disponible pour ce fonds — contacter la société de gestion.",IF(M164="","Calendrier connu jusqu'au "&TEXT(P164,"dd/mm/yyyy")&" — demander le calendrier à jour.","Cut-off : "&TEXT(M164,"dd/mm/yyyy")&" | VL : "&TEXT(N164,"dd/mm/yyyy"))) | F164: =IF(L164=0,"Calendrier non disponible pour ce fonds.",IF(M164="","Calendrier connu jusqu'au "&TEXT(P164,"dd/mm/yyyy")&".",IF(O164="","Non précisé dans le calendrier pour cette échéance.","Réception : "&TEXT(O164,"dd/mm/yyyy")&" (suite au rachat du "&TEXT(N164,"dd/mm/yyyy")&")"))) | G164: =_xlfn.IFS(S164="aucune","Aucune pénalité de sortie."&IF(T164<>""," ("&T164&")",""),S164="manuel","⚠️ À VÉRIFIER MANUELLEMENT : "&T164,S164="inconnue","Pénalité non renseignée — vérifier la notice / DICI du fonds.",$C164="","Saisir une date d'investissement pour statuer sur la pénalité.",Q164="FUTUR","Date d'investissement postérieure à aujourd'hui — vérifier la saisie.",AD164>0,"⚠️ CONCERNÉ : pénalité de "&AD164&"% (détention "&Q164&" mois). "&T164,TRUE,"Non concerné (détention "&Q164&" mois). "&T164) | H164: =COUNTIFS(BDD_Calendrier!$A$2:$A$616,$B164,BDD_Calendrier!$C$2:$C$616,"Souscription") | I164: =IF(H164=0,"",IFERROR(_xlfn.MINIFS(BDD_Calendrier!$D$2:$D$616,BDD_Calendrier!$A$2:$A$616,$B164,BDD_Calendrier!$C$2:$C$616,"Souscription",BDD_Calendrier!$D$2:$D$616,">="&TODAY()),"")) | J164: =IF(I164="","",IFERROR(INDEX(BDD_Calendrier!$E$2:$E$616,MATCH($B164&"|Souscription|"&TEXT(I164,"yyyy-mm-dd"),BDD_Calendrier!$I$2:$I$616,0)),"")) | K164: =IF(H164=0,"",_xlfn.MAXIFS(BDD_Calendrier!$D$2:$D$616,BDD_Calendrier!$A$2:$A$616,$B164,BDD_Calendrier!$C$2:$C$616,"Souscription")) | L164: =COUNTIFS(BDD_Calendrier!$A$2:$A$616,$B164,BDD_Calendrier!$C$2:$C$616,"Rachat") | M164: =IF(L164=0,"",IFERROR(_xlfn.MINIFS(BDD_Calendrier!$D$2:$D$616,BDD_Calendrier!$A$2:$A$616,$B164,BDD_Calendrier!$C$2:$C$616,"Rachat",BDD_Calendrier!$D$2:$D$616,">="&TODAY()),"")) | N164: =IF(M164="","",IFERROR(INDEX(BDD_Calendrier!$E$2:$E$616,MATCH($B164&"|Rachat|"&TEXT(M164,"yyyy-mm-dd"),BDD_Calendrier!$I$2:$I$616,0)),"")) | O164: =IF(M164="","",IFERROR(INDEX(BDD_Calendrier!$H$2:$H$616,MATCH($B164&"|Rachat|"&TEXT(M164,"yyyy-mm-dd"),BDD_Calendrier!$I$2:$I$616,0)),"")) | P164: =IF(L164=0,"",_xlfn.MAXIFS(BDD_Calendrier!$D$2:$D$616,BDD_Calendrier!$A$2:$A$616,$B164,BDD_Calendrier!$C$2:$C$616,"Rachat")) | Q164: =IF($C164="","",IF($C164>TODAY(),"FUTUR",DATEDIF($C164,TODAY(),"m"))) | R164: =COUNTIF(BDD_Penalites!$A$2:$A$130,$B164) | S164: =IF(R164=0,"inconnue",INDEX(BDD_Penalites!$C$2:$C$130,MATCH($B164,BDD_Penalites!$A$2:$A$130,0))) | T164: =IF(R164=0,"",INDEX(BDD_Penalites!$M$2:$M$130,MATCH($B164,BDD_Penalites!$A$2:$A$130,0))) | U164: =IF(R164=0,0,INDEX(BDD_Penalites!$D$2:$D$130,MATCH($B164,BDD_Penalites!$A$2:$A$130,0))) | V164: =IF(R164=0,0,INDEX(BDD_Penalites!$E$2:$E$130,MATCH($B164,BDD_Penalites!$A$2:$A$130,0))) | W164: =IF(R164=0,0,INDEX(BDD_Penalites!$F$2:$F$130,MATCH($B164,BDD_Penalites!$A$2:$A$130,0))) | X164: =IF(R164=0,0,INDEX(BDD_Penalites!$G$2:$G$130,MATCH($B164,BDD_Penalites!$A$2:$A$130,0))) | Y164: =IF(R164=0,0,INDEX(BDD_Penalites!$H$2:$H$130,MATCH($B164,BDD_Penalites!$A$2:$A$130,0))) | Z164: =IF(R164=0,0,INDEX(BDD_Penalites!$I$2:$I$130,MATCH($B164,BDD_Penalites!$A$2:$A$130,0))) | AA164: =IF(R164=0,0,INDEX(BDD_Penalites!$J$2:$J$130,MATCH($B164,BDD_Penalites!$A$2:$A$130,0))) | AB164: =IF(R164=0,0,INDEX(BDD_Penalites!$K$2:$K$130,MATCH($B164,BDD_Penalites!$A$2:$A$130,0))) | AC164: =IF(R164=0,0,INDEX(BDD_Penalites!$L$2:$L$130,MATCH($B164,BDD_Penalites!$A$2:$A$130,0))) | AD164: =IF(OR($C164="",Q164="FUTUR"),"",_xlfn.IFS(Q164<U164,V164,Q164<W164,X164,Q164<Y164,Z164,Q164<AA164,AB164,TRUE,AC164))
A173: Infrastructures non cotées
A174: Antheor Private Infrastructure part F | B174: FR001400ZM09 | D174: =IF(H174=0,"Calendrier non disponible pour ce fonds — contacter la société de gestion.",IF(I174="","Calendrier connu jusqu'au "&TEXT(K174,"dd/mm/yyyy")&" — demander le calendrier à jour.","Cut-off : "&TEXT(I174,"dd/mm/yyyy")&" | VL : "&TEXT(J174,"dd/mm/yyyy"))) | E174: =IF(L174=0,"Calendrier non disponible pour ce fonds — contacter la société de gestion.",IF(M174="","Calendrier connu jusqu'au "&TEXT(P174,"dd/mm/yyyy")&" — demander le calendrier à jour.","Cut-off : "&TEXT(M174,"dd/mm/yyyy")&" | VL : "&TEXT(N174,"dd/mm/yyyy"))) | F174: =IF(L174=0,"Calendrier non disponible pour ce fonds.",IF(M174="","Calendrier connu jusqu'au "&TEXT(P174,"dd/mm/yyyy")&".",IF(O174="","Non précisé dans le calendrier pour cette échéance.","Réception : "&TEXT(O174,"dd/mm/yyyy")&" (suite au rachat du "&TEXT(N174,"dd/mm/yyyy")&")"))) | G174: =_xlfn.IFS(S174="aucune","Aucune pénalité de sortie."&IF(T174<>""," ("&T174&")",""),S174="manuel","⚠️ À VÉRIFIER MANUELLEMENT : "&T174,S174="inconnue","Pénalité non renseignée — vérifier la notice / DICI du fonds.",$C174="","Saisir une date d'investissement pour statuer sur la pénalité.",Q174="FUTUR","Date d'investissement postérieure à aujourd'hui — vérifier la saisie.",AD174>0,"⚠️ CONCERNÉ : pénalité de "&AD174&"% (détention "&Q174&" mois). "&T174,TRUE,"Non concerné (détention "&Q174&" mois). "&T174) | H174: =COUNTIFS(BDD_Calendrier!$A$2:$A$616,$B174,BDD_Calendrier!$C$2:$C$616,"Souscription") | I174: =IF(H174=0,"",IFERROR(_xlfn.MINIFS(BDD_Calendrier!$D$2:$D$616,BDD_Calendrier!$A$2:$A$616,$B174,BDD_Calendrier!$C$2:$C$616,"Souscription",BDD_Calendrier!$D$2:$D$616,">="&TODAY()),"")) | J174: =IF(I174="","",IFERROR(INDEX(BDD_Calendrier!$E$2:$E$616,MATCH($B174&"|Souscription|"&TEXT(I174,"yyyy-mm-dd"),BDD_Calendrier!$I$2:$I$616,0)),"")) | K174: =IF(H174=0,"",_xlfn.MAXIFS(BDD_Calendrier!$D$2:$D$616,BDD_Calendrier!$A$2:$A$616,$B174,BDD_Calendrier!$C$2:$C$616,"Souscription")) | L174: =COUNTIFS(BDD_Calendrier!$A$2:$A$616,$B174,BDD_Calendrier!$C$2:$C$616,"Rachat") | M174: =IF(L174=0,"",IFERROR(_xlfn.MINIFS(BDD_Calendrier!$D$2:$D$616,BDD_Calendrier!$A$2:$A$616,$B174,BDD_Calendrier!$C$2:$C$616,"Rachat",BDD_Calendrier!$D$2:$D$616,">="&TODAY()),"")) | N174: =IF(M174="","",IFERROR(INDEX(BDD_Calendrier!$E$2:$E$616,MATCH($B174&"|Rachat|"&TEXT(M174,"yyyy-mm-dd"),BDD_Calendrier!$I$2:$I$616,0)),"")) | O174: =IF(M174="","",IFERROR(INDEX(BDD_Calendrier!$H$2:$H$616,MATCH($B174&"|Rachat|"&TEXT(M174,"yyyy-mm-dd"),BDD_Calendrier!$I$2:$I$616,0)),"")) | P174: =IF(L174=0,"",_xlfn.MAXIFS(BDD_Calendrier!$D$2:$D$616,BDD_Calendrier!$A$2:$A$616,$B174,BDD_Calendrier!$C$2:$C$616,"Rachat")) | Q174: =IF($C174="","",IF($C174>TODAY(),"FUTUR",DATEDIF($C174,TODAY(),"m"))) | R174: =COUNTIF(BDD_Penalites!$A$2:$A$130,$B174) | S174: =IF(R174=0,"inconnue",INDEX(BDD_Penalites!$C$2:$C$130,MATCH($B174,BDD_Penalites!$A$2:$A$130,0))) | T174: =IF(R174=0,"",INDEX(BDD_Penalites!$M$2:$M$130,MATCH($B174,BDD_Penalites!$A$2:$A$130,0))) | U174: =IF(R174=0,0,INDEX(BDD_Penalites!$D$2:$D$130,MATCH($B174,BDD_Penalites!$A$2:$A$130,0))) | V174: =IF(R174=0,0,INDEX(BDD_Penalites!$E$2:$E$130,MATCH($B174,BDD_Penalites!$A$2:$A$130,0))) | W174: =IF(R174=0,0,INDEX(BDD_Penalites!$F$2:$F$130,MATCH($B174,BDD_Penalites!$A$2:$A$130,0))) | X174: =IF(R174=0,0,INDEX(BDD_Penalites!$G$2:$G$130,MATCH($B174,BDD_Penalites!$A$2:$A$130,0))) | Y174: =IF(R174=0,0,INDEX(BDD_Penalites!$H$2:$H$130,MATCH($B174,BDD_Penalites!$A$2:$A$130,0))) | Z174: =IF(R174=0,0,INDEX(BDD_Penalites!$I$2:$I$130,MATCH($B174,BDD_Penalites!$A$2:$A$130,0))) | AA174: =IF(R174=0,0,INDEX(BDD_Penalites!$J$2:$J$130,MATCH($B174,BDD_Penalites!$A$2:$A$130,0))) | AB174: =IF(R174=0,0,INDEX(BDD_Penalites!$K$2:$K$130,MATCH($B174,BDD_Penalites!$A$2:$A$130,0))) | AC174: =IF(R174=0,0,INDEX(BDD_Penalites!$L$2:$L$130,MATCH($B174,BDD_Penalites!$A$2:$A$130,0))) | AD174: =IF(OR($C174="",Q174="FUTUR"),"",_xlfn.IFS(Q174<U174,V174,Q174<W174,X174,Q174<Y174,Z174,Q174<AA174,AB174,TRUE,AC174))
A175: Antheor Private Infrastructure part A | B175: FR001400ZLZ0 | D175: =IF(H175=0,"Calendrier non disponible pour ce fonds — contacter la société de gestion.",IF(I175="","Calendrier connu jusqu'au "&TEXT(K175,"dd/mm/yyyy")&" — demander le calendrier à jour.","Cut-off : "&TEXT(I175,"dd/mm/yyyy")&" | VL : "&TEXT(J175,"dd/mm/yyyy"))) | E175: =IF(L175=0,"Calendrier non disponible pour ce fonds — contacter la société de gestion.",IF(M175="","Calendrier connu jusqu'au "&TEXT(P175,"dd/mm/yyyy")&" — demander le calendrier à jour.","Cut-off : "&TEXT(M175,"dd/mm/yyyy")&" | VL : "&TEXT(N175,"dd/mm/yyyy"))) | F175: =IF(L175=0,"Calendrier non disponible pour ce fonds.",IF(M175="","Calendrier connu jusqu'au "&TEXT(P175,"dd/mm/yyyy")&".",IF(O175="","Non précisé dans le calendrier pour cette échéance.","Réception : "&TEXT(O175,"dd/mm/yyyy")&" (suite au rachat du "&TEXT(N175,"dd/mm/yyyy")&")"))) | G175: =_xlfn.IFS(S175="aucune","Aucune pénalité de sortie."&IF(T175<>""," ("&T175&")",""),S175="manuel","⚠️ À VÉRIFIER MANUELLEMENT : "&T175,S175="inconnue","Pénalité non renseignée — vérifier la notice / DICI du fonds.",$C175="","Saisir une date d'investissement pour statuer sur la pénalité.",Q175="FUTUR","Date d'investissement postérieure à aujourd'hui — vérifier la saisie.",AD175>0,"⚠️ CONCERNÉ : pénalité de "&AD175&"% (détention "&Q175&" mois). "&T175,TRUE,"Non concerné (détention "&Q175&" mois). "&T175) | H175: =COUNTIFS(BDD_Calendrier!$A$2:$A$616,$B175,BDD_Calendrier!$C$2:$C$616,"Souscription") | I175: =IF(H175=0,"",IFERROR(_xlfn.MINIFS(BDD_Calendrier!$D$2:$D$616,BDD_Calendrier!$A$2:$A$616,$B175,BDD_Calendrier!$C$2:$C$616,"Souscription",BDD_Calendrier!$D$2:$D$616,">="&TODAY()),"")) | J175: =IF(I175="","",IFERROR(INDEX(BDD_Calendrier!$E$2:$E$616,MATCH($B175&"|Souscription|"&TEXT(I175,"yyyy-mm-dd"),BDD_Calendrier!$I$2:$I$616,0)),"")) | K175: =IF(H175=0,"",_xlfn.MAXIFS(BDD_Calendrier!$D$2:$D$616,BDD_Calendrier!$A$2:$A$616,$B175,BDD_Calendrier!$C$2:$C$616,"Souscription")) | L175: =COUNTIFS(BDD_Calendrier!$A$2:$A$616,$B175,BDD_Calendrier!$C$2:$C$616,"Rachat") | M175: =IF(L175=0,"",IFERROR(_xlfn.MINIFS(BDD_Calendrier!$D$2:$D$616,BDD_Calendrier!$A$2:$A$616,$B175,BDD_Calendrier!$C$2:$C$616,"Rachat",BDD_Calendrier!$D$2:$D$616,">="&TODAY()),"")) | N175: =IF(M175="","",IFERROR(INDEX(BDD_Calendrier!$E$2:$E$616,MATCH($B175&"|Rachat|"&TEXT(M175,"yyyy-mm-dd"),BDD_Calendrier!$I$2:$I$616,0)),"")) | O175: =IF(M175="","",IFERROR(INDEX(BDD_Calendrier!$H$2:$H$616,MATCH($B175&"|Rachat|"&TEXT(M175,"yyyy-mm-dd"),BDD_Calendrier!$I$2:$I$616,0)),"")) | P175: =IF(L175=0,"",_xlfn.MAXIFS(BDD_Calendrier!$D$2:$D$616,BDD_Calendrier!$A$2:$A$616,$B175,BDD_Calendrier!$C$2:$C$616,"Rachat")) | Q175: =IF($C175="","",IF($C175>TODAY(),"FUTUR",DATEDIF($C175,TODAY(),"m"))) | R175: =COUNTIF(BDD_Penalites!$A$2:$A$130,$B175) | S175: =IF(R175=0,"inconnue",INDEX(BDD_Penalites!$C$2:$C$130,MATCH($B175,BDD_Penalites!$A$2:$A$130,0))) | T175: =IF(R175=0,"",INDEX(BDD_Penalites!$M$2:$M$130,MATCH($B175,BDD_Penalites!$A$2:$A$130,0))) | U175: =IF(R175=0,0,INDEX(BDD_Penalites!$D$2:$D$130,MATCH($B175,BDD_Penalites!$A$2:$A$130,0))) | V175: =IF(R175=0,0,INDEX(BDD_Penalites!$E$2:$E$130,MATCH($B175,BDD_Penalites!$A$2:$A$130,0))) | W175: =IF(R175=0,0,INDEX(BDD_Penalites!$F$2:$F$130,MATCH($B175,BDD_Penalites!$A$2:$A$130,0))) | X175: =IF(R175=0,0,INDEX(BDD_Penalites!$G$2:$G$130,MATCH($B175,BDD_Penalites!$A$2:$A$130,0))) | Y175: =IF(R175=0,0,INDEX(BDD_Penalites!$H$2:$H$130,MATCH($B175,BDD_Penalites!$A$2:$A$130,0))) | Z175: =IF(R175=0,0,INDEX(BDD_Penalites!$I$2:$I$130,MATCH($B175,BDD_Penalites!$A$2:$A$130,0))) | AA175: =IF(R175=0,0,INDEX(BDD_Penalites!$J$2:$J$130,MATCH($B175,BDD_Penalites!$A$2:$A$130,0))) | AB175: =IF(R175=0,0,INDEX(BDD_Penalites!$K$2:$K$130,MATCH($B175,BDD_Penalites!$A$2:$A$130,0))) | AC175: =IF(R175=0,0,INDEX(BDD_Penalites!$L$2:$L$130,MATCH($B175,BDD_Penalites!$A$2:$A$130,0))) | AD175: =IF(OR($C175="",Q175="FUTUR"),"",_xlfn.IFS(Q175<U175,V175,Q175<W175,X175,Q175<Y175,Z175,Q175<AA175,AB175,TRUE,AC175))
A176: Antheor Private Infrastructure part B | B176: FR001400ZM58 | D176: =IF(H176=0,"Calendrier non disponible pour ce fonds — contacter la société de gestion.",IF(I176="","Calendrier connu jusqu'au "&TEXT(K176,"dd/mm/yyyy")&" — demander le calendrier à jour.","Cut-off : "&TEXT(I176,"dd/mm/yyyy")&" | VL : "&TEXT(J176,"dd/mm/yyyy"))) | E176: =IF(L176=0,"Calendrier non disponible pour ce fonds — contacter la société de gestion.",IF(M176="","Calendrier connu jusqu'au "&TEXT(P176,"dd/mm/yyyy")&" — demander le calendrier à jour.","Cut-off : "&TEXT(M176,"dd/mm/yyyy")&" | VL : "&TEXT(N176,"dd/mm/yyyy"))) | F176: =IF(L176=0,"Calendrier non disponible pour ce fonds.",IF(M176="","Calendrier connu jusqu'au "&TEXT(P176,"dd/mm/yyyy")&".",IF(O176="","Non précisé dans le calendrier pour cette échéance.","Réception : "&TEXT(O176,"dd/mm/yyyy")&" (suite au rachat du "&TEXT(N176,"dd/mm/yyyy")&")"))) | G176: =_xlfn.IFS(S176="aucune","Aucune pénalité de sortie."&IF(T176<>""," ("&T176&")",""),S176="manuel","⚠️ À VÉRIFIER MANUELLEMENT : "&T176,S176="inconnue","Pénalité non renseignée — vérifier la notice / DICI du fonds.",$C176="","Saisir une date d'investissement pour statuer sur la pénalité.",Q176="FUTUR","Date d'investissement postérieure à aujourd'hui — vérifier la saisie.",AD176>0,"⚠️ CONCERNÉ : pénalité de "&AD176&"% (détention "&Q176&" mois). "&T176,TRUE,"Non concerné (détention "&Q176&" mois). "&T176) | H176: =COUNTIFS(BDD_Calendrier!$A$2:$A$616,$B176,BDD_Calendrier!$C$2:$C$616,"Souscription") | I176: =IF(H176=0,"",IFERROR(_xlfn.MINIFS(BDD_Calendrier!$D$2:$D$616,BDD_Calendrier!$A$2:$A$616,$B176,BDD_Calendrier!$C$2:$C$616,"Souscription",BDD_Calendrier!$D$2:$D$616,">="&TODAY()),"")) | J176: =IF(I176="","",IFERROR(INDEX(BDD_Calendrier!$E$2:$E$616,MATCH($B176&"|Souscription|"&TEXT(I176,"yyyy-mm-dd"),BDD_Calendrier!$I$2:$I$616,0)),"")) | K176: =IF(H176=0,"",_xlfn.MAXIFS(BDD_Calendrier!$D$2:$D$616,BDD_Calendrier!$A$2:$A$616,$B176,BDD_Calendrier!$C$2:$C$616,"Souscription")) | L176: =COUNTIFS(BDD_Calendrier!$A$2:$A$616,$B176,BDD_Calendrier!$C$2:$C$616,"Rachat") | M176: =IF(L176=0,"",IFERROR(_xlfn.MINIFS(BDD_Calendrier!$D$2:$D$616,BDD_Calendrier!$A$2:$A$616,$B176,BDD_Calendrier!$C$2:$C$616,"Rachat",BDD_Calendrier!$D$2:$D$616,">="&TODAY()),"")) | N176: =IF(M176="","",IFERROR(INDEX(BDD_Calendrier!$E$2:$E$616,MATCH($B176&"|Rachat|"&TEXT(M176,"yyyy-mm-dd"),BDD_Calendrier!$I$2:$I$616,0)),"")) | O176: =IF(M176="","",IFERROR(INDEX(BDD_Calendrier!$H$2:$H$616,MATCH($B176&"|Rachat|"&TEXT(M176,"yyyy-mm-dd"),BDD_Calendrier!$I$2:$I$616,0)),"")) | P176: =IF(L176=0,"",_xlfn.MAXIFS(BDD_Calendrier!$D$2:$D$616,BDD_Calendrier!$A$2:$A$616,$B176,BDD_Calendrier!$C$2:$C$616,"Rachat")) | Q176: =IF($C176="","",IF($C176>TODAY(),"FUTUR",DATEDIF($C176,TODAY(),"m"))) | R176: =COUNTIF(BDD_Penalites!$A$2:$A$130,$B176) | S176: =IF(R176=0,"inconnue",INDEX(BDD_Penalites!$C$2:$C$130,MATCH($B176,BDD_Penalites!$A$2:$A$130,0))) | T176: =IF(R176=0,"",INDEX(BDD_Penalites!$M$2:$M$130,MATCH($B176,BDD_Penalites!$A$2:$A$130,0))) | U176: =IF(R176=0,0,INDEX(BDD_Penalites!$D$2:$D$130,MATCH($B176,BDD_Penalites!$A$2:$A$130,0))) | V176: =IF(R176=0,0,INDEX(BDD_Penalites!$E$2:$E$130,MATCH($B176,BDD_Penalites!$A$2:$A$130,0))) | W176: =IF(R176=0,0,INDEX(BDD_Penalites!$F$2:$F$130,MATCH($B176,BDD_Penalites!$A$2:$A$130,0))) | X176: =IF(R176=0,0,INDEX(BDD_Penalites!$G$2:$G$130,MATCH($B176,BDD_Penalites!$A$2:$A$130,0))) | Y176: =IF(R176=0,0,INDEX(BDD_Penalites!$H$2:$H$130,MATCH($B176,BDD_Penalites!$A$2:$A$130,0))) | Z176: =IF(R176=0,0,INDEX(BDD_Penalites!$I$2:$I$130,MATCH($B176,BDD_Penalites!$A$2:$A$130,0))) | AA176: =IF(R176=0,0,INDEX(BDD_Penalites!$J$2:$J$130,MATCH($B176,BDD_Penalites!$A$2:$A$130,0))) | AB176: =IF(R176=0,0,INDEX(BDD_Penalites!$K$2:$K$130,MATCH($B176,BDD_Penalites!$A$2:$A$130,0))) | AC176: =IF(R176=0,0,INDEX(BDD_Penalites!$L$2:$L$130,MATCH($B176,BDD_Penalites!$A$2:$A$130,0))) | AD176: =IF(OR($C176="",Q176="FUTUR"),"",_xlfn.IFS(Q176<U176,V176,Q176<W176,X176,Q176<Y176,Z176,Q176<AA176,AB176,TRUE,AC176))
A177: StepStone Structure | B177: LU3084311938 | D177: =IF(H177=0,"Calendrier non disponible pour ce fonds — contacter la société de gestion.",IF(I177="","Calendrier connu jusqu'au "&TEXT(K177,"dd/mm/yyyy")&" — demander le calendrier à jour.","Cut-off : "&TEXT(I177,"dd/mm/yyyy")&" | VL : "&TEXT(J177,"dd/mm/yyyy"))) | E177: =IF(L177=0,"Calendrier non disponible pour ce fonds — contacter la société de gestion.",IF(M177="","Calendrier connu jusqu'au "&TEXT(P177,"dd/mm/yyyy")&" — demander le calendrier à jour.","Cut-off : "&TEXT(M177,"dd/mm/yyyy")&" | VL : "&TEXT(N177,"dd/mm/yyyy"))) | F177: =IF(L177=0,"Calendrier non disponible pour ce fonds.",IF(M177="","Calendrier connu jusqu'au "&TEXT(P177,"dd/mm/yyyy")&".",IF(O177="","Non précisé dans le calendrier pour cette échéance.","Réception : "&TEXT(O177,"dd/mm/yyyy")&" (suite au rachat du "&TEXT(N177,"dd/mm/yyyy")&")"))) | G177: =_xlfn.IFS(S177="aucune","Aucune pénalité de sortie."&IF(T177<>""," ("&T177&")",""),S177="manuel","⚠️ À VÉRIFIER MANUELLEMENT : "&T177,S177="inconnue","Pénalité non renseignée — vérifier la notice / DICI du fonds.",$C177="","Saisir une date d'investissement pour statuer sur la pénalité.",Q177="FUTUR","Date d'investissement postérieure à aujourd'hui — vérifier la saisie.",AD177>0,"⚠️ CONCERNÉ : pénalité de "&AD177&"% (détention "&Q177&" mois). "&T177,TRUE,"Non concerné (détention "&Q177&" mois). "&T177) | H177: =COUNTIFS(BDD_Calendrier!$A$2:$A$616,$B177,BDD_Calendrier!$C$2:$C$616,"Souscription") | I177: =IF(H177=0,"",IFERROR(_xlfn.MINIFS(BDD_Calendrier!$D$2:$D$616,BDD_Calendrier!$A$2:$A$616,$B177,BDD_Calendrier!$C$2:$C$616,"Souscription",BDD_Calendrier!$D$2:$D$616,">="&TODAY()),"")) | J177: =IF(I177="","",IFERROR(INDEX(BDD_Calendrier!$E$2:$E$616,MATCH($B177&"|Souscription|"&TEXT(I177,"yyyy-mm-dd"),BDD_Calendrier!$I$2:$I$616,0)),"")) | K177: =IF(H177=0,"",_xlfn.MAXIFS(BDD_Calendrier!$D$2:$D$616,BDD_Calendrier!$A$2:$A$616,$B177,BDD_Calendrier!$C$2:$C$616,"Souscription")) | L177: =COUNTIFS(BDD_Calendrier!$A$2:$A$616,$B177,BDD_Calendrier!$C$2:$C$616,"Rachat") | M177: =IF(L177=0,"",IFERROR(_xlfn.MINIFS(BDD_Calendrier!$D$2:$D$616,BDD_Calendrier!$A$2:$A$616,$B177,BDD_Calendrier!$C$2:$C$616,"Rachat",BDD_Calendrier!$D$2:$D$616,">="&TODAY()),"")) | N177: =IF(M177="","",IFERROR(INDEX(BDD_Calendrier!$E$2:$E$616,MATCH($B177&"|Rachat|"&TEXT(M177,"yyyy-mm-dd"),BDD_Calendrier!$I$2:$I$616,0)),"")) | O177: =IF(M177="","",IFERROR(INDEX(BDD_Calendrier!$H$2:$H$616,MATCH($B177&"|Rachat|"&TEXT(M177,"yyyy-mm-dd"),BDD_Calendrier!$I$2:$I$616,0)),"")) | P177: =IF(L177=0,"",_xlfn.MAXIFS(BDD_Calendrier!$D$2:$D$616,BDD_Calendrier!$A$2:$A$616,$B177,BDD_Calendrier!$C$2:$C$616,"Rachat")) | Q177: =IF($C177="","",IF($C177>TODAY(),"FUTUR",DATEDIF($C177,TODAY(),"m"))) | R177: =COUNTIF(BDD_Penalites!$A$2:$A$130,$B177) | S177: =IF(R177=0,"inconnue",INDEX(BDD_Penalites!$C$2:$C$130,MATCH($B177,BDD_Penalites!$A$2:$A$130,0))) | T177: =IF(R177=0,"",INDEX(BDD_Penalites!$M$2:$M$130,MATCH($B177,BDD_Penalites!$A$2:$A$130,0))) | U177: =IF(R177=0,0,INDEX(BDD_Penalites!$D$2:$D$130,MATCH($B177,BDD_Penalites!$A$2:$A$130,0))) | V177: =IF(R177=0,0,INDEX(BDD_Penalites!$E$2:$E$130,MATCH($B177,BDD_Penalites!$A$2:$A$130,0))) | W177: =IF(R177=0,0,INDEX(BDD_Penalites!$F$2:$F$130,MATCH($B177,BDD_Penalites!$A$2:$A$130,0))) | X177: =IF(R177=0,0,INDEX(BDD_Penalites!$G$2:$G$130,MATCH($B177,BDD_Penalites!$A$2:$A$130,0))) | Y177: =IF(R177=0,0,INDEX(BDD_Penalites!$H$2:$H$130,MATCH($B177,BDD_Penalites!$A$2:$A$130,0))) | Z177: =IF(R177=0,0,INDEX(BDD_Penalites!$I$2:$I$130,MATCH($B177,BDD_Penalites!$A$2:$A$130,0))) | AA177: =IF(R177=0,0,INDEX(BDD_Penalites!$J$2:$J$130,MATCH($B177,BDD_Penalites!$A$2:$A$130,0))) | AB177: =IF(R177=0,0,INDEX(BDD_Penalites!$K$2:$K$130,MATCH($B177,BDD_Penalites!$A$2:$A$130,0))) | AC177: =IF(R177=0,0,INDEX(BDD_Penalites!$L$2:$L$130,MATCH($B177,BDD_Penalites!$A$2:$A$130,0))) | AD177: =IF(OR($C177="",Q177="FUTUR"),"",_xlfn.IFS(Q177<U177,V177,Q177<W177,X177,Q177<Y177,Z177,Q177<AA177,AB177,TRUE,AC177))
A178: EQT Nexus Infrastructure | B178: LU2984100870 | D178: =IF(H178=0,"Calendrier non disponible pour ce fonds — contacter la société de gestion.",IF(I178="","Calendrier connu jusqu'au "&TEXT(K178,"dd/mm/yyyy")&" — demander le calendrier à jour.","Cut-off : "&TEXT(I178,"dd/mm/yyyy")&" | VL : "&TEXT(J178,"dd/mm/yyyy"))) | E178: =IF(L178=0,"Calendrier non disponible pour ce fonds — contacter la société de gestion.",IF(M178="","Calendrier connu jusqu'au "&TEXT(P178,"dd/mm/yyyy")&" — demander le calendrier à jour.","Cut-off : "&TEXT(M178,"dd/mm/yyyy")&" | VL : "&TEXT(N178,"dd/mm/yyyy"))) | F178: =IF(L178=0,"Calendrier non disponible pour ce fonds.",IF(M178="","Calendrier connu jusqu'au "&TEXT(P178,"dd/mm/yyyy")&".",IF(O178="","Non précisé dans le calendrier pour cette échéance.","Réception : "&TEXT(O178,"dd/mm/yyyy")&" (suite au rachat du "&TEXT(N178,"dd/mm/yyyy")&")"))) | G178: =_xlfn.IFS(S178="aucune","Aucune pénalité de sortie."&IF(T178<>""," ("&T178&")",""),S178="manuel","⚠️ À VÉRIFIER MANUELLEMENT : "&T178,S178="inconnue","Pénalité non renseignée — vérifier la notice / DICI du fonds.",$C178="","Saisir une date d'investissement pour statuer sur la pénalité.",Q178="FUTUR","Date d'investissement postérieure à aujourd'hui — vérifier la saisie.",AD178>0,"⚠️ CONCERNÉ : pénalité de "&AD178&"% (détention "&Q178&" mois). "&T178,TRUE,"Non concerné (détention "&Q178&" mois). "&T178) | H178: =COUNTIFS(BDD_Calendrier!$A$2:$A$616,$B178,BDD_Calendrier!$C$2:$C$616,"Souscription") | I178: =IF(H178=0,"",IFERROR(_xlfn.MINIFS(BDD_Calendrier!$D$2:$D$616,BDD_Calendrier!$A$2:$A$616,$B178,BDD_Calendrier!$C$2:$C$616,"Souscription",BDD_Calendrier!$D$2:$D$616,">="&TODAY()),"")) | J178: =IF(I178="","",IFERROR(INDEX(BDD_Calendrier!$E$2:$E$616,MATCH($B178&"|Souscription|"&TEXT(I178,"yyyy-mm-dd"),BDD_Calendrier!$I$2:$I$616,0)),"")) | K178: =IF(H178=0,"",_xlfn.MAXIFS(BDD_Calendrier!$D$2:$D$616,BDD_Calendrier!$A$2:$A$616,$B178,BDD_Calendrier!$C$2:$C$616,"Souscription")) | L178: =COUNTIFS(BDD_Calendrier!$A$2:$A$616,$B178,BDD_Calendrier!$C$2:$C$616,"Rachat") | M178: =IF(L178=0,"",IFERROR(_xlfn.MINIFS(BDD_Calendrier!$D$2:$D$616,BDD_Calendrier!$A$2:$A$616,$B178,BDD_Calendrier!$C$2:$C$616,"Rachat",BDD_Calendrier!$D$2:$D$616,">="&TODAY()),"")) | N178: =IF(M178="","",IFERROR(INDEX(BDD_Calendrier!$E$2:$E$616,MATCH($B178&"|Rachat|"&TEXT(M178,"yyyy-mm-dd"),BDD_Calendrier!$I$2:$I$616,0)),"")) | O178: =IF(M178="","",IFERROR(INDEX(BDD_Calendrier!$H$2:$H$616,MATCH($B178&"|Rachat|"&TEXT(M178,"yyyy-mm-dd"),BDD_Calendrier!$I$2:$I$616,0)),"")) | P178: =IF(L178=0,"",_xlfn.MAXIFS(BDD_Calendrier!$D$2:$D$616,BDD_Calendrier!$A$2:$A$616,$B178,BDD_Calendrier!$C$2:$C$616,"Rachat")) | Q178: =IF($C178="","",IF($C178>TODAY(),"FUTUR",DATEDIF($C178,TODAY(),"m"))) | R178: =COUNTIF(BDD_Penalites!$A$2:$A$130,$B178) | S178: =IF(R178=0,"inconnue",INDEX(BDD_Penalites!$C$2:$C$130,MATCH($B178,BDD_Penalites!$A$2:$A$130,0))) | T178: =IF(R178=0,"",INDEX(BDD_Penalites!$M$2:$M$130,MATCH($B178,BDD_Penalites!$A$2:$A$130,0))) | U178: =IF(R178=0,0,INDEX(BDD_Penalites!$D$2:$D$130,MATCH($B178,BDD_Penalites!$A$2:$A$130,0))) | V178: =IF(R178=0,0,INDEX(BDD_Penalites!$E$2:$E$130,MATCH($B178,BDD_Penalites!$A$2:$A$130,0))) | W178: =IF(R178=0,0,INDEX(BDD_Penalites!$F$2:$F$130,MATCH($B178,BDD_Penalites!$A$2:$A$130,0))) | X178: =IF(R178=0,0,INDEX(BDD_Penalites!$G$2:$G$130,MATCH($B178,BDD_Penalites!$A$2:$A$130,0))) | Y178: =IF(R178=0,0,INDEX(BDD_Penalites!$H$2:$H$130,MATCH($B178,BDD_Penalites!$A$2:$A$130,0))) | Z178: =IF(R178=0,0,INDEX(BDD_Penalites!$I$2:$I$130,MATCH($B178,BDD_Penalites!$A$2:$A$130,0))) | AA178: =IF(R178=0,0,INDEX(BDD_Penalites!$J$2:$J$130,MATCH($B178,BDD_Penalites!$A$2:$A$130,0))) | AB178: =IF(R178=0,0,INDEX(BDD_Penalites!$K$2:$K$130,MATCH($B178,BDD_Penalites!$A$2:$A$130,0))) | AC178: =IF(R178=0,0,INDEX(BDD_Penalites!$L$2:$L$130,MATCH($B178,BDD_Penalites!$A$2:$A$130,0))) | AD178: =IF(OR($C178="",Q178="FUTUR"),"",_xlfn.IFS(Q178<U178,V178,Q178<W178,X178,Q178<Y178,Z178,Q178<AA178,AB178,TRUE,AC178))
A179: Partners Group Next Generation Infrastructure | B179: LU2710930046 | D179: =IF(H179=0,"Calendrier non disponible pour ce fonds — contacter la société de gestion.",IF(I179="","Calendrier connu jusqu'au "&TEXT(K179,"dd/mm/yyyy")&" — demander le calendrier à jour.","Cut-off : "&TEXT(I179,"dd/mm/yyyy")&" | VL : "&TEXT(J179,"dd/mm/yyyy"))) | E179: =IF(L179=0,"Calendrier non disponible pour ce fonds — contacter la société de gestion.",IF(M179="","Calendrier connu jusqu'au "&TEXT(P179,"dd/mm/yyyy")&" — demander le calendrier à jour.","Cut-off : "&TEXT(M179,"dd/mm/yyyy")&" | VL : "&TEXT(N179,"dd/mm/yyyy"))) | F179: =IF(L179=0,"Calendrier non disponible pour ce fonds.",IF(M179="","Calendrier connu jusqu'au "&TEXT(P179,"dd/mm/yyyy")&".",IF(O179="","Non précisé dans le calendrier pour cette échéance.","Réception : "&TEXT(O179,"dd/mm/yyyy")&" (suite au rachat du "&TEXT(N179,"dd/mm/yyyy")&")"))) | G179: =_xlfn.IFS(S179="aucune","Aucune pénalité de sortie."&IF(T179<>""," ("&T179&")",""),S179="manuel","⚠️ À VÉRIFIER MANUELLEMENT : "&T179,S179="inconnue","Pénalité non renseignée — vérifier la notice / DICI du fonds.",$C179="","Saisir une date d'investissement pour statuer sur la pénalité.",Q179="FUTUR","Date d'investissement postérieure à aujourd'hui — vérifier la saisie.",AD179>0,"⚠️ CONCERNÉ : pénalité de "&AD179&"% (détention "&Q179&" mois). "&T179,TRUE,"Non concerné (détention "&Q179&" mois). "&T179) | H179: =COUNTIFS(BDD_Calendrier!$A$2:$A$616,$B179,BDD_Calendrier!$C$2:$C$616,"Souscription") | I179: =IF(H179=0,"",IFERROR(_xlfn.MINIFS(BDD_Calendrier!$D$2:$D$616,BDD_Calendrier!$A$2:$A$616,$B179,BDD_Calendrier!$C$2:$C$616,"Souscription",BDD_Calendrier!$D$2:$D$616,">="&TODAY()),"")) | J179: =IF(I179="","",IFERROR(INDEX(BDD_Calendrier!$E$2:$E$616,MATCH($B179&"|Souscription|"&TEXT(I179,"yyyy-mm-dd"),BDD_Calendrier!$I$2:$I$616,0)),"")) | K179: =IF(H179=0,"",_xlfn.MAXIFS(BDD_Calendrier!$D$2:$D$616,BDD_Calendrier!$A$2:$A$616,$B179,BDD_Calendrier!$C$2:$C$616,"Souscription")) | L179: =COUNTIFS(BDD_Calendrier!$A$2:$A$616,$B179,BDD_Calendrier!$C$2:$C$616,"Rachat") | M179: =IF(L179=0,"",IFERROR(_xlfn.MINIFS(BDD_Calendrier!$D$2:$D$616,BDD_Calendrier!$A$2:$A$616,$B179,BDD_Calendrier!$C$2:$C$616,"Rachat",BDD_Calendrier!$D$2:$D$616,">="&TODAY()),"")) | N179: =IF(M179="","",IFERROR(INDEX(BDD_Calendrier!$E$2:$E$616,MATCH($B179&"|Rachat|"&TEXT(M179,"yyyy-mm-dd"),BDD_Calendrier!$I$2:$I$616,0)),"")) | O179: =IF(M179="","",IFERROR(INDEX(BDD_Calendrier!$H$2:$H$616,MATCH($B179&"|Rachat|"&TEXT(M179,"yyyy-mm-dd"),BDD_Calendrier!$I$2:$I$616,0)),"")) | P179: =IF(L179=0,"",_xlfn.MAXIFS(BDD_Calendrier!$D$2:$D$616,BDD_Calendrier!$A$2:$A$616,$B179,BDD_Calendrier!$C$2:$C$616,"Rachat")) | Q179: =IF($C179="","",IF($C179>TODAY(),"FUTUR",DATEDIF($C179,TODAY(),"m"))) | R179: =COUNTIF(BDD_Penalites!$A$2:$A$130,$B179) | S179: =IF(R179=0,"inconnue",INDEX(BDD_Penalites!$C$2:$C$130,MATCH($B179,BDD_Penalites!$A$2:$A$130,0))) | T179: =IF(R179=0,"",INDEX(BDD_Penalites!$M$2:$M$130,MATCH($B179,BDD_Penalites!$A$2:$A$130,0))) | U179: =IF(R179=0,0,INDEX(BDD_Penalites!$D$2:$D$130,MATCH($B179,BDD_Penalites!$A$2:$A$130,0))) | V179: =IF(R179=0,0,INDEX(BDD_Penalites!$E$2:$E$130,MATCH($B179,BDD_Penalites!$A$2:$A$130,0))) | W179: =IF(R179=0,0,INDEX(BDD_Penalites!$F$2:$F$130,MATCH($B179,BDD_Penalites!$A$2:$A$130,0))) | X179: =IF(R179=0,0,INDEX(BDD_Penalites!$G$2:$G$130,MATCH($B179,BDD_Penalites!$A$2:$A$130,0))) | Y179: =IF(R179=0,0,INDEX(BDD_Penalites!$H$2:$H$130,MATCH($B179,BDD_Penalites!$A$2:$A$130,0))) | Z179: =IF(R179=0,0,INDEX(BDD_Penalites!$I$2:$I$130,MATCH($B179,BDD_Penalites!$A$2:$A$130,0))) | AA179: =IF(R179=0,0,INDEX(BDD_Penalites!$J$2:$J$130,MATCH($B179,BDD_Penalites!$A$2:$A$130,0))) | AB179: =IF(R179=0,0,INDEX(BDD_Penalites!$K$2:$K$130,MATCH($B179,BDD_Penalites!$A$2:$A$130,0))) | AC179: =IF(R179=0,0,INDEX(BDD_Penalites!$L$2:$L$130,MATCH($B179,BDD_Penalites!$A$2:$A$130,0))) | AD179: =IF(OR($C179="",Q179="FUTUR"),"",_xlfn.IFS(Q179<U179,V179,Q179<W179,X179,Q179<Y179,Z179,Q179<AA179,AB179,TRUE,AC179))
A180: Brookfield Infrastructure Income | B180: LU2571548820 | D180: =IF(H180=0,"Calendrier non disponible pour ce fonds — contacter la société de gestion.",IF(I180="","Calendrier connu jusqu'au "&TEXT(K180,"dd/mm/yyyy")&" — demander le calendrier à jour.","Cut-off : "&TEXT(I180,"dd/mm/yyyy")&" | VL : "&TEXT(J180,"dd/mm/yyyy"))) | E180: =IF(L180=0,"Calendrier non disponible pour ce fonds — contacter la société de gestion.",IF(M180="","Calendrier connu jusqu'au "&TEXT(P180,"dd/mm/yyyy")&" — demander le calendrier à jour.","Cut-off : "&TEXT(M180,"dd/mm/yyyy")&" | VL : "&TEXT(N180,"dd/mm/yyyy"))) | F180: =IF(L180=0,"Calendrier non disponible pour ce fonds.",IF(M180="","Calendrier connu jusqu'au "&TEXT(P180,"dd/mm/yyyy")&".",IF(O180="","Non précisé dans le calendrier pour cette échéance.","Réception : "&TEXT(O180,"dd/mm/yyyy")&" (suite au rachat du "&TEXT(N180,"dd/mm/yyyy")&")"))) | G180: =_xlfn.IFS(S180="aucune","Aucune pénalité de sortie."&IF(T180<>""," ("&T180&")",""),S180="manuel","⚠️ À VÉRIFIER MANUELLEMENT : "&T180,S180="inconnue","Pénalité non renseignée — vérifier la notice / DICI du fonds.",$C180="","Saisir une date d'investissement pour statuer sur la pénalité.",Q180="FUTUR","Date d'investissement postérieure à aujourd'hui — vérifier la saisie.",AD180>0,"⚠️ CONCERNÉ : pénalité de "&AD180&"% (détention "&Q180&" mois). "&T180,TRUE,"Non concerné (détention "&Q180&" mois). "&T180) | H180: =COUNTIFS(BDD_Calendrier!$A$2:$A$616,$B180,BDD_Calendrier!$C$2:$C$616,"Souscription") | I180: =IF(H180=0,"",IFERROR(_xlfn.MINIFS(BDD_Calendrier!$D$2:$D$616,BDD_Calendrier!$A$2:$A$616,$B180,BDD_Calendrier!$C$2:$C$616,"Souscription",BDD_Calendrier!$D$2:$D$616,">="&TODAY()),"")) | J180: =IF(I180="","",IFERROR(INDEX(BDD_Calendrier!$E$2:$E$616,MATCH($B180&"|Souscription|"&TEXT(I180,"yyyy-mm-dd"),BDD_Calendrier!$I$2:$I$616,0)),"")) | K180: =IF(H180=0,"",_xlfn.MAXIFS(BDD_Calendrier!$D$2:$D$616,BDD_Calendrier!$A$2:$A$616,$B180,BDD_Calendrier!$C$2:$C$616,"Souscription")) | L180: =COUNTIFS(BDD_Calendrier!$A$2:$A$616,$B180,BDD_Calendrier!$C$2:$C$616,"Rachat") | M180: =IF(L180=0,"",IFERROR(_xlfn.MINIFS(BDD_Calendrier!$D$2:$D$616,BDD_Calendrier!$A$2:$A$616,$B180,BDD_Calendrier!$C$2:$C$616,"Rachat",BDD_Calendrier!$D$2:$D$616,">="&TODAY()),"")) | N180: =IF(M180="","",IFERROR(INDEX(BDD_Calendrier!$E$2:$E$616,MATCH($B180&"|Rachat|"&TEXT(M180,"yyyy-mm-dd"),BDD_Calendrier!$I$2:$I$616,0)),"")) | O180: =IF(M180="","",IFERROR(INDEX(BDD_Calendrier!$H$2:$H$616,MATCH($B180&"|Rachat|"&TEXT(M180,"yyyy-mm-dd"),BDD_Calendrier!$I$2:$I$616,0)),"")) | P180: =IF(L180=0,"",_xlfn.MAXIFS(BDD_Calendrier!$D$2:$D$616,BDD_Calendrier!$A$2:$A$616,$B180,BDD_Calendrier!$C$2:$C$616,"Rachat")) | Q180: =IF($C180="","",IF($C180>TODAY(),"FUTUR",DATEDIF($C180,TODAY(),"m"))) | R180: =COUNTIF(BDD_Penalites!$A$2:$A$130,$B180) | S180: =IF(R180=0,"inconnue",INDEX(BDD_Penalites!$C$2:$C$130,MATCH($B180,BDD_Penalites!$A$2:$A$130,0))) | T180: =IF(R180=0,"",INDEX(BDD_Penalites!$M$2:$M$130,MATCH($B180,BDD_Penalites!$A$2:$A$130,0))) | U180: =IF(R180=0,0,INDEX(BDD_Penalites!$D$2:$D$130,MATCH($B180,BDD_Penalites!$A$2:$A$130,0))) | V180: =IF(R180=0,0,INDEX(BDD_Penalites!$E$2:$E$130,MATCH($B180,BDD_Penalites!$A$2:$A$130,0))) | W180: =IF(R180=0,0,INDEX(BDD_Penalites!$F$2:$F$130,MATCH($B180,BDD_Penalites!$A$2:$A$130,0))) | X180: =IF(R180=0,0,INDEX(BDD_Penalites!$G$2:$G$130,MATCH($B180,BDD_Penalites!$A$2:$A$130,0))) | Y180: =IF(R180=0,0,INDEX(BDD_Penalites!$H$2:$H$130,MATCH($B180,BDD_Penalites!$A$2:$A$130,0))) | Z180: =IF(R180=0,0,INDEX(BDD_Penalites!$I$2:$I$130,MATCH($B180,BDD_Penalites!$A$2:$A$130,0))) | AA180: =IF(R180=0,0,INDEX(BDD_Penalites!$J$2:$J$130,MATCH($B180,BDD_Penalites!$A$2:$A$130,0))) | AB180: =IF(R180=0,0,INDEX(BDD_Penalites!$K$2:$K$130,MATCH($B180,BDD_Penalites!$A$2:$A$130,0))) | AC180: =IF(R180=0,0,INDEX(BDD_Penalites!$L$2:$L$130,MATCH($B180,BDD_Penalites!$A$2:$A$130,0))) | AD180: =IF(OR($C180="",Q180="FUTUR"),"",_xlfn.IFS(Q180<U180,V180,Q180<W180,X180,Q180<Y180,Z180,Q180<AA180,AB180,TRUE,AC180))
A181: Stepstone Priv Infra A | B181: LU2677665254 | D181: =IF(H181=0,"Calendrier non disponible pour ce fonds — contacter la société de gestion.",IF(I181="","Calendrier connu jusqu'au "&TEXT(K181,"dd/mm/yyyy")&" — demander le calendrier à jour.","Cut-off : "&TEXT(I181,"dd/mm/yyyy")&" | VL : "&TEXT(J181,"dd/mm/yyyy"))) | E181: =IF(L181=0,"Calendrier non disponible pour ce fonds — contacter la société de gestion.",IF(M181="","Calendrier connu jusqu'au "&TEXT(P181,"dd/mm/yyyy")&" — demander le calendrier à jour.","Cut-off : "&TEXT(M181,"dd/mm/yyyy")&" | VL : "&TEXT(N181,"dd/mm/yyyy"))) | F181: =IF(L181=0,"Calendrier non disponible pour ce fonds.",IF(M181="","Calendrier connu jusqu'au "&TEXT(P181,"dd/mm/yyyy")&".",IF(O181="","Non précisé dans le calendrier pour cette échéance.","Réception : "&TEXT(O181,"dd/mm/yyyy")&" (suite au rachat du "&TEXT(N181,"dd/mm/yyyy")&")"))) | G181: =_xlfn.IFS(S181="aucune","Aucune pénalité de sortie."&IF(T181<>""," ("&T181&")",""),S181="manuel","⚠️ À VÉRIFIER MANUELLEMENT : "&T181,S181="inconnue","Pénalité non renseignée — vérifier la notice / DICI du fonds.",$C181="","Saisir une date d'investissement pour statuer sur la pénalité.",Q181="FUTUR","Date d'investissement postérieure à aujourd'hui — vérifier la saisie.",AD181>0,"⚠️ CONCERNÉ : pénalité de "&AD181&"% (détention "&Q181&" mois). "&T181,TRUE,"Non concerné (détention "&Q181&" mois). "&T181) | H181: =COUNTIFS(BDD_Calendrier!$A$2:$A$616,$B181,BDD_Calendrier!$C$2:$C$616,"Souscription") | I181: =IF(H181=0,"",IFERROR(_xlfn.MINIFS(BDD_Calendrier!$D$2:$D$616,BDD_Calendrier!$A$2:$A$616,$B181,BDD_Calendrier!$C$2:$C$616,"Souscription",BDD_Calendrier!$D$2:$D$616,">="&TODAY()),"")) | J181: =IF(I181="","",IFERROR(INDEX(BDD_Calendrier!$E$2:$E$616,MATCH($B181&"|Souscription|"&TEXT(I181,"yyyy-mm-dd"),BDD_Calendrier!$I$2:$I$616,0)),"")) | K181: =IF(H181=0,"",_xlfn.MAXIFS(BDD_Calendrier!$D$2:$D$616,BDD_Calendrier!$A$2:$A$616,$B181,BDD_Calendrier!$C$2:$C$616,"Souscription")) | L181: =COUNTIFS(BDD_Calendrier!$A$2:$A$616,$B181,BDD_Calendrier!$C$2:$C$616,"Rachat") | M181: =IF(L181=0,"",IFERROR(_xlfn.MINIFS(BDD_Calendrier!$D$2:$D$616,BDD_Calendrier!$A$2:$A$616,$B181,BDD_Calendrier!$C$2:$C$616,"Rachat",BDD_Calendrier!$D$2:$D$616,">="&TODAY()),"")) | N181: =IF(M181="","",IFERROR(INDEX(BDD_Calendrier!$E$2:$E$616,MATCH($B181&"|Rachat|"&TEXT(M181,"yyyy-mm-dd"),BDD_Calendrier!$I$2:$I$616,0)),"")) | O181: =IF(M181="","",IFERROR(INDEX(BDD_Calendrier!$H$2:$H$616,MATCH($B181&"|Rachat|"&TEXT(M181,"yyyy-mm-dd"),BDD_Calendrier!$I$2:$I$616,0)),"")) | P181: =IF(L181=0,"",_xlfn.MAXIFS(BDD_Calendrier!$D$2:$D$616,BDD_Calendrier!$A$2:$A$616,$B181,BDD_Calendrier!$C$2:$C$616,"Rachat")) | Q181: =IF($C181="","",IF($C181>TODAY(),"FUTUR",DATEDIF($C181,TODAY(),"m"))) | R181: =COUNTIF(BDD_Penalites!$A$2:$A$130,$B181) | S181: =IF(R181=0,"inconnue",INDEX(BDD_Penalites!$C$2:$C$130,MATCH($B181,BDD_Penalites!$A$2:$A$130,0))) | T181: =IF(R181=0,"",INDEX(BDD_Penalites!$M$2:$M$130,MATCH($B181,BDD_Penalites!$A$2:$A$130,0))) | U181: =IF(R181=0,0,INDEX(BDD_Penalites!$D$2:$D$130,MATCH($B181,BDD_Penalites!$A$2:$A$130,0))) | V181: =IF(R181=0,0,INDEX(BDD_Penalites!$E$2:$E$130,MATCH($B181,BDD_Penalites!$A$2:$A$130,0))) | W181: =IF(R181=0,0,INDEX(BDD_Penalites!$F$2:$F$130,MATCH($B181,BDD_Penalites!$A$2:$A$130,0))) | X181: =IF(R181=0,0,INDEX(BDD_Penalites!$G$2:$G$130,MATCH($B181,BDD_Penalites!$A$2:$A$130,0))) | Y181: =IF(R181=0,0,INDEX(BDD_Penalites!$H$2:$H$130,MATCH($B181,BDD_Penalites!$A$2:$A$130,0))) | Z181: =IF(R181=0,0,INDEX(BDD_Penalites!$I$2:$I$130,MATCH($B181,BDD_Penalites!$A$2:$A$130,0))) | AA181: =IF(R181=0,0,INDEX(BDD_Penalites!$J$2:$J$130,MATCH($B181,BDD_Penalites!$A$2:$A$130,0))) | AB181: =IF(R181=0,0,INDEX(BDD_Penalites!$K$2:$K$130,MATCH($B181,BDD_Penalites!$A$2:$A$130,0))) | AC181: =IF(R181=0,0,INDEX(BDD_Penalites!$L$2:$L$130,MATCH($B181,BDD_Penalites!$A$2:$A$130,0))) | AD181: =IF(OR($C181="",Q181="FUTUR"),"",_xlfn.IFS(Q181<U181,V181,Q181<W181,X181,Q181<Y181,Z181,Q181<AA181,AB181,TRUE,AC181))
A182: FCPR Eiffel Infrastructures Vertes C | B182: FR001400BCG0 | D182: =IF(H182=0,"Calendrier non disponible pour ce fonds — contacter la société de gestion.",IF(I182="","Calendrier connu jusqu'au "&TEXT(K182,"dd/mm/yyyy")&" — demander le calendrier à jour.","Cut-off : "&TEXT(I182,"dd/mm/yyyy")&" | VL : "&TEXT(J182,"dd/mm/yyyy"))) | E182: =IF(L182=0,"Calendrier non disponible pour ce fonds — contacter la société de gestion.",IF(M182="","Calendrier connu jusqu'au "&TEXT(P182,"dd/mm/yyyy")&" — demander le calendrier à jour.","Cut-off : "&TEXT(M182,"dd/mm/yyyy")&" | VL : "&TEXT(N182,"dd/mm/yyyy"))) | F182: =IF(L182=0,"Calendrier non disponible pour ce fonds.",IF(M182="","Calendrier connu jusqu'au "&TEXT(P182,"dd/mm/yyyy")&".",IF(O182="","Non précisé dans le calendrier pour cette échéance.","Réception : "&TEXT(O182,"dd/mm/yyyy")&" (suite au rachat du "&TEXT(N182,"dd/mm/yyyy")&")"))) | G182: =_xlfn.IFS(S182="aucune","Aucune pénalité de sortie."&IF(T182<>""," ("&T182&")",""),S182="manuel","⚠️ À VÉRIFIER MANUELLEMENT : "&T182,S182="inconnue","Pénalité non renseignée — vérifier la notice / DICI du fonds.",$C182="","Saisir une date d'investissement pour statuer sur la pénalité.",Q182="FUTUR","Date d'investissement postérieure à aujourd'hui — vérifier la saisie.",AD182>0,"⚠️ CONCERNÉ : pénalité de "&AD182&"% (détention "&Q182&" mois). "&T182,TRUE,"Non concerné (détention "&Q182&" mois). "&T182) | H182: =COUNTIFS(BDD_Calendrier!$A$2:$A$616,$B182,BDD_Calendrier!$C$2:$C$616,"Souscription") | I182: =IF(H182=0,"",IFERROR(_xlfn.MINIFS(BDD_Calendrier!$D$2:$D$616,BDD_Calendrier!$A$2:$A$616,$B182,BDD_Calendrier!$C$2:$C$616,"Souscription",BDD_Calendrier!$D$2:$D$616,">="&TODAY()),"")) | J182: =IF(I182="","",IFERROR(INDEX(BDD_Calendrier!$E$2:$E$616,MATCH($B182&"|Souscription|"&TEXT(I182,"yyyy-mm-dd"),BDD_Calendrier!$I$2:$I$616,0)),"")) | K182: =IF(H182=0,"",_xlfn.MAXIFS(BDD_Calendrier!$D$2:$D$616,BDD_Calendrier!$A$2:$A$616,$B182,BDD_Calendrier!$C$2:$C$616,"Souscription")) | L182: =COUNTIFS(BDD_Calendrier!$A$2:$A$616,$B182,BDD_Calendrier!$C$2:$C$616,"Rachat") | M182: =IF(L182=0,"",IFERROR(_xlfn.MINIFS(BDD_Calendrier!$D$2:$D$616,BDD_Calendrier!$A$2:$A$616,$B182,BDD_Calendrier!$C$2:$C$616,"Rachat",BDD_Calendrier!$D$2:$D$616,">="&TODAY()),"")) | N182: =IF(M182="","",IFERROR(INDEX(BDD_Calendrier!$E$2:$E$616,MATCH($B182&"|Rachat|"&TEXT(M182,"yyyy-mm-dd"),BDD_Calendrier!$I$2:$I$616,0)),"")) | O182: =IF(M182="","",IFERROR(INDEX(BDD_Calendrier!$H$2:$H$616,MATCH($B182&"|Rachat|"&TEXT(M182,"yyyy-mm-dd"),BDD_Calendrier!$I$2:$I$616,0)),"")) | P182: =IF(L182=0,"",_xlfn.MAXIFS(BDD_Calendrier!$D$2:$D$616,BDD_Calendrier!$A$2:$A$616,$B182,BDD_Calendrier!$C$2:$C$616,"Rachat")) | Q182: =IF($C182="","",IF($C182>TODAY(),"FUTUR",DATEDIF($C182,TODAY(),"m"))) | R182: =COUNTIF(BDD_Penalites!$A$2:$A$130,$B182) | S182: =IF(R182=0,"inconnue",INDEX(BDD_Penalites!$C$2:$C$130,MATCH($B182,BDD_Penalites!$A$2:$A$130,0))) | T182: =IF(R182=0,"",INDEX(BDD_Penalites!$M$2:$M$130,MATCH($B182,BDD_Penalites!$A$2:$A$130,0))) | U182: =IF(R182=0,0,INDEX(BDD_Penalites!$D$2:$D$130,MATCH($B182,BDD_Penalites!$A$2:$A$130,0))) | V182: =IF(R182=0,0,INDEX(BDD_Penalites!$E$2:$E$130,MATCH($B182,BDD_Penalites!$A$2:$A$130,0))) | W182: =IF(R182=0,0,INDEX(BDD_Penalites!$F$2:$F$130,MATCH($B182,BDD_Penalites!$A$2:$A$130,0))) | X182: =IF(R182=0,0,INDEX(BDD_Penalites!$G$2:$G$130,MATCH($B182,BDD_Penalites!$A$2:$A$130,0))) | Y182: =IF(R182=0,0,INDEX(BDD_Penalites!$H$2:$H$130,MATCH($B182,BDD_Penalites!$A$2:$A$130,0))) | Z182: =IF(R182=0,0,INDEX(BDD_Penalites!$I$2:$I$130,MATCH($B182,BDD_Penalites!$A$2:$A$130,0))) | AA182: =IF(R182=0,0,INDEX(BDD_Penalites!$J$2:$J$130,MATCH($B182,BDD_Penalites!$A$2:$A$130,0))) | AB182: =IF(R182=0,0,INDEX(BDD_Penalites!$K$2:$K$130,MATCH($B182,BDD_Penalites!$A$2:$A$130,0))) | AC182: =IF(R182=0,0,INDEX(BDD_Penalites!$L$2:$L$130,MATCH($B182,BDD_Penalites!$A$2:$A$130,0))) | AD182: =IF(OR($C182="",Q182="FUTUR"),"",_xlfn.IFS(Q182<U182,V182,Q182<W182,X182,Q182<Y182,Z182,Q182<AA182,AB182,TRUE,AC182))
A183: Rive Tangible Assets Income Fund | B183: LU2441620379 | D183: =IF(H183=0,"Calendrier non disponible pour ce fonds — contacter la société de gestion.",IF(I183="","Calendrier connu jusqu'au "&TEXT(K183,"dd/mm/yyyy")&" — demander le calendrier à jour.","Cut-off : "&TEXT(I183,"dd/mm/yyyy")&" | VL : "&TEXT(J183,"dd/mm/yyyy"))) | E183: =IF(L183=0,"Calendrier non disponible pour ce fonds — contacter la société de gestion.",IF(M183="","Calendrier connu jusqu'au "&TEXT(P183,"dd/mm/yyyy")&" — demander le calendrier à jour.","Cut-off : "&TEXT(M183,"dd/mm/yyyy")&" | VL : "&TEXT(N183,"dd/mm/yyyy"))) | F183: =IF(L183=0,"Calendrier non disponible pour ce fonds.",IF(M183="","Calendrier connu jusqu'au "&TEXT(P183,"dd/mm/yyyy")&".",IF(O183="","Non précisé dans le calendrier pour cette échéance.","Réception : "&TEXT(O183,"dd/mm/yyyy")&" (suite au rachat du "&TEXT(N183,"dd/mm/yyyy")&")"))) | G183: =_xlfn.IFS(S183="aucune","Aucune pénalité de sortie."&IF(T183<>""," ("&T183&")",""),S183="manuel","⚠️ À VÉRIFIER MANUELLEMENT : "&T183,S183="inconnue","Pénalité non renseignée — vérifier la notice / DICI du fonds.",$C183="","Saisir une date d'investissement pour statuer sur la pénalité.",Q183="FUTUR","Date d'investissement postérieure à aujourd'hui — vérifier la saisie.",AD183>0,"⚠️ CONCERNÉ : pénalité de "&AD183&"% (détention "&Q183&" mois). "&T183,TRUE,"Non concerné (détention "&Q183&" mois). "&T183) | H183: =COUNTIFS(BDD_Calendrier!$A$2:$A$616,$B183,BDD_Calendrier!$C$2:$C$616,"Souscription") | I183: =IF(H183=0,"",IFERROR(_xlfn.MINIFS(BDD_Calendrier!$D$2:$D$616,BDD_Calendrier!$A$2:$A$616,$B183,BDD_Calendrier!$C$2:$C$616,"Souscription",BDD_Calendrier!$D$2:$D$616,">="&TODAY()),"")) | J183: =IF(I183="","",IFERROR(INDEX(BDD_Calendrier!$E$2:$E$616,MATCH($B183&"|Souscription|"&TEXT(I183,"yyyy-mm-dd"),BDD_Calendrier!$I$2:$I$616,0)),"")) | K183: =IF(H183=0,"",_xlfn.MAXIFS(BDD_Calendrier!$D$2:$D$616,BDD_Calendrier!$A$2:$A$616,$B183,BDD_Calendrier!$C$2:$C$616,"Souscription")) | L183: =COUNTIFS(BDD_Calendrier!$A$2:$A$616,$B183,BDD_Calendrier!$C$2:$C$616,"Rachat") | M183: =IF(L183=0,"",IFERROR(_xlfn.MINIFS(BDD_Calendrier!$D$2:$D$616,BDD_Calendrier!$A$2:$A$616,$B183,BDD_Calendrier!$C$2:$C$616,"Rachat",BDD_Calendrier!$D$2:$D$616,">="&TODAY()),"")) | N183: =IF(M183="","",IFERROR(INDEX(BDD_Calendrier!$E$2:$E$616,MATCH($B183&"|Rachat|"&TEXT(M183,"yyyy-mm-dd"),BDD_Calendrier!$I$2:$I$616,0)),"")) | O183: =IF(M183="","",IFERROR(INDEX(BDD_Calendrier!$H$2:$H$616,MATCH($B183&"|Rachat|"&TEXT(M183,"yyyy-mm-dd"),BDD_Calendrier!$I$2:$I$616,0)),"")) | P183: =IF(L183=0,"",_xlfn.MAXIFS(BDD_Calendrier!$D$2:$D$616,BDD_Calendrier!$A$2:$A$616,$B183,BDD_Calendrier!$C$2:$C$616,"Rachat")) | Q183: =IF($C183="","",IF($C183>TODAY(),"FUTUR",DATEDIF($C183,TODAY(),"m"))) | R183: =COUNTIF(BDD_Penalites!$A$2:$A$130,$B183) | S183: =IF(R183=0,"inconnue",INDEX(BDD_Penalites!$C$2:$C$130,MATCH($B183,BDD_Penalites!$A$2:$A$130,0))) | T183: =IF(R183=0,"",INDEX(BDD_Penalites!$M$2:$M$130,MATCH($B183,BDD_Penalites!$A$2:$A$130,0))) | U183: =IF(R183=0,0,INDEX(BDD_Penalites!$D$2:$D$130,MATCH($B183,BDD_Penalites!$A$2:$A$130,0))) | V183: =IF(R183=0,0,INDEX(BDD_Penalites!$E$2:$E$130,MATCH($B183,BDD_Penalites!$A$2:$A$130,0))) | W183: =IF(R183=0,0,INDEX(BDD_Penalites!$F$2:$F$130,MATCH($B183,BDD_Penalites!$A$2:$A$130,0))) | X183: =IF(R183=0,0,INDEX(BDD_Penalites!$G$2:$G$130,MATCH($B183,BDD_Penalites!$A$2:$A$130,0))) | Y183: =IF(R183=0,0,INDEX(BDD_Penalites!$H$2:$H$130,MATCH($B183,BDD_Penalites!$A$2:$A$130,0))) | Z183: =IF(R183=0,0,INDEX(BDD_Penalites!$I$2:$I$130,MATCH($B183,BDD_Penalites!$A$2:$A$130,0))) | AA183: =IF(R183=0,0,INDEX(BDD_Penalites!$J$2:$J$130,MATCH($B183,BDD_Penalites!$A$2:$A$130,0))) | AB183: =IF(R183=0,0,INDEX(BDD_Penalites!$K$2:$K$130,MATCH($B183,BDD_Penalites!$A$2:$A$130,0))) | AC183: =IF(R183=0,0,INDEX(BDD_Penalites!$L$2:$L$130,MATCH($B183,BDD_Penalites!$A$2:$A$130,0))) | AD183: =IF(OR($C183="",Q183="FUTUR"),"",_xlfn.IFS(Q183<U183,V183,Q183<W183,X183,Q183<Y183,Z183,Q183<AA183,AB183,TRUE,AC183))
A184: FCPR AXA Avenir Infrastructures Parts T | B184: FR001400BZG1 | D184: =IF(H184=0,"Calendrier non disponible pour ce fonds — contacter la société de gestion.",IF(I184="","Calendrier connu jusqu'au "&TEXT(K184,"dd/mm/yyyy")&" — demander le calendrier à jour.","Cut-off : "&TEXT(I184,"dd/mm/yyyy")&" | VL : "&TEXT(J184,"dd/mm/yyyy"))) | E184: =IF(L184=0,"Calendrier non disponible pour ce fonds — contacter la société de gestion.",IF(M184="","Calendrier connu jusqu'au "&TEXT(P184,"dd/mm/yyyy")&" — demander le calendrier à jour.","Cut-off : "&TEXT(M184,"dd/mm/yyyy")&" | VL : "&TEXT(N184,"dd/mm/yyyy"))) | F184: =IF(L184=0,"Calendrier non disponible pour ce fonds.",IF(M184="","Calendrier connu jusqu'au "&TEXT(P184,"dd/mm/yyyy")&".",IF(O184="","Non précisé dans le calendrier pour cette échéance.","Réception : "&TEXT(O184,"dd/mm/yyyy")&" (suite au rachat du "&TEXT(N184,"dd/mm/yyyy")&")"))) | G184: =_xlfn.IFS(S184="aucune","Aucune pénalité de sortie."&IF(T184<>""," ("&T184&")",""),S184="manuel","⚠️ À VÉRIFIER MANUELLEMENT : "&T184,S184="inconnue","Pénalité non renseignée — vérifier la notice / DICI du fonds.",$C184="","Saisir une date d'investissement pour statuer sur la pénalité.",Q184="FUTUR","Date d'investissement postérieure à aujourd'hui — vérifier la saisie.",AD184>0,"⚠️ CONCERNÉ : pénalité de "&AD184&"% (détention "&Q184&" mois). "&T184,TRUE,"Non concerné (détention "&Q184&" mois). "&T184) | H184: =COUNTIFS(BDD_Calendrier!$A$2:$A$616,$B184,BDD_Calendrier!$C$2:$C$616,"Souscription") | I184: =IF(H184=0,"",IFERROR(_xlfn.MINIFS(BDD_Calendrier!$D$2:$D$616,BDD_Calendrier!$A$2:$A$616,$B184,BDD_Calendrier!$C$2:$C$616,"Souscription",BDD_Calendrier!$D$2:$D$616,">="&TODAY()),"")) | J184: =IF(I184="","",IFERROR(INDEX(BDD_Calendrier!$E$2:$E$616,MATCH($B184&"|Souscription|"&TEXT(I184,"yyyy-mm-dd"),BDD_Calendrier!$I$2:$I$616,0)),"")) | K184: =IF(H184=0,"",_xlfn.MAXIFS(BDD_Calendrier!$D$2:$D$616,BDD_Calendrier!$A$2:$A$616,$B184,BDD_Calendrier!$C$2:$C$616,"Souscription")) | L184: =COUNTIFS(BDD_Calendrier!$A$2:$A$616,$B184,BDD_Calendrier!$C$2:$C$616,"Rachat") | M184: =IF(L184=0,"",IFERROR(_xlfn.MINIFS(BDD_Calendrier!$D$2:$D$616,BDD_Calendrier!$A$2:$A$616,$B184,BDD_Calendrier!$C$2:$C$616,"Rachat",BDD_Calendrier!$D$2:$D$616,">="&TODAY()),"")) | N184: =IF(M184="","",IFERROR(INDEX(BDD_Calendrier!$E$2:$E$616,MATCH($B184&"|Rachat|"&TEXT(M184,"yyyy-mm-dd"),BDD_Calendrier!$I$2:$I$616,0)),"")) | O184: =IF(M184="","",IFERROR(INDEX(BDD_Calendrier!$H$2:$H$616,MATCH($B184&"|Rachat|"&TEXT(M184,"yyyy-mm-dd"),BDD_Calendrier!$I$2:$I$616,0)),"")) | P184: =IF(L184=0,"",_xlfn.MAXIFS(BDD_Calendrier!$D$2:$D$616,BDD_Calendrier!$A$2:$A$616,$B184,BDD_Calendrier!$C$2:$C$616,"Rachat")) | Q184: =IF($C184="","",IF($C184>TODAY(),"FUTUR",DATEDIF($C184,TODAY(),"m"))) | R184: =COUNTIF(BDD_Penalites!$A$2:$A$130,$B184) | S184: =IF(R184=0,"inconnue",INDEX(BDD_Penalites!$C$2:$C$130,MATCH($B184,BDD_Penalites!$A$2:$A$130,0))) | T184: =IF(R184=0,"",INDEX(BDD_Penalites!$M$2:$M$130,MATCH($B184,BDD_Penalites!$A$2:$A$130,0))) | U184: =IF(R184=0,0,INDEX(BDD_Penalites!$D$2:$D$130,MATCH($B184,BDD_Penalites!$A$2:$A$130,0))) | V184: =IF(R184=0,0,INDEX(BDD_Penalites!$E$2:$E$130,MATCH($B184,BDD_Penalites!$A$2:$A$130,0))) | W184: =IF(R184=0,0,INDEX(BDD_Penalites!$F$2:$F$130,MATCH($B184,BDD_Penalites!$A$2:$A$130,0))) | X184: =IF(R184=0,0,INDEX(BDD_Penalites!$G$2:$G$130,MATCH($B184,BDD_Penalites!$A$2:$A$130,0))) | Y184: =IF(R184=0,0,INDEX(BDD_Penalites!$H$2:$H$130,MATCH($B184,BDD_Penalites!$A$2:$A$130,0))) | Z184: =IF(R184=0,0,INDEX(BDD_Penalites!$I$2:$I$130,MATCH($B184,BDD_Penalites!$A$2:$A$130,0))) | AA184: =IF(R184=0,0,INDEX(BDD_Penalites!$J$2:$J$130,MATCH($B184,BDD_Penalites!$A$2:$A$130,0))) | AB184: =IF(R184=0,0,INDEX(BDD_Penalites!$K$2:$K$130,MATCH($B184,BDD_Penalites!$A$2:$A$130,0))) | AC184: =IF(R184=0,0,INDEX(BDD_Penalites!$L$2:$L$130,MATCH($B184,BDD_Penalites!$A$2:$A$130,0))) | AD184: =IF(OR($C184="",Q184="FUTUR"),"",_xlfn.IFS(Q184<U184,V184,Q184<W184,X184,Q184<Y184,Z184,Q184<AA184,AB184,TRUE,AC184))
A185: GF Infrastructures Durables | B185: FR0013473667 | D185: =IF(H185=0,"Calendrier non disponible pour ce fonds — contacter la société de gestion.",IF(I185="","Calendrier connu jusqu'au "&TEXT(K185,"dd/mm/yyyy")&" — demander le calendrier à jour.","Cut-off : "&TEXT(I185,"dd/mm/yyyy")&" | VL : "&TEXT(J185,"dd/mm/yyyy"))) | E185: =IF(L185=0,"Calendrier non disponible pour ce fonds — contacter la société de gestion.",IF(M185="","Calendrier connu jusqu'au "&TEXT(P185,"dd/mm/yyyy")&" — demander le calendrier à jour.","Cut-off : "&TEXT(M185,"dd/mm/yyyy")&" | VL : "&TEXT(N185,"dd/mm/yyyy"))) | F185: =IF(L185=0,"Calendrier non disponible pour ce fonds.",IF(M185="","Calendrier connu jusqu'au "&TEXT(P185,"dd/mm/yyyy")&".",IF(O185="","Non précisé dans le calendrier pour cette échéance.","Réception : "&TEXT(O185,"dd/mm/yyyy")&" (suite au rachat du "&TEXT(N185,"dd/mm/yyyy")&")"))) | G185: =_xlfn.IFS(S185="aucune","Aucune pénalité de sortie."&IF(T185<>""," ("&T185&")",""),S185="manuel","⚠️ À VÉRIFIER MANUELLEMENT : "&T185,S185="inconnue","Pénalité non renseignée — vérifier la notice / DICI du fonds.",$C185="","Saisir une date d'investissement pour statuer sur la pénalité.",Q185="FUTUR","Date d'investissement postérieure à aujourd'hui — vérifier la saisie.",AD185>0,"⚠️ CONCERNÉ : pénalité de "&AD185&"% (détention "&Q185&" mois). "&T185,TRUE,"Non concerné (détention "&Q185&" mois). "&T185) | H185: =COUNTIFS(BDD_Calendrier!$A$2:$A$616,$B185,BDD_Calendrier!$C$2:$C$616,"Souscription") | I185: =IF(H185=0,"",IFERROR(_xlfn.MINIFS(BDD_Calendrier!$D$2:$D$616,BDD_Calendrier!$A$2:$A$616,$B185,BDD_Calendrier!$C$2:$C$616,"Souscription",BDD_Calendrier!$D$2:$D$616,">="&TODAY()),"")) | J185: =IF(I185="","",IFERROR(INDEX(BDD_Calendrier!$E$2:$E$616,MATCH($B185&"|Souscription|"&TEXT(I185,"yyyy-mm-dd"),BDD_Calendrier!$I$2:$I$616,0)),"")) | K185: =IF(H185=0,"",_xlfn.MAXIFS(BDD_Calendrier!$D$2:$D$616,BDD_Calendrier!$A$2:$A$616,$B185,BDD_Calendrier!$C$2:$C$616,"Souscription")) | L185: =COUNTIFS(BDD_Calendrier!$A$2:$A$616,$B185,BDD_Calendrier!$C$2:$C$616,"Rachat") | M185: =IF(L185=0,"",IFERROR(_xlfn.MINIFS(BDD_Calendrier!$D$2:$D$616,BDD_Calendrier!$A$2:$A$616,$B185,BDD_Calendrier!$C$2:$C$616,"Rachat",BDD_Calendrier!$D$2:$D$616,">="&TODAY()),"")) | N185: =IF(M185="","",IFERROR(INDEX(BDD_Calendrier!$E$2:$E$616,MATCH($B185&"|Rachat|"&TEXT(M185,"yyyy-mm-dd"),BDD_Calendrier!$I$2:$I$616,0)),"")) | O185: =IF(M185="","",IFERROR(INDEX(BDD_Calendrier!$H$2:$H$616,MATCH($B185&"|Rachat|"&TEXT(M185,"yyyy-mm-dd"),BDD_Calendrier!$I$2:$I$616,0)),"")) | P185: =IF(L185=0,"",_xlfn.MAXIFS(BDD_Calendrier!$D$2:$D$616,BDD_Calendrier!$A$2:$A$616,$B185,BDD_Calendrier!$C$2:$C$616,"Rachat")) | Q185: =IF($C185="","",IF($C185>TODAY(),"FUTUR",DATEDIF($C185,TODAY(),"m"))) | R185: =COUNTIF(BDD_Penalites!$A$2:$A$130,$B185) | S185: =IF(R185=0,"inconnue",INDEX(BDD_Penalites!$C$2:$C$130,MATCH($B185,BDD_Penalites!$A$2:$A$130,0))) | T185: =IF(R185=0,"",INDEX(BDD_Penalites!$M$2:$M$130,MATCH($B185,BDD_Penalites!$A$2:$A$130,0))) | U185: =IF(R185=0,0,INDEX(BDD_Penalites!$D$2:$D$130,MATCH($B185,BDD_Penalites!$A$2:$A$130,0))) | V185: =IF(R185=0,0,INDEX(BDD_Penalites!$E$2:$E$130,MATCH($B185,BDD_Penalites!$A$2:$A$130,0))) | W185: =IF(R185=0,0,INDEX(BDD_Penalites!$F$2:$F$130,MATCH($B185,BDD_Penalites!$A$2:$A$130,0))) | X185: =IF(R185=0,0,INDEX(BDD_Penalites!$G$2:$G$130,MATCH($B185,BDD_Penalites!$A$2:$A$130,0))) | Y185: =IF(R185=0,0,INDEX(BDD_Penalites!$H$2:$H$130,MATCH($B185,BDD_Penalites!$A$2:$A$130,0))) | Z185: =IF(R185=0,0,INDEX(BDD_Penalites!$I$2:$I$130,MATCH($B185,BDD_Penalites!$A$2:$A$130,0))) | AA185: =IF(R185=0,0,INDEX(BDD_Penalites!$J$2:$J$130,MATCH($B185,BDD_Penalites!$A$2:$A$130,0))) | AB185: =IF(R185=0,0,INDEX(BDD_Penalites!$K$2:$K$130,MATCH($B185,BDD_Penalites!$A$2:$A$130,0))) | AC185: =IF(R185=0,0,INDEX(BDD_Penalites!$L$2:$L$130,MATCH($B185,BDD_Penalites!$A$2:$A$130,0))) | AD185: =IF(OR($C185="",Q185="FUTUR"),"",_xlfn.IFS(Q185<U185,V185,Q185<W185,X185,Q185<Y185,Z185,Q185<AA185,AB185,TRUE,AC185))
... A187: Rive Tangible Assets Income Fund AS3 | B187: LU2563800726 | D187: =IF(H187=0,"Calendrier non disponible pour ce fonds — contacter la société de gestion.",IF(I187="","Calendrier connu jusqu'au "&TEXT(K187,"dd/mm/yyyy")&" — demander le calendrier à jour.","Cut-off : "&TEXT(I187,"dd/mm/yyyy")&" | VL : "&TEXT(J187,"dd/mm/yyyy"))) | E187: =IF(L187=0,"Calendrier non disponible pour ce fonds — contacter la société de gestion.",IF(M187="","Calendrier connu jusqu'au "&TEXT(P187,"dd/mm/yyyy")&" — demander le calendrier à jour.","Cut-off : "&TEXT(M187,"dd/mm/yyyy")&" | VL : "&TEXT(N187,"dd/mm/yyyy"))) | F187: =IF(L187=0,"Calendrier non disponible pour ce fonds.",IF(M187="","Calendrier connu jusqu'au "&TEXT(P187,"dd/mm/yyyy")&".",IF(O187="","Non précisé dans le calendrier pour cette échéance.","Réception : "&TEXT(O187,"dd/mm/yyyy")&" (suite au rachat du "&TEXT(N187,"dd/mm/yyyy")&")"))) | G187: =_xlfn.IFS(S187="aucune","Aucune pénalité de sortie."&IF(T187<>""," ("&T187&")",""),S187="manuel","⚠️ À VÉRIFIER MANUELLEMENT : "&T187,S187="inconnue","Pénalité non renseignée — vérifier la notice / DICI du fonds.",$C187="","Saisir une date d'investissement pour statuer sur la pénalité.",Q187="FUTUR","Date d'investissement postérieure à aujourd'hui — vérifier la saisie.",AD187>0,"⚠️ CONCERNÉ : pénalité de "&AD187&"% (détention "&Q187&" mois). "&T187,TRUE,"Non concerné (détention "&Q187&" mois). "&T187) | H187: =COUNTIFS(BDD_Calendrier!$A$2:$A$616,$B187,BDD_Calendrier!$C$2:$C$616,"Souscription") | I187: =IF(H187=0,"",IFERROR(_xlfn.MINIFS(BDD_Calendrier!$D$2:$D$616,BDD_Calendrier!$A$2:$A$616,$B187,BDD_Calendrier!$C$2:$C$616,"Souscription",BDD_Calendrier!$D$2:$D$616,">="&TODAY()),"")) | J187: =IF(I187="","",IFERROR(INDEX(BDD_Calendrier!$E$2:$E$616,MATCH($B187&"|Souscription|"&TEXT(I187,"yyyy-mm-dd"),BDD_Calendrier!$I$2:$I$616,0)),"")) | K187: =IF(H187=0,"",_xlfn.MAXIFS(BDD_Calendrier!$D$2:$D$616,BDD_Calendrier!$A$2:$A$616,$B187,BDD_Calendrier!$C$2:$C$616,"Souscription")) | L187: =COUNTIFS(BDD_Calendrier!$A$2:$A$616,$B187,BDD_Calendrier!$C$2:$C$616,"Rachat") | M187: =IF(L187=0,"",IFERROR(_xlfn.MINIFS(BDD_Calendrier!$D$2:$D$616,BDD_Calendrier!$A$2:$A$616,$B187,BDD_Calendrier!$C$2:$C$616,"Rachat",BDD_Calendrier!$D$2:$D$616,">="&TODAY()),"")) | N187: =IF(M187="","",IFERROR(INDEX(BDD_Calendrier!$E$2:$E$616,MATCH($B187&"|Rachat|"&TEXT(M187,"yyyy-mm-dd"),BDD_Calendrier!$I$2:$I$616,0)),"")) | O187: =IF(M187="","",IFERROR(INDEX(BDD_Calendrier!$H$2:$H$616,MATCH($B187&"|Rachat|"&TEXT(M187,"yyyy-mm-dd"),BDD_Calendrier!$I$2:$I$616,0)),"")) | P187: =IF(L187=0,"",_xlfn.MAXIFS(BDD_Calendrier!$D$2:$D$616,BDD_Calendrier!$A$2:$A$616,$B187,BDD_Calendrier!$C$2:$C$616,"Rachat")) | Q187: =IF($C187="","",IF($C187>TODAY(),"FUTUR",DATEDIF($C187,TODAY(),"m"))) | R187: =COUNTIF(BDD_Penalites!$A$2:$A$130,$B187) | S187: =IF(R187=0,"inconnue",INDEX(BDD_Penalites!$C$2:$C$130,MATCH($B187,BDD_Penalites!$A$2:$A$130,0))) | T187: =IF(R187=0,"",INDEX(BDD_Penalites!$M$2:$M$130,MATCH($B187,BDD_Penalites!$A$2:$A$130,0))) | U187: =IF(R187=0,0,INDEX(BDD_Penalites!$D$2:$D$130,MATCH($B187,BDD_Penalites!$A$2:$A$130,0))) | V187: =IF(R187=0,0,INDEX(BDD_Penalites!$E$2:$E$130,MATCH($B187,BDD_Penalites!$A$2:$A$130,0))) | W187: =IF(R187=0,0,INDEX(BDD_Penalites!$F$2:$F$130,MATCH($B187,BDD_Penalites!$A$2:$A$130,0))) | X187: =IF(R187=0,0,INDEX(BDD_Penalites!$G$2:$G$130,MATCH($B187,BDD_Penalites!$A$2:$A$130,0))) | Y187: =IF(R187=0,0,INDEX(BDD_Penalites!$H$2:$H$130,MATCH($B187,BDD_Penalites!$A$2:$A$130,0))) | Z187: =IF(R187=0,0,INDEX(BDD_Penalites!$I$2:$I$130,MATCH($B187,BDD_Penalites!$A$2:$A$130,0))) | AA187: =IF(R187=0,0,INDEX(BDD_Penalites!$J$2:$J$130,MATCH($B187,BDD_Penalites!$A$2:$A$130,0))) | AB187: =IF(R187=0,0,INDEX(BDD_Penalites!$K$2:$K$130,MATCH($B187,BDD_Penalites!$A$2:$A$130,0))) | AC187: =IF(R187=0,0,INDEX(BDD_Penalites!$L$2:$L$130,MATCH($B187,BDD_Penalites!$A$2:$A$130,0))) | AD187: =IF(OR($C187="",Q187="FUTUR"),"",_xlfn.IFS(Q187<U187,V187,Q187<W187,X187,Q187<Y187,Z187,Q187<AA187,AB187,TRUE,AC187))
A194: Dette privée
A195: Althos Private Credit part F - Capitalisante | B195: FR001400XGV4 | D195: =IF(H195=0,"Calendrier non disponible pour ce fonds — contacter la société de gestion.",IF(I195="","Calendrier connu jusqu'au "&TEXT(K195,"dd/mm/yyyy")&" — demander le calendrier à jour.","Cut-off : "&TEXT(I195,"dd/mm/yyyy")&" | VL : "&TEXT(J195,"dd/mm/yyyy"))) | E195: =IF(L195=0,"Calendrier non disponible pour ce fonds — contacter la société de gestion.",IF(M195="","Calendrier connu jusqu'au "&TEXT(P195,"dd/mm/yyyy")&" — demander le calendrier à jour.","Cut-off : "&TEXT(M195,"dd/mm/yyyy")&" | VL : "&TEXT(N195,"dd/mm/yyyy"))) | F195: =IF(L195=0,"Calendrier non disponible pour ce fonds.",IF(M195="","Calendrier connu jusqu'au "&TEXT(P195,"dd/mm/yyyy")&".",IF(O195="","Non précisé dans le calendrier pour cette échéance.","Réception : "&TEXT(O195,"dd/mm/yyyy")&" (suite au rachat du "&TEXT(N195,"dd/mm/yyyy")&")"))) | G195: =_xlfn.IFS(S195="aucune","Aucune pénalité de sortie."&IF(T195<>""," ("&T195&")",""),S195="manuel","⚠️ À VÉRIFIER MANUELLEMENT : "&T195,S195="inconnue","Pénalité non renseignée — vérifier la notice / DICI du fonds.",$C195="","Saisir une date d'investissement pour statuer sur la pénalité.",Q195="FUTUR","Date d'investissement postérieure à aujourd'hui — vérifier la saisie.",AD195>0,"⚠️ CONCERNÉ : pénalité de "&AD195&"% (détention "&Q195&" mois). "&T195,TRUE,"Non concerné (détention "&Q195&" mois). "&T195) | H195: =COUNTIFS(BDD_Calendrier!$A$2:$A$616,$B195,BDD_Calendrier!$C$2:$C$616,"Souscription") | I195: =IF(H195=0,"",IFERROR(_xlfn.MINIFS(BDD_Calendrier!$D$2:$D$616,BDD_Calendrier!$A$2:$A$616,$B195,BDD_Calendrier!$C$2:$C$616,"Souscription",BDD_Calendrier!$D$2:$D$616,">="&TODAY()),"")) | J195: =IF(I195="","",IFERROR(INDEX(BDD_Calendrier!$E$2:$E$616,MATCH($B195&"|Souscription|"&TEXT(I195,"yyyy-mm-dd"),BDD_Calendrier!$I$2:$I$616,0)),"")) | K195: =IF(H195=0,"",_xlfn.MAXIFS(BDD_Calendrier!$D$2:$D$616,BDD_Calendrier!$A$2:$A$616,$B195,BDD_Calendrier!$C$2:$C$616,"Souscription")) | L195: =COUNTIFS(BDD_Calendrier!$A$2:$A$616,$B195,BDD_Calendrier!$C$2:$C$616,"Rachat") | M195: =IF(L195=0,"",IFERROR(_xlfn.MINIFS(BDD_Calendrier!$D$2:$D$616,BDD_Calendrier!$A$2:$A$616,$B195,BDD_Calendrier!$C$2:$C$616,"Rachat",BDD_Calendrier!$D$2:$D$616,">="&TODAY()),"")) | N195: =IF(M195="","",IFERROR(INDEX(BDD_Calendrier!$E$2:$E$616,MATCH($B195&"|Rachat|"&TEXT(M195,"yyyy-mm-dd"),BDD_Calendrier!$I$2:$I$616,0)),"")) | O195: =IF(M195="","",IFERROR(INDEX(BDD_Calendrier!$H$2:$H$616,MATCH($B195&"|Rachat|"&TEXT(M195,"yyyy-mm-dd"),BDD_Calendrier!$I$2:$I$616,0)),"")) | P195: =IF(L195=0,"",_xlfn.MAXIFS(BDD_Calendrier!$D$2:$D$616,BDD_Calendrier!$A$2:$A$616,$B195,BDD_Calendrier!$C$2:$C$616,"Rachat")) | Q195: =IF($C195="","",IF($C195>TODAY(),"FUTUR",DATEDIF($C195,TODAY(),"m"))) | R195: =COUNTIF(BDD_Penalites!$A$2:$A$130,$B195) | S195: =IF(R195=0,"inconnue",INDEX(BDD_Penalites!$C$2:$C$130,MATCH($B195,BDD_Penalites!$A$2:$A$130,0))) | T195: =IF(R195=0,"",INDEX(BDD_Penalites!$M$2:$M$130,MATCH($B195,BDD_Penalites!$A$2:$A$130,0))) | U195: =IF(R195=0,0,INDEX(BDD_Penalites!$D$2:$D$130,MATCH($B195,BDD_Penalites!$A$2:$A$130,0))) | V195: =IF(R195=0,0,INDEX(BDD_Penalites!$E$2:$E$130,MATCH($B195,BDD_Penalites!$A$2:$A$130,0))) | W195: =IF(R195=0,0,INDEX(BDD_Penalites!$F$2:$F$130,MATCH($B195,BDD_Penalites!$A$2:$A$130,0))) | X195: =IF(R195=0,0,INDEX(BDD_Penalites!$G$2:$G$130,MATCH($B195,BDD_Penalites!$A$2:$A$130,0))) | Y195: =IF(R195=0,0,INDEX(BDD_Penalites!$H$2:$H$130,MATCH($B195,BDD_Penalites!$A$2:$A$130,0))) | Z195: =IF(R195=0,0,INDEX(BDD_Penalites!$I$2:$I$130,MATCH($B195,BDD_Penalites!$A$2:$A$130,0))) | AA195: =IF(R195=0,0,INDEX(BDD_Penalites!$J$2:$J$130,MATCH($B195,BDD_Penalites!$A$2:$A$130,0))) | AB195: =IF(R195=0,0,INDEX(BDD_Penalites!$K$2:$K$130,MATCH($B195,BDD_Penalites!$A$2:$A$130,0))) | AC195: =IF(R195=0,0,INDEX(BDD_Penalites!$L$2:$L$130,MATCH($B195,BDD_Penalites!$A$2:$A$130,0))) | AD195: =IF(OR($C195="",Q195="FUTUR"),"",_xlfn.IFS(Q195<U195,V195,Q195<W195,X195,Q195<Y195,Z195,Q195<AA195,AB195,TRUE,AC195))
A196: Althos Private Credit part F - Distribuant | B196: FR001400XGQ4 | D196: =IF(H196=0,"Calendrier non disponible pour ce fonds — contacter la société de gestion.",IF(I196="","Calendrier connu jusqu'au "&TEXT(K196,"dd/mm/yyyy")&" — demander le calendrier à jour.","Cut-off : "&TEXT(I196,"dd/mm/yyyy")&" | VL : "&TEXT(J196,"dd/mm/yyyy"))) | E196: =IF(L196=0,"Calendrier non disponible pour ce fonds — contacter la société de gestion.",IF(M196="","Calendrier connu jusqu'au "&TEXT(P196,"dd/mm/yyyy")&" — demander le calendrier à jour.","Cut-off : "&TEXT(M196,"dd/mm/yyyy")&" | VL : "&TEXT(N196,"dd/mm/yyyy"))) | F196: =IF(L196=0,"Calendrier non disponible pour ce fonds.",IF(M196="","Calendrier connu jusqu'au "&TEXT(P196,"dd/mm/yyyy")&".",IF(O196="","Non précisé dans le calendrier pour cette échéance.","Réception : "&TEXT(O196,"dd/mm/yyyy")&" (suite au rachat du "&TEXT(N196,"dd/mm/yyyy")&")"))) | G196: =_xlfn.IFS(S196="aucune","Aucune pénalité de sortie."&IF(T196<>""," ("&T196&")",""),S196="manuel","⚠️ À VÉRIFIER MANUELLEMENT : "&T196,S196="inconnue","Pénalité non renseignée — vérifier la notice / DICI du fonds.",$C196="","Saisir une date d'investissement pour statuer sur la pénalité.",Q196="FUTUR","Date d'investissement postérieure à aujourd'hui — vérifier la saisie.",AD196>0,"⚠️ CONCERNÉ : pénalité de "&AD196&"% (détention "&Q196&" mois). "&T196,TRUE,"Non concerné (détention "&Q196&" mois). "&T196) | H196: =COUNTIFS(BDD_Calendrier!$A$2:$A$616,$B196,BDD_Calendrier!$C$2:$C$616,"Souscription") | I196: =IF(H196=0,"",IFERROR(_xlfn.MINIFS(BDD_Calendrier!$D$2:$D$616,BDD_Calendrier!$A$2:$A$616,$B196,BDD_Calendrier!$C$2:$C$616,"Souscription",BDD_Calendrier!$D$2:$D$616,">="&TODAY()),"")) | J196: =IF(I196="","",IFERROR(INDEX(BDD_Calendrier!$E$2:$E$616,MATCH($B196&"|Souscription|"&TEXT(I196,"yyyy-mm-dd"),BDD_Calendrier!$I$2:$I$616,0)),"")) | K196: =IF(H196=0,"",_xlfn.MAXIFS(BDD_Calendrier!$D$2:$D$616,BDD_Calendrier!$A$2:$A$616,$B196,BDD_Calendrier!$C$2:$C$616,"Souscription")) | L196: =COUNTIFS(BDD_Calendrier!$A$2:$A$616,$B196,BDD_Calendrier!$C$2:$C$616,"Rachat") | M196: =IF(L196=0,"",IFERROR(_xlfn.MINIFS(BDD_Calendrier!$D$2:$D$616,BDD_Calendrier!$A$2:$A$616,$B196,BDD_Calendrier!$C$2:$C$616,"Rachat",BDD_Calendrier!$D$2:$D$616,">="&TODAY()),"")) | N196: =IF(M196="","",IFERROR(INDEX(BDD_Calendrier!$E$2:$E$616,MATCH($B196&"|Rachat|"&TEXT(M196,"yyyy-mm-dd"),BDD_Calendrier!$I$2:$I$616,0)),"")) | O196: =IF(M196="","",IFERROR(INDEX(BDD_Calendrier!$H$2:$H$616,MATCH($B196&"|Rachat|"&TEXT(M196,"yyyy-mm-dd"),BDD_Calendrier!$I$2:$I$616,0)),"")) | P196: =IF(L196=0,"",_xlfn.MAXIFS(BDD_Calendrier!$D$2:$D$616,BDD_Calendrier!$A$2:$A$616,$B196,BDD_Calendrier!$C$2:$C$616,"Rachat")) | Q196: =IF($C196="","",IF($C196>TODAY(),"FUTUR",DATEDIF($C196,TODAY(),"m"))) | R196: =COUNTIF(BDD_Penalites!$A$2:$A$130,$B196) | S196: =IF(R196=0,"inconnue",INDEX(BDD_Penalites!$C$2:$C$130,MATCH($B196,BDD_Penalites!$A$2:$A$130,0))) | T196: =IF(R196=0,"",INDEX(BDD_Penalites!$M$2:$M$130,MATCH($B196,BDD_Penalites!$A$2:$A$130,0))) | U196: =IF(R196=0,0,INDEX(BDD_Penalites!$D$2:$D$130,MATCH($B196,BDD_Penalites!$A$2:$A$130,0))) | V196: =IF(R196=0,0,INDEX(BDD_Penalites!$E$2:$E$130,MATCH($B196,BDD_Penalites!$A$2:$A$130,0))) | W196: =IF(R196=0,0,INDEX(BDD_Penalites!$F$2:$F$130,MATCH($B196,BDD_Penalites!$A$2:$A$130,0))) | X196: =IF(R196=0,0,INDEX(BDD_Penalites!$G$2:$G$130,MATCH($B196,BDD_Penalites!$A$2:$A$130,0))) | Y196: =IF(R196=0,0,INDEX(BDD_Penalites!$H$2:$H$130,MATCH($B196,BDD_Penalites!$A$2:$A$130,0))) | Z196: =IF(R196=0,0,INDEX(BDD_Penalites!$I$2:$I$130,MATCH($B196,BDD_Penalites!$A$2:$A$130,0))) | AA196: =IF(R196=0,0,INDEX(BDD_Penalites!$J$2:$J$130,MATCH($B196,BDD_Penalites!$A$2:$A$130,0))) | AB196: =IF(R196=0,0,INDEX(BDD_Penalites!$K$2:$K$130,MATCH($B196,BDD_Penalites!$A$2:$A$130,0))) | AC196: =IF(R196=0,0,INDEX(BDD_Penalites!$L$2:$L$130,MATCH($B196,BDD_Penalites!$A$2:$A$130,0))) | AD196: =IF(OR($C196="",Q196="FUTUR"),"",_xlfn.IFS(Q196<U196,V196,Q196<W196,X196,Q196<Y196,Z196,Q196<AA196,AB196,TRUE,AC196))
A197: Althos Private Credit part A - Capitalisante | B197: FR001400XGO9 | D197: =IF(H197=0,"Calendrier non disponible pour ce fonds — contacter la société de gestion.",IF(I197="","Calendrier connu jusqu'au "&TEXT(K197,"dd/mm/yyyy")&" — demander le calendrier à jour.","Cut-off : "&TEXT(I197,"dd/mm/yyyy")&" | VL : "&TEXT(J197,"dd/mm/yyyy"))) | E197: =IF(L197=0,"Calendrier non disponible pour ce fonds — contacter la société de gestion.",IF(M197="","Calendrier connu jusqu'au "&TEXT(P197,"dd/mm/yyyy")&" — demander le calendrier à jour.","Cut-off : "&TEXT(M197,"dd/mm/yyyy")&" | VL : "&TEXT(N197,"dd/mm/yyyy"))) | F197: =IF(L197=0,"Calendrier non disponible pour ce fonds.",IF(M197="","Calendrier connu jusqu'au "&TEXT(P197,"dd/mm/yyyy")&".",IF(O197="","Non précisé dans le calendrier pour cette échéance.","Réception : "&TEXT(O197,"dd/mm/yyyy")&" (suite au rachat du "&TEXT(N197,"dd/mm/yyyy")&")"))) | G197: =_xlfn.IFS(S197="aucune","Aucune pénalité de sortie."&IF(T197<>""," ("&T197&")",""),S197="manuel","⚠️ À VÉRIFIER MANUELLEMENT : "&T197,S197="inconnue","Pénalité non renseignée — vérifier la notice / DICI du fonds.",$C197="","Saisir une date d'investissement pour statuer sur la pénalité.",Q197="FUTUR","Date d'investissement postérieure à aujourd'hui — vérifier la saisie.",AD197>0,"⚠️ CONCERNÉ : pénalité de "&AD197&"% (détention "&Q197&" mois). "&T197,TRUE,"Non concerné (détention "&Q197&" mois). "&T197) | H197: =COUNTIFS(BDD_Calendrier!$A$2:$A$616,$B197,BDD_Calendrier!$C$2:$C$616,"Souscription") | I197: =IF(H197=0,"",IFERROR(_xlfn.MINIFS(BDD_Calendrier!$D$2:$D$616,BDD_Calendrier!$A$2:$A$616,$B197,BDD_Calendrier!$C$2:$C$616,"Souscription",BDD_Calendrier!$D$2:$D$616,">="&TODAY()),"")) | J197: =IF(I197="","",IFERROR(INDEX(BDD_Calendrier!$E$2:$E$616,MATCH($B197&"|Souscription|"&TEXT(I197,"yyyy-mm-dd"),BDD_Calendrier!$I$2:$I$616,0)),"")) | K197: =IF(H197=0,"",_xlfn.MAXIFS(BDD_Calendrier!$D$2:$D$616,BDD_Calendrier!$A$2:$A$616,$B197,BDD_Calendrier!$C$2:$C$616,"Souscription")) | L197: =COUNTIFS(BDD_Calendrier!$A$2:$A$616,$B197,BDD_Calendrier!$C$2:$C$616,"Rachat") | M197: =IF(L197=0,"",IFERROR(_xlfn.MINIFS(BDD_Calendrier!$D$2:$D$616,BDD_Calendrier!$A$2:$A$616,$B197,BDD_Calendrier!$C$2:$C$616,"Rachat",BDD_Calendrier!$D$2:$D$616,">="&TODAY()),"")) | N197: =IF(M197="","",IFERROR(INDEX(BDD_Calendrier!$E$2:$E$616,MATCH($B197&"|Rachat|"&TEXT(M197,"yyyy-mm-dd"),BDD_Calendrier!$I$2:$I$616,0)),"")) | O197: =IF(M197="","",IFERROR(INDEX(BDD_Calendrier!$H$2:$H$616,MATCH($B197&"|Rachat|"&TEXT(M197,"yyyy-mm-dd"),BDD_Calendrier!$I$2:$I$616,0)),"")) | P197: =IF(L197=0,"",_xlfn.MAXIFS(BDD_Calendrier!$D$2:$D$616,BDD_Calendrier!$A$2:$A$616,$B197,BDD_Calendrier!$C$2:$C$616,"Rachat")) | Q197: =IF($C197="","",IF($C197>TODAY(),"FUTUR",DATEDIF($C197,TODAY(),"m"))) | R197: =COUNTIF(BDD_Penalites!$A$2:$A$130,$B197) | S197: =IF(R197=0,"inconnue",INDEX(BDD_Penalites!$C$2:$C$130,MATCH($B197,BDD_Penalites!$A$2:$A$130,0))) | T197: =IF(R197=0,"",INDEX(BDD_Penalites!$M$2:$M$130,MATCH($B197,BDD_Penalites!$A$2:$A$130,0))) | U197: =IF(R197=0,0,INDEX(BDD_Penalites!$D$2:$D$130,MATCH($B197,BDD_Penalites!$A$2:$A$130,0))) | V197: =IF(R197=0,0,INDEX(BDD_Penalites!$E$2:$E$130,MATCH($B197,BDD_Penalites!$A$2:$A$130,0))) | W197: =IF(R197=0,0,INDEX(BDD_Penalites!$F$2:$F$130,MATCH($B197,BDD_Penalites!$A$2:$A$130,0))) | X197: =IF(R197=0,0,INDEX(BDD_Penalites!$G$2:$G$130,MATCH($B197,BDD_Penalites!$A$2:$A$130,0))) | Y197: =IF(R197=0,0,INDEX(BDD_Penalites!$H$2:$H$130,MATCH($B197,BDD_Penalites!$A$2:$A$130,0))) | Z197: =IF(R197=0,0,INDEX(BDD_Penalites!$I$2:$I$130,MATCH($B197,BDD_Penalites!$A$2:$A$130,0))) | AA197: =IF(R197=0,0,INDEX(BDD_Penalites!$J$2:$J$130,MATCH($B197,BDD_Penalites!$A$2:$A$130,0))) | AB197: =IF(R197=0,0,INDEX(BDD_Penalites!$K$2:$K$130,MATCH($B197,BDD_Penalites!$A$2:$A$130,0))) | AC197: =IF(R197=0,0,INDEX(BDD_Penalites!$L$2:$L$130,MATCH($B197,BDD_Penalites!$A$2:$A$130,0))) | AD197: =IF(OR($C197="",Q197="FUTUR"),"",_xlfn.IFS(Q197<U197,V197,Q197<W197,X197,Q197<Y197,Z197,Q197<AA197,AB197,TRUE,AC197))
A198: Althos Private Credit part A - Distribuant | B198: FR001400XGM3 | D198: =IF(H198=0,"Calendrier non disponible pour ce fonds — contacter la société de gestion.",IF(I198="","Calendrier connu jusqu'au "&TEXT(K198,"dd/mm/yyyy")&" — demander le calendrier à jour.","Cut-off : "&TEXT(I198,"dd/mm/yyyy")&" | VL : "&TEXT(J198,"dd/mm/yyyy"))) | E198: =IF(L198=0,"Calendrier non disponible pour ce fonds — contacter la société de gestion.",IF(M198="","Calendrier connu jusqu'au "&TEXT(P198,"dd/mm/yyyy")&" — demander le calendrier à jour.","Cut-off : "&TEXT(M198,"dd/mm/yyyy")&" | VL : "&TEXT(N198,"dd/mm/yyyy"))) | F198: =IF(L198=0,"Calendrier non disponible pour ce fonds.",IF(M198="","Calendrier connu jusqu'au "&TEXT(P198,"dd/mm/yyyy")&".",IF(O198="","Non précisé dans le calendrier pour cette échéance.","Réception : "&TEXT(O198,"dd/mm/yyyy")&" (suite au rachat du "&TEXT(N198,"dd/mm/yyyy")&")"))) | G198: =_xlfn.IFS(S198="aucune","Aucune pénalité de sortie."&IF(T198<>""," ("&T198&")",""),S198="manuel","⚠️ À VÉRIFIER MANUELLEMENT : "&T198,S198="inconnue","Pénalité non renseignée — vérifier la notice / DICI du fonds.",$C198="","Saisir une date d'investissement pour statuer sur la pénalité.",Q198="FUTUR","Date d'investissement postérieure à aujourd'hui — vérifier la saisie.",AD198>0,"⚠️ CONCERNÉ : pénalité de "&AD198&"% (détention "&Q198&" mois). "&T198,TRUE,"Non concerné (détention "&Q198&" mois). "&T198) | H198: =COUNTIFS(BDD_Calendrier!$A$2:$A$616,$B198,BDD_Calendrier!$C$2:$C$616,"Souscription") | I198: =IF(H198=0,"",IFERROR(_xlfn.MINIFS(BDD_Calendrier!$D$2:$D$616,BDD_Calendrier!$A$2:$A$616,$B198,BDD_Calendrier!$C$2:$C$616,"Souscription",BDD_Calendrier!$D$2:$D$616,">="&TODAY()),"")) | J198: =IF(I198="","",IFERROR(INDEX(BDD_Calendrier!$E$2:$E$616,MATCH($B198&"|Souscription|"&TEXT(I198,"yyyy-mm-dd"),BDD_Calendrier!$I$2:$I$616,0)),"")) | K198: =IF(H198=0,"",_xlfn.MAXIFS(BDD_Calendrier!$D$2:$D$616,BDD_Calendrier!$A$2:$A$616,$B198,BDD_Calendrier!$C$2:$C$616,"Souscription")) | L198: =COUNTIFS(BDD_Calendrier!$A$2:$A$616,$B198,BDD_Calendrier!$C$2:$C$616,"Rachat") | M198: =IF(L198=0,"",IFERROR(_xlfn.MINIFS(BDD_Calendrier!$D$2:$D$616,BDD_Calendrier!$A$2:$A$616,$B198,BDD_Calendrier!$C$2:$C$616,"Rachat",BDD_Calendrier!$D$2:$D$616,">="&TODAY()),"")) | N198: =IF(M198="","",IFERROR(INDEX(BDD_Calendrier!$E$2:$E$616,MATCH($B198&"|Rachat|"&TEXT(M198,"yyyy-mm-dd"),BDD_Calendrier!$I$2:$I$616,0)),"")) | O198: =IF(M198="","",IFERROR(INDEX(BDD_Calendrier!$H$2:$H$616,MATCH($B198&"|Rachat|"&TEXT(M198,"yyyy-mm-dd"),BDD_Calendrier!$I$2:$I$616,0)),"")) | P198: =IF(L198=0,"",_xlfn.MAXIFS(BDD_Calendrier!$D$2:$D$616,BDD_Calendrier!$A$2:$A$616,$B198,BDD_Calendrier!$C$2:$C$616,"Rachat")) | Q198: =IF($C198="","",IF($C198>TODAY(),"FUTUR",DATEDIF($C198,TODAY(),"m"))) | R198: =COUNTIF(BDD_Penalites!$A$2:$A$130,$B198) | S198: =IF(R198=0,"inconnue",INDEX(BDD_Penalites!$C$2:$C$130,MATCH($B198,BDD_Penalites!$A$2:$A$130,0))) | T198: =IF(R198=0,"",INDEX(BDD_Penalites!$M$2:$M$130,MATCH($B198,BDD_Penalites!$A$2:$A$130,0))) | U198: =IF(R198=0,0,INDEX(BDD_Penalites!$D$2:$D$130,MATCH($B198,BDD_Penalites!$A$2:$A$130,0))) | V198: =IF(R198=0,0,INDEX(BDD_Penalites!$E$2:$E$130,MATCH($B198,BDD_Penalites!$A$2:$A$130,0))) | W198: =IF(R198=0,0,INDEX(BDD_Penalites!$F$2:$F$130,MATCH($B198,BDD_Penalites!$A$2:$A$130,0))) | X198: =IF(R198=0,0,INDEX(BDD_Penalites!$G$2:$G$130,MATCH($B198,BDD_Penalites!$A$2:$A$130,0))) | Y198: =IF(R198=0,0,INDEX(BDD_Penalites!$H$2:$H$130,MATCH($B198,BDD_Penalites!$A$2:$A$130,0))) | Z198: =IF(R198=0,0,INDEX(BDD_Penalites!$I$2:$I$130,MATCH($B198,BDD_Penalites!$A$2:$A$130,0))) | AA198: =IF(R198=0,0,INDEX(BDD_Penalites!$J$2:$J$130,MATCH($B198,BDD_Penalites!$A$2:$A$130,0))) | AB198: =IF(R198=0,0,INDEX(BDD_Penalites!$K$2:$K$130,MATCH($B198,BDD_Penalites!$A$2:$A$130,0))) | AC198: =IF(R198=0,0,INDEX(BDD_Penalites!$L$2:$L$130,MATCH($B198,BDD_Penalites!$A$2:$A$130,0))) | AD198: =IF(OR($C198="",Q198="FUTUR"),"",_xlfn.IFS(Q198<U198,V198,Q198<W198,X198,Q198<Y198,Z198,Q198<AA198,AB198,TRUE,AC198))
A199: Morgan Stanley EPIF | B199: LU2860459879 | D199: =IF(H199=0,"Calendrier non disponible pour ce fonds — contacter la société de gestion.",IF(I199="","Calendrier connu jusqu'au "&TEXT(K199,"dd/mm/yyyy")&" — demander le calendrier à jour.","Cut-off : "&TEXT(I199,"dd/mm/yyyy")&" | VL : "&TEXT(J199,"dd/mm/yyyy"))) | E199: =IF(L199=0,"Calendrier non disponible pour ce fonds — contacter la société de gestion.",IF(M199="","Calendrier connu jusqu'au "&TEXT(P199,"dd/mm/yyyy")&" — demander le calendrier à jour.","Cut-off : "&TEXT(M199,"dd/mm/yyyy")&" | VL : "&TEXT(N199,"dd/mm/yyyy"))) | F199: =IF(L199=0,"Calendrier non disponible pour ce fonds.",IF(M199="","Calendrier connu jusqu'au "&TEXT(P199,"dd/mm/yyyy")&".",IF(O199="","Non précisé dans le calendrier pour cette échéance.","Réception : "&TEXT(O199,"dd/mm/yyyy")&" (suite au rachat du "&TEXT(N199,"dd/mm/yyyy")&")"))) | G199: =_xlfn.IFS(S199="aucune","Aucune pénalité de sortie."&IF(T199<>""," ("&T199&")",""),S199="manuel","⚠️ À VÉRIFIER MANUELLEMENT : "&T199,S199="inconnue","Pénalité non renseignée — vérifier la notice / DICI du fonds.",$C199="","Saisir une date d'investissement pour statuer sur la pénalité.",Q199="FUTUR","Date d'investissement postérieure à aujourd'hui — vérifier la saisie.",AD199>0,"⚠️ CONCERNÉ : pénalité de "&AD199&"% (détention "&Q199&" mois). "&T199,TRUE,"Non concerné (détention "&Q199&" mois). "&T199) | H199: =COUNTIFS(BDD_Calendrier!$A$2:$A$616,$B199,BDD_Calendrier!$C$2:$C$616,"Souscription") | I199: =IF(H199=0,"",IFERROR(_xlfn.MINIFS(BDD_Calendrier!$D$2:$D$616,BDD_Calendrier!$A$2:$A$616,$B199,BDD_Calendrier!$C$2:$C$616,"Souscription",BDD_Calendrier!$D$2:$D$616,">="&TODAY()),"")) | J199: =IF(I199="","",IFERROR(INDEX(BDD_Calendrier!$E$2:$E$616,MATCH($B199&"|Souscription|"&TEXT(I199,"yyyy-mm-dd"),BDD_Calendrier!$I$2:$I$616,0)),"")) | K199: =IF(H199=0,"",_xlfn.MAXIFS(BDD_Calendrier!$D$2:$D$616,BDD_Calendrier!$A$2:$A$616,$B199,BDD_Calendrier!$C$2:$C$616,"Souscription")) | L199: =COUNTIFS(BDD_Calendrier!$A$2:$A$616,$B199,BDD_Calendrier!$C$2:$C$616,"Rachat") | M199: =IF(L199=0,"",IFERROR(_xlfn.MINIFS(BDD_Calendrier!$D$2:$D$616,BDD_Calendrier!$A$2:$A$616,$B199,BDD_Calendrier!$C$2:$C$616,"Rachat",BDD_Calendrier!$D$2:$D$616,">="&TODAY()),"")) | N199: =IF(M199="","",IFERROR(INDEX(BDD_Calendrier!$E$2:$E$616,MATCH($B199&"|Rachat|"&TEXT(M199,"yyyy-mm-dd"),BDD_Calendrier!$I$2:$I$616,0)),"")) | O199: =IF(M199="","",IFERROR(INDEX(BDD_Calendrier!$H$2:$H$616,MATCH($B199&"|Rachat|"&TEXT(M199,"yyyy-mm-dd"),BDD_Calendrier!$I$2:$I$616,0)),"")) | P199: =IF(L199=0,"",_xlfn.MAXIFS(BDD_Calendrier!$D$2:$D$616,BDD_Calendrier!$A$2:$A$616,$B199,BDD_Calendrier!$C$2:$C$616,"Rachat")) | Q199: =IF($C199="","",IF($C199>TODAY(),"FUTUR",DATEDIF($C199,TODAY(),"m"))) | R199: =COUNTIF(BDD_Penalites!$A$2:$A$130,$B199) | S199: =IF(R199=0,"inconnue",INDEX(BDD_Penalites!$C$2:$C$130,MATCH($B199,BDD_Penalites!$A$2:$A$130,0))) | T199: =IF(R199=0,"",INDEX(BDD_Penalites!$M$2:$M$130,MATCH($B199,BDD_Penalites!$A$2:$A$130,0))) | U199: =IF(R199=0,0,INDEX(BDD_Penalites!$D$2:$D$130,MATCH($B199,BDD_Penalites!$A$2:$A$130,0))) | V199: =IF(R199=0,0,INDEX(BDD_Penalites!$E$2:$E$130,MATCH($B199,BDD_Penalites!$A$2:$A$130,0))) | W199: =IF(R199=0,0,INDEX(BDD_Penalites!$F$2:$F$130,MATCH($B199,BDD_Penalites!$A$2:$A$130,0))) | X199: =IF(R199=0,0,INDEX(BDD_Penalites!$G$2:$G$130,MATCH($B199,BDD_Penalites!$A$2:$A$130,0))) | Y199: =IF(R199=0,0,INDEX(BDD_Penalites!$H$2:$H$130,MATCH($B199,BDD_Penalites!$A$2:$A$130,0))) | Z199: =IF(R199=0,0,INDEX(BDD_Penalites!$I$2:$I$130,MATCH($B199,BDD_Penalites!$A$2:$A$130,0))) | AA199: =IF(R199=0,0,INDEX(BDD_Penalites!$J$2:$J$130,MATCH($B199,BDD_Penalites!$A$2:$A$130,0))) | AB199: =IF(R199=0,0,INDEX(BDD_Penalites!$K$2:$K$130,MATCH($B199,BDD_Penalites!$A$2:$A$130,0))) | AC199: =IF(R199=0,0,INDEX(BDD_Penalites!$L$2:$L$130,MATCH($B199,BDD_Penalites!$A$2:$A$130,0))) | AD199: =IF(OR($C199="",Q199="FUTUR"),"",_xlfn.IFS(Q199<U199,V199,Q199<W199,X199,Q199<Y199,Z199,Q199<AA199,AB199,TRUE,AC199))
A200: Pantheon GCS S Acc | B200: LU3047997575 | D200: =IF(H200=0,"Calendrier non disponible pour ce fonds — contacter la société de gestion.",IF(I200="","Calendrier connu jusqu'au "&TEXT(K200,"dd/mm/yyyy")&" — demander le calendrier à jour.","Cut-off : "&TEXT(I200,"dd/mm/yyyy")&" | VL : "&TEXT(J200,"dd/mm/yyyy"))) | E200: =IF(L200=0,"Calendrier non disponible pour ce fonds — contacter la société de gestion.",IF(M200="","Calendrier connu jusqu'au "&TEXT(P200,"dd/mm/yyyy")&" — demander le calendrier à jour.","Cut-off : "&TEXT(M200,"dd/mm/yyyy")&" | VL : "&TEXT(N200,"dd/mm/yyyy"))) | F200: =IF(L200=0,"Calendrier non disponible pour ce fonds.",IF(M200="","Calendrier connu jusqu'au "&TEXT(P200,"dd/mm/yyyy")&".",IF(O200="","Non précisé dans le calendrier pour cette échéance.","Réception : "&TEXT(O200,"dd/mm/yyyy")&" (suite au rachat du "&TEXT(N200,"dd/mm/yyyy")&")"))) | G200: =_xlfn.IFS(S200="aucune","Aucune pénalité de sortie."&IF(T200<>""," ("&T200&")",""),S200="manuel","⚠️ À VÉRIFIER MANUELLEMENT : "&T200,S200="inconnue","Pénalité non renseignée — vérifier la notice / DICI du fonds.",$C200="","Saisir une date d'investissement pour statuer sur la pénalité.",Q200="FUTUR","Date d'investissement postérieure à aujourd'hui — vérifier la saisie.",AD200>0,"⚠️ CONCERNÉ : pénalité de "&AD200&"% (détention "&Q200&" mois). "&T200,TRUE,"Non concerné (détention "&Q200&" mois). "&T200) | H200: =COUNTIFS(BDD_Calendrier!$A$2:$A$616,$B200,BDD_Calendrier!$C$2:$C$616,"Souscription") | I200: =IF(H200=0,"",IFERROR(_xlfn.MINIFS(BDD_Calendrier!$D$2:$D$616,BDD_Calendrier!$A$2:$A$616,$B200,BDD_Calendrier!$C$2:$C$616,"Souscription",BDD_Calendrier!$D$2:$D$616,">="&TODAY()),"")) | J200: =IF(I200="","",IFERROR(INDEX(BDD_Calendrier!$E$2:$E$616,MATCH($B200&"|Souscription|"&TEXT(I200,"yyyy-mm-dd"),BDD_Calendrier!$I$2:$I$616,0)),"")) | K200: =IF(H200=0,"",_xlfn.MAXIFS(BDD_Calendrier!$D$2:$D$616,BDD_Calendrier!$A$2:$A$616,$B200,BDD_Calendrier!$C$2:$C$616,"Souscription")) | L200: =COUNTIFS(BDD_Calendrier!$A$2:$A$616,$B200,BDD_Calendrier!$C$2:$C$616,"Rachat") | M200: =IF(L200=0,"",IFERROR(_xlfn.MINIFS(BDD_Calendrier!$D$2:$D$616,BDD_Calendrier!$A$2:$A$616,$B200,BDD_Calendrier!$C$2:$C$616,"Rachat",BDD_Calendrier!$D$2:$D$616,">="&TODAY()),"")) | N200: =IF(M200="","",IFERROR(INDEX(BDD_Calendrier!$E$2:$E$616,MATCH($B200&"|Rachat|"&TEXT(M200,"yyyy-mm-dd"),BDD_Calendrier!$I$2:$I$616,0)),"")) | O200: =IF(M200="","",IFERROR(INDEX(BDD_Calendrier!$H$2:$H$616,MATCH($B200&"|Rachat|"&TEXT(M200,"yyyy-mm-dd"),BDD_Calendrier!$I$2:$I$616,0)),"")) | P200: =IF(L200=0,"",_xlfn.MAXIFS(BDD_Calendrier!$D$2:$D$616,BDD_Calendrier!$A$2:$A$616,$B200,BDD_Calendrier!$C$2:$C$616,"Rachat")) | Q200: =IF($C200="","",IF($C200>TODAY(),"FUTUR",DATEDIF($C200,TODAY(),"m"))) | R200: =COUNTIF(BDD_Penalites!$A$2:$A$130,$B200) | S200: =IF(R200=0,"inconnue",INDEX(BDD_Penalites!$C$2:$C$130,MATCH($B200,BDD_Penalites!$A$2:$A$130,0))) | T200: =IF(R200=0,"",INDEX(BDD_Penalites!$M$2:$M$130,MATCH($B200,BDD_Penalites!$A$2:$A$130,0))) | U200: =IF(R200=0,0,INDEX(BDD_Penalites!$D$2:$D$130,MATCH($B200,BDD_Penalites!$A$2:$A$130,0))) | V200: =IF(R200=0,0,INDEX(BDD_Penalites!$E$2:$E$130,MATCH($B200,BDD_Penalites!$A$2:$A$130,0))) | W200: =IF(R200=0,0,INDEX(BDD_Penalites!$F$2:$F$130,MATCH($B200,BDD_Penalites!$A$2:$A$130,0))) | X200: =IF(R200=0,0,INDEX(BDD_Penalites!$G$2:$G$130,MATCH($B200,BDD_Penalites!$A$2:$A$130,0))) | Y200: =IF(R200=0,0,INDEX(BDD_Penalites!$H$2:$H$130,MATCH($B200,BDD_Penalites!$A$2:$A$130,0))) | Z200: =IF(R200=0,0,INDEX(BDD_Penalites!$I$2:$I$130,MATCH($B200,BDD_Penalites!$A$2:$A$130,0))) | AA200: =IF(R200=0,0,INDEX(BDD_Penalites!$J$2:$J$130,MATCH($B200,BDD_Penalites!$A$2:$A$130,0))) | AB200: =IF(R200=0,0,INDEX(BDD_Penalites!$K$2:$K$130,MATCH($B200,BDD_Penalites!$A$2:$A$130,0))) | AC200: =IF(R200=0,0,INDEX(BDD_Penalites!$L$2:$L$130,MATCH($B200,BDD_Penalites!$A$2:$A$130,0))) | AD200: =IF(OR($C200="",Q200="FUTUR"),"",_xlfn.IFS(Q200<U200,V200,Q200<W200,X200,Q200<Y200,Z200,Q200<AA200,AB200,TRUE,AC200))
A201: Blackstone Crédit Privé Europe SC | B201: FR001400L0X2 | D201: =IF(H201=0,"Calendrier non disponible pour ce fonds — contacter la société de gestion.",IF(I201="","Calendrier connu jusqu'au "&TEXT(K201,"dd/mm/yyyy")&" — demander le calendrier à jour.","Cut-off : "&TEXT(I201,"dd/mm/yyyy")&" | VL : "&TEXT(J201,"dd/mm/yyyy"))) | E201: =IF(L201=0,"Calendrier non disponible pour ce fonds — contacter la société de gestion.",IF(M201="","Calendrier connu jusqu'au "&TEXT(P201,"dd/mm/yyyy")&" — demander le calendrier à jour.","Cut-off : "&TEXT(M201,"dd/mm/yyyy")&" | VL : "&TEXT(N201,"dd/mm/yyyy"))) | F201: =IF(L201=0,"Calendrier non disponible pour ce fonds.",IF(M201="","Calendrier connu jusqu'au "&TEXT(P201,"dd/mm/yyyy")&".",IF(O201="","Non précisé dans le calendrier pour cette échéance.","Réception : "&TEXT(O201,"dd/mm/yyyy")&" (suite au rachat du "&TEXT(N201,"dd/mm/yyyy")&")"))) | G201: =_xlfn.IFS(S201="aucune","Aucune pénalité de sortie."&IF(T201<>""," ("&T201&")",""),S201="manuel","⚠️ À VÉRIFIER MANUELLEMENT : "&T201,S201="inconnue","Pénalité non renseignée — vérifier la notice / DICI du fonds.",$C201="","Saisir une date d'investissement pour statuer sur la pénalité.",Q201="FUTUR","Date d'investissement postérieure à aujourd'hui — vérifier la saisie.",AD201>0,"⚠️ CONCERNÉ : pénalité de "&AD201&"% (détention "&Q201&" mois). "&T201,TRUE,"Non concerné (détention "&Q201&" mois). "&T201) | H201: =COUNTIFS(BDD_Calendrier!$A$2:$A$616,$B201,BDD_Calendrier!$C$2:$C$616,"Souscription") | I201: =IF(H201=0,"",IFERROR(_xlfn.MINIFS(BDD_Calendrier!$D$2:$D$616,BDD_Calendrier!$A$2:$A$616,$B201,BDD_Calendrier!$C$2:$C$616,"Souscription",BDD_Calendrier!$D$2:$D$616,">="&TODAY()),"")) | J201: =IF(I201="","",IFERROR(INDEX(BDD_Calendrier!$E$2:$E$616,MATCH($B201&"|Souscription|"&TEXT(I201,"yyyy-mm-dd"),BDD_Calendrier!$I$2:$I$616,0)),"")) | K201: =IF(H201=0,"",_xlfn.MAXIFS(BDD_Calendrier!$D$2:$D$616,BDD_Calendrier!$A$2:$A$616,$B201,BDD_Calendrier!$C$2:$C$616,"Souscription")) | L201: =COUNTIFS(BDD_Calendrier!$A$2:$A$616,$B201,BDD_Calendrier!$C$2:$C$616,"Rachat") | M201: =IF(L201=0,"",IFERROR(_xlfn.MINIFS(BDD_Calendrier!$D$2:$D$616,BDD_Calendrier!$A$2:$A$616,$B201,BDD_Calendrier!$C$2:$C$616,"Rachat",BDD_Calendrier!$D$2:$D$616,">="&TODAY()),"")) | N201: =IF(M201="","",IFERROR(INDEX(BDD_Calendrier!$E$2:$E$616,MATCH($B201&"|Rachat|"&TEXT(M201,"yyyy-mm-dd"),BDD_Calendrier!$I$2:$I$616,0)),"")) | O201: =IF(M201="","",IFERROR(INDEX(BDD_Calendrier!$H$2:$H$616,MATCH($B201&"|Rachat|"&TEXT(M201,"yyyy-mm-dd"),BDD_Calendrier!$I$2:$I$616,0)),"")) | P201: =IF(L201=0,"",_xlfn.MAXIFS(BDD_Calendrier!$D$2:$D$616,BDD_Calendrier!$A$2:$A$616,$B201,BDD_Calendrier!$C$2:$C$616,"Rachat")) | Q201: =IF($C201="","",IF($C201>TODAY(),"FUTUR",DATEDIF($C201,TODAY(),"m"))) | R201: =COUNTIF(BDD_Penalites!$A$2:$A$130,$B201) | S201: =IF(R201=0,"inconnue",INDEX(BDD_Penalites!$C$2:$C$130,MATCH($B201,BDD_Penalites!$A$2:$A$130,0))) | T201: =IF(R201=0,"",INDEX(BDD_Penalites!$M$2:$M$130,MATCH($B201,BDD_Penalites!$A$2:$A$130,0))) | U201: =IF(R201=0,0,INDEX(BDD_Penalites!$D$2:$D$130,MATCH($B201,BDD_Penalites!$A$2:$A$130,0))) | V201: =IF(R201=0,0,INDEX(BDD_Penalites!$E$2:$E$130,MATCH($B201,BDD_Penalites!$A$2:$A$130,0))) | W201: =IF(R201=0,0,INDEX(BDD_Penalites!$F$2:$F$130,MATCH($B201,BDD_Penalites!$A$2:$A$130,0))) | X201: =IF(R201=0,0,INDEX(BDD_Penalites!$G$2:$G$130,MATCH($B201,BDD_Penalites!$A$2:$A$130,0))) | Y201: =IF(R201=0,0,INDEX(BDD_Penalites!$H$2:$H$130,MATCH($B201,BDD_Penalites!$A$2:$A$130,0))) | Z201: =IF(R201=0,0,INDEX(BDD_Penalites!$I$2:$I$130,MATCH($B201,BDD_Penalites!$A$2:$A$130,0))) | AA201: =IF(R201=0,0,INDEX(BDD_Penalites!$J$2:$J$130,MATCH($B201,BDD_Penalites!$A$2:$A$130,0))) | AB201: =IF(R201=0,0,INDEX(BDD_Penalites!$K$2:$K$130,MATCH($B201,BDD_Penalites!$A$2:$A$130,0))) | AC201: =IF(R201=0,0,INDEX(BDD_Penalites!$L$2:$L$130,MATCH($B201,BDD_Penalites!$A$2:$A$130,0))) | AD201: =IF(OR($C201="",Q201="FUTUR"),"",_xlfn.IFS(Q201<U201,V201,Q201<W201,X201,Q201<Y201,Z201,Q201<AA201,AB201,TRUE,AC201))
